Workbook

Sheet Summary
A1: Metric | B1: Value
A2: Total Pokémon | B2: 1025
A3: Number of Game Titles (columns per section) | B3: 45
A4: Game Titles (chronological) | B4: Red, Blue, Yellow, Gold, Silver, Crystal, Ruby, Sapphire, Emerald, FireRed, LeafGreen, Diamond, Pearl, Platinum, HeartGold, SoulSilver, Black, White, Black 2, White 2, X, Y, Omega Ruby, Alpha Sapphire, Sun, Moon, Ultra Sun, Ultra Moon, Let's Go Pikachu, Let's Go Eevee, Sword, Shield, The Isle of Armor, The Crown Tundra, Brilliant Diamond, Shining Pearl, Legends: Arceus, Scarlet, Violet, The Teal Mask, The Indigo Disk, Legends: Z-A, Legends: Z, U.Moon, U.Sun
A5: Columns (base) | B5: 27
A6: Columns (Local #) | B6: 45
A7: Columns (Dex Text) | B7: 45
A8: Columns (Where to Find) | B8: 45
A9: Total Columns | B9: 162

Sheet MasterDex
Y1: Base Stats | AG1: =image("https://img.pokemondb.net/boxes/avif/"&lower(AG2)&".avif") | AH1: =image("https://img.pokemondb.net/boxes/avif/"&lower(AH2)&".avif") | AI1: =image("https://img.pokemondb.net/boxes/avif/"&lower(AI2)&".avif") | AJ1: =image("https://img.pokemondb.net/boxes/avif/"&lower(AJ2)&".avif") | AK1: =image("https://img.pokemondb.net/boxes/avif/"&lower(AK2)&".avif") | AL1: =image("https://img.pokemondb.net/boxes/avif/"&lower(AL2)&".avif") | AM1: =image("https://img.pokemondb.net/boxes/avif/"&lower(AM2)&".avif") | AN1: =image("https://img.pokemondb.net/boxes/avif/"&lower(AN2)&".avif") | ... BH1: =image("https://img.pokemondb.net/boxes/avif/"&lower(BH2)&".avif") | BI1: =image("https://img.pokemondb.net/boxes/lg/"&lower(BI2)&"-large.jpg") | BJ1: =image("https://img.pokemondb.net/boxes/lg/"&lower(BJ2)&"-large.jpg") | BK1: =image("https://img.pokemondb.net/boxes/lg/"&lower(BK2)&"-large.jpg") | BL1: =image("https://img.pokemondb.net/boxes/lg/"&lower(BL2)&"-large.jpg") | BM1: =image("https://assets-prd.ignimgs.com/2020/06/23/pokemon-sword-shield-dlc-the-isle-of-armor-button-00-1592945233643.jpg?crop=1%3A1%2Csmart&format=jpg&auto=webp&quality=80") | BN1: =image("https://assets-prd.ignimgs.com/2020/06/23/pokemon-sword-shield-dlc-the-crown-tundra-button-00-1592945232346.jpg?crop=1%3A1%2Csmart&format=jpg&auto=webp&quality=80") | BO1: =image("https://img.pokemondb.net/boxes/lg/"&lower(BO2)&"-large.jpg") | BP1: =image("https://img.pokemondb.net/boxes/lg/"&lower(BP2)&"-large.jpg") | BQ1: =image("https://img.pokemondb.net/boxes/lg/"&lower(BQ2)&"-large.jpg") | BR1: =image("https://img.pokemondb.net/boxes/lg/"&lower(BR2)&"-large.jpg") | BS1: =image("https://img.pokemondb.net/boxes/lg/"&lower(BS2)&"-large.jpg") | BT1: =image("https://archives.bulbagarden.net/media/upload/thumb/e/ea/SV_eShop_Part_1_The_Teal_Mask.jpg/250px-SV_eShop_Part_1_The_Teal_Mask.jpg") | BU1: =image("https://pokemongohub.net/wp-content/uploads/2023/12/the-indigo-disk.jpg") | BV1: =image("https://archives.bulbagarden.net/media/upload/thumb/b/bd/Legends_Z-A_Nintendo_Switch_2_Edition_EN_boxart.png/250px-Legends_Z-A_Nintendo_Switch_2_Edition_EN_boxart.png")
A2: ref_id | B2: National Dex Number | C2: Name | D2: Sprite | E2: Shiny | F2: Type 1 | G2: Type 2 | H2: Type 1 Helper | I2: Type 2 Helper | J2: Species | K2: Height | L2: Weight | M2: Ability 1 | N2: Ability 2 | O2: Hidden Ability | P2: EV Yield | Q2: Catch Rate | R2: Base Friendship | S2: Base EXP | T2: Growth Rate | U2: Egg Group 1 | V2: Egg Group 2 | W2: Gender Ratio | X2: Egg Cycles | Y2: HP | Z2: Attack | AA2: Defense | AB2: Sp. Atk | AC2: Sp. Def | AD2: Speed | AE2: Total | AF2: Evolution Chain | AG2: Red | AH2: Blue | AI2: Yellow | AJ2: Gold | AK2: Silver | AL2: Crystal | AM2: Ruby | AN2: Sapphire | AO2: Emerald | AP2: FireRed | AQ2: LeafGreen | AR2: Diamond | AS2: Pearl | AT2: Platinum | AU2: HeartGold | AV2: SoulSilver | AW2: Black | AX2: White | AY2: Black-2 | AZ2: White-2 | BA2: X | BB2: Y | BC2: Omega-Ruby | BD2: Alpha-Sapphire | BE2: Sun | BF2: Moon | BG2: Ultra-Sun | BH2: Ultra-Moon | BI2: Lets-Go-Pikachu | BJ2: Lets-Go-Eevee | BK2: Sword | BL2: Shield | BM2: The-Isle-Of-Armor | BN2: The Crown Tundra | BO2: Brilliant-Diamond | BP2: Shining-Pearl | BQ2: Legends-Arceus | BR2: Scarlet | BS2: Violet | BT2: The-Teal-Mask | BU2: The-Indigo-Disk | BV2: Legends-Z-A | BW2: Red Dex Text | BX2: Blue Dex Text | BY2: Yellow Dex Text | BZ2: Gold Dex Text | CA2: Silver Dex Text | CB2: Crystal Dex Text | CC2: Ruby Dex Text | CD2: Sapphire Dex Text | CE2: Emerald Dex Text | CF2: FireRed Dex Text | CG2: LeafGreen Dex Text | CH2: Diamond Dex Text | CI2: Pearl Dex Text | CJ2: Platinum Dex Text | CK2: HeartGold Dex Text | CL2: SoulSilver Dex Text | CM2: Black Dex Text | CN2: White Dex Text | CO2: Black 2 Dex Text | CP2: White 2 Dex Text | CQ2: X Dex Text | CR2: Y Dex Text | CS2: Omega Ruby Dex Text | CT2: Alpha Sapphire Dex Text | CU2: Sun Dex Text | CV2: Moon Dex Text | CW2: Ultra Sun Dex Text | CX2: Ultra Moon Dex Text | CY2: Let's Go Pikachu Dex Text | CZ2: Let's Go Eevee Dex Text | DA2: Sword Dex Text | DB2: Shield Dex Text | DC2: The Isle of Armor Dex Text | DD2: The Crown Tundra Dex Text | DE2: Brilliant Diamond Dex Text | DF2: Shining Pearl Dex Text | DG2: Legends: Arceus Dex Text | DH2: Scarlet Dex Text | DI2: Violet Dex Text | DJ2: The Teal Mask Dex Text | DK2: The Indigo Disk Dex Text | DL2: Legends: Z-A Dex Text | DM2: Legends: Z Dex Text | DN2: U.Moon Dex Text | DO2: U.Sun Dex Text | DP2: Red Location | DQ2: Blue Location | DR2: Yellow Location | DS2: Gold Location | DT2: Silver Location | DU2: Crystal Location | DV2: Ruby Location | DW2: Sapphire Location | DX2: Emerald Location | DY2: FireRed Location | DZ2: LeafGreen Location | EA2: Diamond Location | EB2: Pearl Location | EC2: Platinum Location | ED2: HeartGold Location | EE2: SoulSilver Location | EF2: Black Location | EG2: White Location | EH2: Black 2 Location | EI2: White 2 Location | EJ2: X Location | EK2: Y Location | EL2: Omega Ruby Location | EM2: Alpha Sapphire Location | EN2: Sun Location | EO2: Moon Location | EP2: Ultra Sun Location | EQ2: Ultra Moon Location | ER2: Let's Go Pikachu Location | ES2: Let's Go Eevee Location | ET2: Sword Location | EU2: Shield Location | EV2: The Isle of Armor Location | EW2: The Crown Tundra Location | EX2: Brilliant Diamond Location | EY2: Shining Pearl Location | EZ2: Legends: Arceus Location | FA2: Scarlet Location | FB2: Violet Location | FC2: The Teal Mask Location | FD2: The Indigo Disk Location | FE2: Legends: Z-A Location
A3: 0001-00 | B3: 1 | C3: Bulbasaur | D3: =image("https://img.pokemondb.net/sprites/home/normal/"& lower(C3) &".png") | E3: =image("https://img.pokemondb.net/sprites/home/shiny/"& lower(C3) &".png") | F3: =image("https://www.serebii.net/pokedex-bw/type/"&lower(H3)&".gif") | G3: =image("https://www.serebii.net/pokedex-bw/type/"&lower(I3)&".gif") | H3: Grass | I3: Poison | J3: Seed Pokémon | K3: 0.7 m (2′04″) | L3: 6.9 kg (15.2 lbs) | M3: Overgrow | O3: Chlorophyll | P3: 1 Sp. Atk | Q3: 45 (5.9% with PokéBall, full HP) | R3: 50 (normal) | S3: 64 | T3: Medium Slow | U3: Grass | V3: Monster | W3: 87.5% male, 12.5% female | X3: 20 (4,884–5,140 steps) | Y3: 45 | Z3: 49 | AA3: 49 | AB3: 65 | AC3: 65 | AD3: 45 | AE3: =sum(Y3:AD3) -> 318 | AF3: Bulbasaur → Ivysaur (Level 16) → Venusaur (Level 32) | AG3: 0001 | AH3: 0001 | AI3: 0001 | AJ3: 0226 | AK3: 0226 | AL3: 0226 | AP3: 0001 | AQ3: 0001 | AU3: 0231 | AV3: 0231 | BA3: 0080 | BB3: 0080 | BI3: 0001 | BJ3: 0001 | BM3: 0068 | BU3: 0164 | BV3: 0148 | BW3: A strange seed was planted on its back at birth. The plant sprouts and grows with this POKéMON. | BX3: A strange seed was planted on its back at birth. The plant sprouts and grows with this POKéMON. | BY3: It can go for days without eating a single morsel. In the bulb on its back, it stores energy. | BZ3: The seed on its back is filled with nutrients. The seed grows steadily larger as its body grows. | CA3: It carries a seed on its back right from birth. As it grows older, the seed also grows larger. | CB3: While it is young, it uses the nutrients that are stored in the seeds on its back in order to grow. | CC3: BULBASAUR can be seen napping in bright sunlight. There is a seed on its back. By soaking up the sun’s rays, the seed grows progressively larger. | CD3: BULBASAUR can be seen napping in bright sunlight. There is a seed on its back. By soaking up the sun’s rays, the seed grows progressively larger. | CE3: BULBASAUR can be seen napping in bright sunlight. There is a seed on its back. By soaking up the sun’s rays, the seed grows progressively larger. | CF3: There is a plant seed on its back right from the day this POKéMON is born. The seed slowly grows larger. | CG3: A strange seed was planted on its back at birth. The plant sprouts and grows with this POKéMON. | CH3: For some time after its birth, it grows by gaining nourishment from the seed on its back. | CI3: For some time after its birth, it grows by gaining nourishment from the seed on its back. | CJ3: For some time after its birth, it grows by gaining nourishment from the seed on its back. | CK3: The seed on its back is filled with nutrients. The seed grows steadily larger as its body grows. | CL3: It carries a seed on its back right from birth. As it grows older, the seed also grows larger. | CM3: For some time after its birth, it grows by gaining nourishment from the seed on its back. | CN3: For some time after its birth, it grows by gaining nourishment from the seed on its back. | CO3: For some time after its birth, it grows by gaining nourishment from the seed on its back. | CP3: For some time after its birth, it grows by gaining nourishment from the seed on its back. | CQ3: A strange seed was planted on its back at birth. The plant sprouts and grows with this Pokémon. | CR3: For some time after its birth, it grows by gaining nourishment from the seed on its back. | CS3: Bulbasaur can be seen napping in bright sunlight. There is a seed on its back. By soaking up the sun’s rays, the seed grows progressively larger. | CT3: Bulbasaur can be seen napping in bright sunlight. There is a seed on its back. By soaking up the sun’s rays, the seed grows progressively larger. | CY3: It can go for days without eating a single morsel. In the bulb on its back, it stores energy. | CZ3: It can go for days without eating a single morsel. In the bulb on its back, it stores energy. | DA3: There is a plant seed on its back right from the day this Pokémon is born. The seed slowly grows larger. | DB3: While it is young, it uses the nutrients that are stored in the seed on its back in order to grow. | DE3: For some time after its birth, it grows by taking nourishment from the seed on its back. | DF3: For some time after its birth, it grows by taking nourishment from the seed on its back. | DP3: Pallet Town | DQ3: Pallet Town | DR3: Cerulean City | DS3: Trade/migrate from another game | DT3: Trade/migrate from another game | DU3: Trade/migrate from another game | DV3: Trade/migrate from another game | DW3: Trade/migrate from another game | DX3: Trade/migrate from another game | DY3: Pallet Town | DZ3: Pallet Town | EA3: Trade/migrate from another game | EB3: Trade/migrate from another game | EC3: Trade/migrate from another game | ED3: Pallet Town | EE3: Pallet Town | EF3: Trade/migrate from another game | EG3: Trade/migrate from another game | EH3: Trade/migrate from another game | EI3: Trade/migrate from another game | EJ3: Lumiose City | EK3: Lumiose City | EL3: Trade/migrate from another game | EM3: Trade/migrate from another game | EN3: Trade/migrate from another game | EO3: Trade/migrate from another game | EP3: Route 2 | EQ3: Route 2 | ER3: Cerulean City , Viridian Forest | ES3: Cerulean City , Viridian Forest | ET3: Trade/migrate from another game | EU3: Trade/migrate from another game | EX3: Grassland Cave , Swampy Cave , Riverbank Cave , Still-Water Cavern , Sunlit Cavern , Bogsunk Cavern | EY3: Grassland Cave , Swampy Cave , Riverbank Cave , Still-Water Cavern , Sunlit Cavern , Bogsunk Cavern | EZ3: Not available in this game | FA3: Location data not yet available | FB3: Location data not yet available | FE3: Location data not yet available
A4: 0002-00 | B4: 2 | C4: Ivysaur | D4: =image("https://img.pokemondb.net/sprites/home/normal/"& lower(C4) &".png") | E4: =image("https://img.pokemondb.net/sprites/home/shiny/"& lower(C4) &".png") | F4: =image("https://www.serebii.net/pokedex-bw/type/"&lower(H4)&".gif") | G4: =image("https://www.serebii.net/pokedex-bw/type/"&lower(I4)&".gif") | H4: Grass | I4: Poison | J4: Seed Pokémon | K4: 1.0 m (3′03″) | L4: 13.0 kg (28.7 lbs) | M4: Overgrow | O4: Chlorophyll | P4: 1 Sp. Atk, 1 Sp. Def | Q4: 45 (5.9% with PokéBall, full HP) | R4: 50 (normal) | S4: 142 | T4: Medium Slow | U4: Grass | V4: Monster | W4: 87.5% male, 12.5% female | X4: 20 (4,884–5,140 steps) | Y4: 60 | Z4: 62 | AA4: 63 | AB4: 80 | AC4: 80 | AD4: 60 | AE4: =sum(Y4:AD4) -> 405 | AF4: Bulbasaur → Ivysaur (Level 16) → Venusaur (Level 32) | AG4: 0002 | AH4: 0002 | AI4: 0002 | AJ4: 0227 | AK4: 0227 | AL4: 0227 | AP4: 0002 | AQ4: 0002 | AU4: 0232 | AV4: 0232 | BA4: 0081 | BB4: 0081 | BI4: 0002 | BJ4: 0002 | BM4: 0069 | BU4: 0165 | BV4: 0149 | BW4: When the bulb on its back grows large, it appears to lose the ability to stand on its hind legs. | BX4: When the bulb on its back grows large, it appears to lose the ability to stand on its hind legs. | BY4: The bulb on its back grows by drawing energy. It gives off an aroma when it is ready to bloom. | BZ4: Exposure to sunlight adds to its strength. Sunlight also makes the bud on its back grow larger. | CA4: If the bud on its back starts to smell sweet, it is evidence that the large flower will soon bloom. | CB4: The bulb on its back grows as it absorbs nutrients. The bulb gives off a pleasant aroma when it blooms. | CC4: There is a bud on this POKéMON’s back. To support its weight, IVYSAUR’s legs and trunk grow thick and strong. If it starts spending more time lying in the sunlight, it’s a sign that the bud will bloom into a large flower soon. | CD4: There is a bud on this POKéMON’s back. To support its weight, IVYSAUR’s legs and trunk grow thick and strong. If it starts spending more time lying in the sunlight, it’s a sign that the bud will bloom into a large flower soon. | CE4: To support its bulb, IVYSAUR’s legs grow sturdy. If it spends more time lying in the sunlight, the bud will soon bloom into a large flower. | CF4: There is a plant bulb on its back. When it absorbs nutrients, the bulb is said to blossom into a large flower. | CG4: When the bulb on its back grows large, it appears to lose the ability to stand on its hind legs. | CH4: When the bud on its back starts swelling, a sweet aroma wafts to indicate the flower’s coming bloom. | CI4: When the bud on its back starts swelling, a sweet aroma wafts to indicate the flower’s coming bloom. | CJ4: When the bud on its back starts swelling, a sweet aroma wafts to indicate the flower’s coming bloom. | CK4: Exposure to sunlight adds to its strength. Sunlight also makes the bud on its back grow larger. | CL4: If the bud on its back starts to smell sweet, it is evidence that the large flower will soon bloom. | CM4: When the bud on its back starts swelling, a sweet aroma wafts to indicate the flower’s coming bloom. | CN4: When the bud on its back starts swelling, a sweet aroma wafts to indicate the flower’s coming bloom. | CO4: When the bud on its back starts swelling, a sweet aroma wafts to indicate the flower’s coming bloom. | CP4: When the bud on its back starts swelling, a sweet aroma wafts to indicate the flower’s coming bloom. | CQ4: There is a plant bulb on its back. When it absorbs nutrients, the bulb is said to blossom into a large flower. | CR4: When the bud on its back starts swelling, a sweet aroma wafts to indicate the flower’s coming bloom. | CS4: There is a bud on this Pokémon’s back. To support its weight, Ivysaur’s legs and trunk grow thick and strong. If it starts spending more time lying in the sunlight, it’s a sign that the bud will bloom into a large flower soon. | CT4: There is a bud on this Pokémon’s back. To support its weight, Ivysaur’s legs and trunk grow thick and strong. If it starts spending more time lying in the sunlight, it’s a sign that the bud will bloom into a large flower soon. | CY4: The bud on its back grows by drawing energy. It gives off an aroma when it is ready to bloom. | CZ4: The bud on its back grows by drawing energy. It gives off an aroma when it is ready to bloom. | DA4: When the bulb on its back grows large, it appears to lose the ability to stand on its hind legs. | DB4: Exposure to sunlight adds to its strength. Sunlight also makes the bud on its back grow larger. | DE4: When the bud on its back starts swelling, a sweet aroma wafts to indicate the flower’s coming bloom. | DF4: When the bud on its back starts swelling, a sweet aroma wafts to indicate the flower’s coming bloom. | DP4: Evolve Bulbasaur | DQ4: Evolve Bulbasaur | DR4: Evolve Bulbasaur | DS4: Trade/migrate from another game | DT4: Trade/migrate from another game | DU4: Trade/migrate from another game | DV4: Trade/migrate from another game | DW4: Trade/migrate from another game | DX4: Trade/migrate from another game | DY4: Evolve Bulbasaur | DZ4: Evolve Bulbasaur | EA4: Trade/migrate from another game | EB4: Trade/migrate from another game | EC4: Trade/migrate from another game | ED4: Evolve Bulbasaur | EE4: Evolve Bulbasaur | EF4: Trade/migrate from another game | EG4: Trade/migrate from another game | EH4: Trade/migrate from another game | EI4: Trade/migrate from another game | EJ4: Evolve Bulbasaur | EK4: Evolve Bulbasaur | EL4: Trade/migrate from another game | EM4: Trade/migrate from another game | EN4: Trade/migrate from another game | EO4: Trade/migrate from another game | EP4: Evolve Bulbasaur | EQ4: Evolve Bulbasaur | ER4: Evolve Bulbasaur | ES4: Evolve Bulbasaur | ET4: Trade/migrate from another game | EU4: Trade/migrate from another game | EX4: Evolve Bulbasaur | EY4: Evolve Bulbasaur | EZ4: Not available in this game | FA4: Location data not yet available | FB4: Location data not yet available | FE4: Location data not yet available
A5: 0003-00 | B5: 3 | C5: Venusaur | D5: =image("https://img.pokemondb.net/sprites/home/normal/"& lower(C5) &".png") | E5: =image("https://img.pokemondb.net/sprites/home/shiny/"& lower(C5) &".png") | F5: =image("https://www.serebii.net/pokedex-bw/type/"&lower(H5)&".gif") | G5: =image("https://www.serebii.net/pokedex-bw/type/"&lower(I5)&".gif") | H5: Grass | I5: Poison | J5: Seed Pokémon | K5: 2.0 m (6′07″) | L5: 100.0 kg (220.5 lbs) | M5: Overgrow | O5: Chlorophyll | P5: 2 Sp. Atk, 1 Sp. Def | Q5: 45 (5.9% with PokéBall, full HP) | R5: 50 (normal) | S5: 236 | T5: Medium Slow | U5: Grass | V5: Monster | W5: 87.5% male, 12.5% female | X5: 20 (4,884–5,140 steps) | Y5: 80 | Z5: 82 | AA5: 83 | AB5: 100 | AC5: 100 | AD5: 80 | AE5: =sum(Y5:AD5) -> 525 | AF5: Bulbasaur → Ivysaur (Level 16) → Venusaur (Level 32) | AG5: 0003 | AH5: 0003 | AI5: 0003 | AJ5: 0228 | AK5: 0228 | AL5: 0228 | AP5: 0003 | AQ5: 0003 | AU5: 0233 | AV5: 0233 | BA5: 0082 | BB5: 0082 | BI5: 0003 | BJ5: 0003 | BM5: 0070 | BU5: 0166 | BV5: 0150 | BW5: The plant blooms when it is absorbing solar energy. It stays on the move to seek sunlight. | BX5: The plant blooms when it is absorbing solar energy. It stays on the move to seek sunlight. | BY5: The flower on its back catches the sun’s rays. The sunlight is then absorbed and used for energy. | BZ5: By spreading the broad petals of its flower and catching the sun’s rays, it fills its body with power. | CA5: It is able to convert sunlight into energy. As a result, it is more powerful in the summertime. | CB5: As it warms itself and absorbs the sunlight, its flower petals release a pleasant fragrance. | CC5: There is a large flower on VENUSAUR’s back. The flower is said to take on vivid colors if it gets plenty of nutrition and sunlight. The flower’s aroma soothes the emotions of people. | CD5: There is a large flower on VENUSAUR’s back. The flower is said to take on vivid colors if it gets plenty of nutrition and sunlight. The flower’s aroma soothes the emotions of people. | CE5: VENUSAUR’s flower is said to take on vivid colors if it gets plenty of nutrition and sunlight. The flower’s aroma soothes the emotions of people. | CF5: A bewitching aroma wafts from its flower. The fragrance becalms those engaged in a battle. | CG5: Its plant blooms when it is absorbing solar energy. It stays on the move to seek sunlight. | CH5: After a rainy day, the flower on its back smells stronger. The scent attracts other Pokémon. | CI5: After a rainy day, the flower on its back smells stronger. The scent attracts other Pokémon. | CJ5: After a rainy day, the flower on its back smells stronger. The scent attracts other Pokémon. | CK5: By spreading the broad petals of its flower and catching the sun’s rays, it fills its body with power. | CL5: It is able to convert sunlight into energy. As a result, it is more powerful in the summertime. | CM5: After a rainy day, the flower on its back smells stronger. The scent attracts other Pokémon. | CN5: After a rainy day, the flower on its back smells stronger. The scent attracts other Pokémon. | CO5: After a rainy day, the flower on its back smells stronger. The scent attracts other Pokémon. | CP5: After a rainy day, the flower on its back smells stronger. The scent attracts other Pokémon. | CQ5: By spreading the broad petals of its flower and catching the sun’s rays, it fills its body with power. | CR5: After a rainy day, the flower on its back smells stronger. The scent attracts other Pokémon. | CS5: There is a large flower on Venusaur’s back. The flower is said to take on vivid colors if it gets plenty of nutrition and sunlight. The flower’s aroma soothes the emotions of people. | CT5: There is a large flower on Venusaur’s back. The flower is said to take on vivid colors if it gets plenty of nutrition and sunlight. The flower’s aroma soothes the emotions of people. | CY5: The flower on its back catches the sun’s rays. The sunlight is then absorbed and used for energy. | CZ5: The flower on its back catches the sun’s rays. The sunlight is then absorbed and used for energy. | DA5: Its plant blooms when it is absorbing solar energy. It stays on the move to seek sunlight. | DB5: A bewitching aroma wafts from its flower. The fragrance becalms those engaged in a battle. | DE5: After a rainy day, the flower on its back smells stronger. The scent attracts other Pokémon. | DF5: After a rainy day, the flower on its back smells stronger. The scent attracts other Pokémon. | DP5: Evolve Bulbasaur / Ivysaur | DQ5: Evolve Bulbasaur / Ivysaur | DR5: Evolve Bulbasaur / Ivysaur | DS5: Trade/migrate from another game | DT5: Trade/migrate from another game | DU5: Trade/migrate from another game | DV5: Trade/migrate from another game | DW5: Trade/migrate from another game | DX5: Trade/migrate from another game | DY5: Evolve Bulbasaur / Ivysaur | DZ5: Evolve Bulbasaur / Ivysaur | EA5: Trade/migrate from another game | EB5: Trade/migrate from another game | EC5: Trade/migrate from another game | ED5: Evolve Bulbasaur / Ivysaur | EE5: Evolve Bulbasaur / Ivysaur | EF5: Trade/migrate from another game | EG5: Trade/migrate from another game | EH5: Trade/migrate from another game | EI5: Trade/migrate from another game | EJ5: Evolve Bulbasaur / Ivysaur | EK5: Evolve Bulbasaur / Ivysaur | EL5: Trade/migrate from another game | EM5: Trade/migrate from another game | EN5: Trade/migrate from another game | EO5: Trade/migrate from another game | EP5: Evolve Bulbasaur / Ivysaur | EQ5: Evolve Bulbasaur / Ivysaur | ER5: Evolve Bulbasaur / Ivysaur | ES5: Evolve Bulbasaur / Ivysaur | ET5: Trade/migrate from another game | EU5: Trade/migrate from another game | EX5: Evolve Bulbasaur / Ivysaur | EY5: Evolve Bulbasaur / Ivysaur | EZ5: Not available in this game | FA5: Location data not yet available | FB5: Location data not yet available | FE5: Location data not yet available
A6: 0003-01 | B6: 3 | C6: Mega Venusaur | D6: =Sprite_Data!F2 | E6: =Sprite_Data!G2 | F6: =image("https://www.serebii.net/pokedex-bw/type/"&lower(H6)&".gif") | G6: =image("https://www.serebii.net/pokedex-bw/type/"&lower(I6)&".gif") | H6: Grass | I6: Poison | J6: Seed Pokémon | K6: 2.0 m (6′07″) | L6: 100.0 kg (220.5 lbs) | M6: Thick Fat | P6: 3 Sp. Atk, 1 Sp. Def | Q6: 46 (5.9% with PokéBall, full HP) | R6: 51 (normal) | S6: 281 | T6: Medium Slow | U6: Grass | V6: Monster | W6: 87.5% male, 12.5% female | X6: 21 (4,884–5,140 steps) | Y6: 80 | Z6: 100 | AA6: 123 | AB6: 122 | AC6: 120 | AD6: 80 | AE6: =sum(Y6:AD6) -> 625 | AF6: Venusaurite | AG6: 0004 | AH6: 0004 | AI6: 0004 | AJ6: 0229 | AK6: 0229 | AL6: 0229 | AP6: 0004 | AQ6: 0004 | AU6: 0234 | AV6: 0234 | BA6: 0083 | BB6: 0083 | BI6: 0004 | BJ6: 0004 | BM6: 0071 | BU6: 0167 | BV6: 0151
A7: 0003-02 | B7: 3 | C7: Venusaur Gigantamax | D7: =Sprite_Data!J2 | E7: =Sprite_Data!K2 | F7: =image("https://www.serebii.net/pokedex-bw/type/"&lower(H7)&".gif") | G7: =image("https://www.serebii.net/pokedex-bw/type/"&lower(I7)&".gif") | H7: Grass | I7: Poison | J7: Seed Pokémon | K7: 24.0 m (78'09") | M7: Overgrow | O7: Chlorophyll | AE7: =sum(Y7:AD7) -> 0 | AF7: Dynamax Band
A8: 0004-00 | B8: 4 | C8: Charmander | D8: =image("https://img.pokemondb.net/sprites/home/normal/"& lower(C8) &".png") | E8: =image("https://img.pokemondb.net/sprites/home/shiny/"& lower(C8) &".png") | F8: =image("https://www.serebii.net/pokedex-bw/type/"&lower(H8)&".gif") | G8: =image("https://www.serebii.net/pokedex-bw/type/"&lower(I8)&".gif") | H8: Fire | J8: Lizard Pokémon | K8: 0.6 m (2′00″) | L8: 8.5 kg (18.7 lbs) | M8: Blaze | O8: Solar Power | P8: 1 Speed | Q8: 45 (5.9% with PokéBall, full HP) | R8: 50 (normal) | S8: 62 | T8: Medium Slow | U8: Dragon | V8: Monster | W8: 87.5% male, 12.5% female | X8: 20 (4,884–5,140 steps) | Y8: 39 | Z8: 52 | AA8: 43 | AB8: 60 | AC8: 50 | AD8: 65 | AE8: =sum(Y8:AD8) -> 309 | AF8: Charmander → Charmeleon (Level 16) → Charizard (Level 36) | AG8: 0004 | AH8: 0004 | AI8: 0004 | AJ8: 0229 | AK8: 0229 | AL8: 0229 | AP8: 0004 | AQ8: 0004 | AU8: 0234 | AV8: 0234 | BA8: 0083 | BB8: 0083 | BI8: 0004 | BJ8: 0004 | BK8: 0378 | BL8: 0378 | BU8: 0167 | BV8: 0151 | BW8: Obviously prefers hot places. When it rains, steam is said to spout from the tip of its tail. | BX8: Obviously prefers hot places. When it rains, steam is said to spout from the tip of its tail. | BY8: The flame at the tip of its tail makes a sound as it burns. You can only hear it in quiet places. | BZ8: The flame on its tail shows the strength of its life force. If it is weak, the flame also burns weakly. | CA8: The flame on its tail indicates CHARMANDER’s life force. If it is healthy, the flame burns brightly. | CB8: If it’s healthy, the flame on the tip of its tail will burn vigorously, even if it gets a bit wet. | CC8: The flame that burns at the tip of its tail is an indication of its emotions. The flame wavers when CHARMANDER is enjoying itself. If the POKéMON becomes enraged, the flame burns fiercely. | CD8: The flame that burns at the tip of its tail is an indication of its emotions. The flame wavers when CHARMANDER is enjoying itself. If the POKéMON becomes enraged, the flame burns fiercely. | CE8: The flame that burns at the tip of its tail is an indication of its emotions. The flame wavers when CHARMANDER is happy, and blazes when it is enraged. | CF8: From the time it is born, a flame burns at the tip of its tail. Its life would end if the flame were to go out. | CG8: It has a preference for hot things. When it rains, steam is said to spout from the tip of its tail. | CH8: The fire on the tip of its tail is a measure of its life. If healthy, its tail burns intensely. | CI8: The fire on the tip of its tail is a measure of its life. If healthy, its tail burns intensely. | CJ8: The fire on the tip of its tail is a measure of its life. If healthy, its tail burns intensely. | CK8: The flame on its tail shows the strength of its life force. If it is weak, the flame also burns weakly. | CL8: The flame on its tail indicates CHARMANDER’s life force. If it is healthy, the flame burns brightly. | CM8: The fire on the tip of its tail is a measure of its life. If healthy, its tail burns intensely. | CN8: The fire on the tip of its tail is a measure of its life. If healthy, its tail burns intensely. | CO8: The fire on the tip of its tail is a measure of its life. If healthy, its tail burns intensely. | CP8: The fire on the tip of its tail is a measure of its life. If healthy, its tail burns intensely. | CQ8: The flame on its tail indicates Charmander’s life force. If it is healthy, the flame burns brightly. | CR8: From the time it is born, a flame burns at the tip of its tail. Its life would end if the flame were to go out. | CS8: The flame that burns at the tip of its tail is an indication of its emotions. The flame wavers when Charmander is enjoying itself. If the Pokémon becomes enraged, the flame burns fiercely. | CT8: The flame that burns at the tip of its tail is an indication of its emotions. The flame wavers when Charmander is enjoying itself. If the Pokémon becomes enraged, the flame burns fiercely. | CY8: The flame at the tip of its tail makes a sound as it burns. You can only hear it in quiet places. | CZ8: The flame at the tip of its tail makes a sound as it burns. You can only hear it in quiet places. | DA8: It has a preference for hot things. When it rains, steam is said to spout from the tip of its tail. | DB8: From the time it is born, a flame burns at the tip of its tail. Its life would end if the flame were to go out. | DE8: The fire on the tip of its tail is a measure of its life. If the Pokémon is healthy, its tail burns intensely. | DF8: The fire on the tip of its tail is a measure of its life. If the Pokémon is healthy, its tail burns intensely. | DP8: Pallet Town | DQ8: Pallet Town | DR8: Route 24 | DS8: Trade/migrate from another game | DT8: Trade/migrate from another game | DU8: Trade/migrate from another game | DV8: Trade/migrate from another game | DW8: Trade/migrate from another game | DX8: Trade/migrate from another game | DY8: Pallet Town | DZ8: Pallet Town | EA8: Trade/migrate from another game | EB8: Trade/migrate from another game | EC8: Trade/migrate from another game | ED8: Pallet Town | EE8: Pallet Town | EF8: Trade/migrate from another game | EG8: Trade/migrate from another game | EH8: Trade/migrate from another game | EI8: Trade/migrate from another game | EJ8: Lumiose City | EK8: Lumiose City | EL8: Trade/migrate from another game | EM8: Trade/migrate from another game | EN8: Trade/migrate from another game | EO8: Trade/migrate from another game | EP8: Route 3 | EQ8: Route 3 | ER8: Route 3 , 4 , 24 , Rock Tunnel | ES8: Route 3 , 4 , 24 , Rock Tunnel | ET8: Trade/migrate from another game | EU8: Trade/migrate from another game | EX8: Volcanic Cave , Sandsear Cave , Typhlo Cavern | EY8: Volcanic Cave , Sandsear Cave , Typhlo Cavern | EZ8: Not available in this game | FA8: Location data not yet available | FB8: Location data not yet available | FE8: Location data not yet available
A9: 0005-00 | B9: 5 | C9: Charmeleon | D9: =image("https://img.pokemondb.net/sprites/home/normal/"& lower(C9) &".png") | E9: =image("https://img.pokemondb.net/sprites/home/shiny/"& lower(C9) &".png") | F9: =image("https://www.serebii.net/pokedex-bw/type/"&lower(H9)&".gif") | G9: =image("https://www.serebii.net/pokedex-bw/type/"&lower(I9)&".gif") | H9: Fire | J9: Flame Pokémon | K9: 1.1 m (3′07″) | L9: 19.0 kg (41.9 lbs) | M9: Blaze | O9: Solar Power | P9: 1 Sp. Atk, 1 Speed | Q9: 45 (5.9% with PokéBall, full HP) | R9: 50 (normal) | S9: 142 | T9: Medium Slow | U9: Dragon | V9: Monster | W9: 87.5% male, 12.5% female | X9: 20 (4,884–5,140 steps) | Y9: 58 | Z9: 64 | AA9: 58 | AB9: 80 | AC9: 65 | AD9: 80 | AE9: =sum(Y9:AD9) -> 405 | AF9: Charmander → Charmeleon (Level 16) → Charizard (Level 36) | AG9: 0005 | AH9: 0005 | AI9: 0005 | AJ9: 0230 | AK9: 0230 | AL9: 0230 | AP9: 0005 | AQ9: 0005 | AU9: 0235 | AV9: 0235 | BA9: 0084 | BB9: 0084 | BI9: 0005 | BJ9: 0005 | BK9: 0379 | BL9: 0379 | BU9: 0168 | BV9: 0152 | BW9: When it swings its burning tail, it elevates the temperature to unbearably high levels. | BX9: When it swings its burning tail, it elevates the temperature to unbearably high levels. | BY9: Tough fights could excite this POKéMON. When excited, it may blow out bluish-white flames. | BZ9: It is very hotheaded by nature, so it constantly seeks opponents. It calms down only when it wins. | CA9: It has a barbaric nature. In battle, it whips its fiery tail around and slashes away with sharp claws. | CB9: If it becomes agitated during battle, it spouts intense flames, incinerating its surroundings. | CC9: CHARMELEON mercilessly destroys its foes using its sharp claws. If it encounters a strong foe, it turns aggressive. In this excited state, the flame at the tip of its tail flares with a bluish white color. | CD9: CHARMELEON mercilessly destroys its foes using its sharp claws. If it encounters a strong foe, it turns aggressive. In this excited state, the flame at the tip of its tail flares with a bluish white color. | CE9: Without pity, its sharp claws destroy foes. If it encounters a strong enemy, it becomes agitated, and the flame on its tail flares with a bluish white color. | CF9: It lashes about with its tail to knock down its foe. It then tears up the fallen opponent with sharp claws. | CG9: When it swings its burning tail, it elevates the air temperature to unbearably high levels. | CH9: In the rocky mountains where CHARMELEON live, their fiery tails shine at night like stars. | CI9: In the rocky mountains where CHARMELEON live, their fiery tails shine at night like stars. | CJ9: In the rocky mountains where CHARMELEON live, their fiery tails shine at night like stars. | CK9: It is very hotheaded by nature, so it constantly seeks opponents. It calms down only when it wins. | CL9: It has a barbaric nature. In battle, it whips its fiery tail around and slashes away with sharp claws. | CM9: In the rocky mountains where Charmeleon live, their fiery tails shine at night like stars. | CN9: In the rocky mountains where Charmeleon live, their fiery tails shine at night like stars. | CO9: In the rocky mountains where Charmeleon live, their fiery tails shine at night like stars. | CP9: In the rocky mountains where Charmeleon live, their fiery tails shine at night like stars. | CQ9: It lashes about with its tail to knock down its foe. It then tears up the fallen opponent with sharp claws. | CR9: When it swings its burning tail, it elevates the air temperature to unbearably high levels. | CS9: Charmeleon mercilessly destroys its foes using its sharp claws. If it encounters a strong foe, it turns aggressive. In this excited state, the flame at the tip of its tail flares with a bluish white color. | CT9: Charmeleon mercilessly destroys its foes using its sharp claws. If it encounters a strong foe, it turns aggressive. In this excited state, the flame at the tip of its tail flares with a bluish white color. | CY9: Tough fights could excite this Pokémon. When excited, it may breathe out bluish-white flames. | CZ9: Tough fights could excite this Pokémon. When excited, it may breathe out bluish-white flames. | DA9: It has a barbaric nature. In battle, it whips its fiery tail around and slashes away with sharp claws. | DB9: If it becomes agitated during battle, it spouts intense flames, incinerating its surroundings. | DE9: In the rocky mountains where Charmeleon live, their fiery tails shine at night like stars. | DF9: In the rocky mountains where Charmeleon live, their fiery tails shine at night like stars. | DP9: Evolve Charmander | DQ9: Evolve Charmander | DR9: Evolve Charmander | DS9: Trade/migrate from another game | DT9: Trade/migrate from another game | DU9: Trade/migrate from another game | DV9: Trade/migrate from another game | DW9: Trade/migrate from another game | DX9: Trade/migrate from another game | DY9: Evolve Charmander | DZ9: Evolve Charmander | EA9: Trade/migrate from another game | EB9: Trade/migrate from another game | EC9: Trade/migrate from another game | ED9: Evolve Charmander | EE9: Evolve Charmander | EF9: Trade/migrate from another game | EG9: Trade/migrate from another game | EH9: Trade/migrate from another game | EI9: Trade/migrate from another game | EJ9: Evolve Charmander | EK9: Evolve Charmander | EL9: Trade/migrate from another game | EM9: Trade/migrate from another game | EN9: Trade/migrate from another game | EO9: Trade/migrate from another game | EP9: Evolve Charmander | EQ9: Evolve Charmander | ER9: Evolve Charmander | ES9: Evolve Charmander | ET9: Trade/migrate from another game | EU9: Trade/migrate from another game | EX9: Evolve Charmander | EY9: Evolve Charmander | EZ9: Not available in this game | FA9: Location data not yet available | FB9: Location data not yet available | FE9: Location data not yet available
A10: 0006-00 | B10: 6 | C10: Charizard | D10: =image("https://img.pokemondb.net/sprites/home/normal/"& lower(C10) &".png") | E10: =image("https://img.pokemondb.net/sprites/home/shiny/"& lower(C10) &".png") | F10: =image("https://www.serebii.net/pokedex-bw/type/"&lower(H10)&".gif") | G10: =image("https://www.serebii.net/pokedex-bw/type/"&lower(I10)&".gif") | H10: Fire | I10: Flying | J10: Flame Pokémon | K10: 1.7 m (5′07″) | L10: 90.5 kg (199.5 lbs) | M10: Blaze | O10: Solar Power | P10: 3 Sp. Atk | Q10: 45 (5.9% with PokéBall, full HP) | R10: 50 (normal) | S10: 267 | T10: Medium Slow | U10: Dragon | V10: Monster | W10: 87.5% male, 12.5% female | X10: 20 (4,884–5,140 steps) | Y10: 78 | Z10: 84 | AA10: 78 | AB10: 109 | AC10: 85 | AD10: 100 | AE10: =sum(Y10:AD10) -> 534 | AF10: Charmander → Charmeleon (Level 16) → Charizard (Level 36) | AG10: 0006 | AH10: 0006 | AI10: 0006 | AJ10: 0231 | AK10: 0231 | AL10: 0231 | AP10: 0006 | AQ10: 0006 | AU10: 0236 | AV10: 0236 | BA10: 0085 | BB10: 0085 | BI10: 0006 | BJ10: 0006 | BK10: 0380 | BL10: 0380 | BU10: 0169 | BV10: 0153 | BW10: Spits fire that is hot enough to melt boulders. Known to cause forest fires unintentionally. | BX10: Spits fire that is hot enough to melt boulders. Known to cause forest fires unintentionally. | BY10: When expelling a blast of super hot fire, the red flame at the tip of its tail burns more intensely. | BZ10: If CHARIZARD becomes furious, the flame at the tip of its tail flares up in a whitish-blue color. | CA10: Breathing intense, hot flames, it can melt almost anything. Its breath inflicts terrible pain on enemies. | CB10: It uses its wings to fly high. The temperature of its fire increases as it gains experience in battle. | CC10: CHARIZARD flies around the sky in search of powerful opponents. It breathes fire of such great heat that it melts anything. However, it never turns its fiery breath on any opponent weaker than itself. | CD10: CHARIZARD flies around the sky in search of powerful opponents. It breathes fire of such great heat that it melts anything. However, it never turns its fiery breath on any opponent weaker than itself. | CE10: A CHARIZARD flies about in search of strong opponents. It breathes intense flames that can melt any material. However, it will never torch a weaker foe. | CF10: Its wings can carry this POKéMON close to an altitude of 4,600 feet. It blows out fire at very high temperatures. | CG10: It spits fire that is hot enough to melt boulders. It may cause forest fires by blowing flames. | CH10: It is said that CHARIZARD’s fire burns hotter if it has experienced harsh battles. | CI10: It is said that CHARIZARD’s fire burns hotter if it has experienced harsh battles. | CJ10: It is said that CHARIZARD’s fire burns hotter if it has experienced harsh battles. | CK10: If CHARIZARD becomes furious, the flame at the tip of its tail flares up in a light blue shade. | CL10: Breathing intense, hot flames, it can melt almost anything. Its breath inflicts terrible pain on enemies. | CM10: It is said that Charizard’s fire burns hotter if it has experienced harsh battles. | CN10: It is said that Charizard’s fire burns hotter if it has experienced harsh battles. | CO10: It is said that Charizard’s fire burns hotter if it has experienced harsh battles. | CP10: It is said that Charizard’s fire burns hotter if it has experienced harsh battles. | CQ10: When expelling a blast of superhot fire, the red flame at the tip of its tail burns more intensely. | CR10: Its wings can carry this Pokémon close to an altitude of 4,600 feet. It blows out fire at very high temperatures. | CS10: Charizard flies around the sky in search of powerful opponents. It breathes fire of such great heat that it melts anything. However, it never turns its fiery breath on any opponent weaker than itself. | CT10: Charizard flies around the sky in search of powerful opponents. It breathes fire of such great heat that it melts anything. However, it never turns its fiery breath on any opponent weaker than itself. | CY10: When this Pokémon expels a blast of superhot fire, the red flame at the tip of its tails burns more intensely. | CZ10: When this Pokémon expels a blast of superhot fire, the red flame at the tip of its tails burns more intensely. | DA10: It spits fire that is hot enough to melt boulders. It may cause forest fires by blowing flames. | DB10: Its wings can carry this Pokémon close to an altitude of 4,600 feet. It blows out fire at very high temperatures. | DE10: It is said that Charizard’s fire burns hotter if it has experienced harsh battles. | DF10: It is said that Charizard’s fire burns hotter if it has experienced harsh battles. | DP10: Evolve Charmander / Charmeleon | DQ10: Evolve Charmander / Charmeleon | DR10: Evolve Charmander / Charmeleon | DS10: Trade/migrate from another game | DT10: Trade/migrate from another game | DU10: Trade/migrate from another game | DV10: Trade/migrate from another game | DW10: Trade/migrate from another game | DX10: Trade/migrate from another game | DY10: Evolve Charmander / Charmeleon | DZ10: Evolve Charmander / Charmeleon | EA10: Trade/migrate from another game | EB10: Trade/migrate from another game | EC10: Trade/migrate from another game | ED10: Evolve Charmander / Charmeleon | EE10: Evolve Charmander / Charmeleon | EF10: Trade/migrate from another game | EG10: Trade/migrate from another game | EH10: Trade/migrate from another game | EI10: Trade/migrate from another game | EJ10: Evolve Charmander / Charmeleon | EK10: Evolve Charmander / Charmeleon | EL10: Trade/migrate from another game | EM10: Trade/migrate from another game | EN10: Trade/migrate from another game | EO10: Trade/migrate from another game | EP10: Evolve Charmander / Charmeleon | EQ10: Evolve Charmander / Charmeleon | ER10: Route 2 , 3 , 4 , 7 , 8 , 10 , 11 , 12 , 13 , 14 , 15 , 16 , 17 , 18 , 19 , 21 , 22 , 23 , 24 , 25 | ES10: Route 2 , 3 , 4 , 7 , 8 , 10 , 11 , 12 , 13 , 14 , 15 , 16 , 17 , 18 , 19 , 21 , 22 , 23 , 24 , 25 | ET10: Trade/migrate from another game | EU10: Trade/migrate from another game | EX10: Evolve Charmander / Charmeleon | EY10: Evolve Charmander / Charmeleon | EZ10: Not available in this game | FA10: Location data not yet available | FB10: Location data not yet available | FE10: Location data not yet available
A11: 0006-01 | B11: 6 | C11: Mega Charizard X | D11: =Sprite_Data!F3 | E11: =Sprite_Data!G3 | F11: =image("https://www.serebii.net/pokedex-bw/type/"&lower(H11)&".gif") | G11: =image("https://www.serebii.net/pokedex-bw/type/"&lower(I11)&".gif") | H11: Fire | I11: Dragon | J11: Flame Pokémon | K11: 1.7 m (5′07″) | L11: 110.5 kg (243.6 lbs) | M11: Tough Claws | P11: 3 Sp. Atk | Q11: 45 (5.9% with PokéBall, full HP) | R11: 50 (normal) | S11: 285 | T11: Medium Slow | U11: Dragon | V11: Monster | W11: 87.5% male, 12.5% female | X11: 20 (4,884–5,140 steps) | Y11: 78 | Z11: 130 | AA11: 111 | AB11: 130 | AC11: 85 | AD11: 100 | AE11: =sum(Y11:AD11) -> 634 | AF11: Charizardite X | AG11: 0006 | AH11: 0006 | AI11: 0006 | AJ11: 0231 | AK11: 0231 | AL11: 0231 | AP11: 0006 | AQ11: 0006 | AU11: 0236 | AV11: 0236 | BA11: 0085 | BB11: 0085 | BI11: 0006 | BJ11: 0006 | BK11: 0380 | BL11: 0380 | BV11: 0153
A12: 0006-02 | B12: 6 | C12: Mega Charizard Y | D12: =Sprite_Data!F4 | E12: =Sprite_Data!G4 | F12: =image("https://www.serebii.net/pokedex-bw/type/"&lower(H12)&".gif") | G12: =image("https://www.serebii.net/pokedex-bw/type/"&lower(I12)&".gif") | H12: Fire | I12: Flying | J12: Flame Pokémon | K12: 1.7 m (5′07″) | L12: 100.5 kg (221.6 lbs) | M12: Drought | P12: 3 Sp. Atk | Q12: 45 (5.9% with PokéBall, full HP) | R12: 50 (normal) | S12: 285 | T12: Medium Slow | U12: Dragon | V12: Monster | W12: 87.5% male, 12.5% female | X12: 20 (4,884–5,140 steps) | Y12: 78 | Z12: 104 | AA12: 78 | AB12: 159 | AC12: 115 | AD12: 100 | AE12: =sum(Y12:AD12) -> 634 | AF12: Charizardite Y | AG12: 0006 | AH12: 0006 | AI12: 0006 | AJ12: 0231 | AK12: 0231 | AL12: 0231 | AP12: 0006 | AQ12: 0006 | AU12: 0236 | AV12: 0236 | BA12: 0085 | BB12: 0085 | BI12: 0006 | BJ12: 0006 | BK12: 0380 | BL12: 0380 | BV12: 0153
A13: 0006-03 | B13: 6 | C13: Charizard Gigantamax | D13: =Sprite_Data!J3 | E13: =Sprite_Data!K3 | F13: =image("https://www.serebii.net/pokedex-bw/type/"&lower(H13)&".gif") | G13: =image("https://www.serebii.net/pokedex-bw/type/"&lower(I13)&".gif") | H13: Fire | I13: Flying | J13: Flame Pokémon | M13: Blaze | O13: Solar Power | AE13: =sum(Y13:AD13) -> 0 | AF13: Dynamax Band
A14: 0007-00 | B14: 7 | C14: Squirtle | D14: =image("https://img.pokemondb.net/sprites/home/normal/"& lower(C14) &".png") | E14: =image("https://img.pokemondb.net/sprites/home/shiny/"& lower(C14) &".png") | F14: =image("https://www.serebii.net/pokedex-bw/type/"&lower(H14)&".gif") | G14: =image("https://www.serebii.net/pokedex-bw/type/"&lower(I14)&".gif") | H14: Water | J14: Tiny Turtle Pokémon | K14: 0.5 m (1′08″) | L14: 9.0 kg (19.8 lbs) | M14: Torrent | O14: Rain Dish | P14: 1 Defense | Q14: 45 (5.9% with PokéBall, full HP) | R14: 50 (normal) | S14: 63 | T14: Medium Slow | U14: Monster | V14: Water 1 | W14: 87.5% male, 12.5% female | X14: 20 (4,884–5,140 steps) | Y14: 44 | Z14: 48 | AA14: 65 | AB14: 50 | AC14: 64 | AD14: 43 | AE14: =sum(Y14:AD14) -> 314 | AF14: Squirtle → Wartortle (Level 16) → Blastoise (Level 36) | AG14: 0007 | AH14: 0007 | AI14: 0007 | AJ14: 0232 | AK14: 0232 | AL14: 0232 | AP14: 0007 | AQ14: 0007 | AU14: 0237 | AV14: 0237 | BA14: 0086 | BB14: 0086 | BI14: 0007 | BJ14: 0007 | BM14: 0071 | BU14: 0170 | BV14: 0154 | BW14: After birth, its back swells and hardens into a shell. Powerfully sprays foam from its mouth. | BX14: After birth, its back swells and hardens into a shell. Powerfully sprays foam from its mouth. | BY14: Shoots water at prey while in the water. Withdraws into its shell when in danger. | BZ14: The shell is soft when it is born. It soon becomes so resilient, prodding fingers will bounce off it. | CA14: The shell, which hardens soon after it is born, is resilient. If you poke it, it will bounce back out. | CB14: When it feels threatened, it draws its legs inside its shell and sprays water from its mouth. | CC14: SQUIRTLE’s shell is not merely used for protection. The shell’s rounded shape and the grooves on its surface help minimize resistance in water, enabling this POKéMON to swim at high speeds. | CD14: SQUIRTLE’s shell is not merely used for protection. The shell’s rounded shape and the grooves on its surface help minimize resistance in water, enabling this POKéMON to swim at high speeds. | CE14: Its shell is not just for protection. Its rounded shape and the grooves on its surface minimize resistance in water, enabling SQUIRTLE to swim at high speeds. | CF14: When it retracts its long neck into its shell, it squirts out water with vigorous force. | CG14: After birth, its back swells and hardens into a shell. It powerfully sprays foam from its mouth. | CH14: It shelters itself in its shell, then strikes back with spouts of water at every opportunity. | CI14: It shelters itself in its shell, then strikes back with spouts of water at every opportunity. | CJ14: It shelters itself in its shell, then strikes back with spouts of water at every opportunity. | CK14: The shell is soft when it is born. It soon becomes so resilient, prodding fingers will bounce off it. | CL14: The shell, which hardens soon after it is born, is resilient. If you poke it, it will bounce back out. | CM14: It shelters itself in its shell, then strikes back with spouts of water at every opportunity. | CN14: It shelters itself in its shell, then strikes back with spouts of water at every opportunity. | CO14: It shelters itself in its shell then strikes back with spouts of water at every opportunity. | CP14: It shelters itself in its shell then strikes back with spouts of water at every opportunity. | CQ14: It shelters itself in its shell, then strikes back with spouts of water at every opportunity. | CR14: Shoots water at prey while in the water. Withdraws into its shell when in danger. | CS14: Squirtle’s shell is not merely used for protection. The shell’s rounded shape and the grooves on its surface help minimize resistance in water, enabling this Pokémon to swim at high speeds. | CT14: Squirtle’s shell is not merely used for protection. The shell’s rounded shape and the grooves on its surface help minimize resistance in water, enabling this Pokémon to swim at high speeds. | CY14: Shoots water at prey while in the water. Withdraws into its shell when in danger. | CZ14: Shoots water at prey while in the water. Withdraws into its shell when in danger. | DA14: When it retracts its long neck into its shell, it squirts out water with vigorous force. | DB14: When it feels threatened, it draws its limbs inside its shell and sprays water from its mouth. | DE14: It hides in its shell to protect itself, then strikes back with spouts of water at every opportunity. | DF14: It hides in its shell to protect itself, then strikes back with spouts of water at every opportunity. | DP14: Pallet Town | DQ14: Pallet Town | DR14: Vermilion City | DS14: Trade/migrate from another game | DT14: Trade/migrate from another game | DU14: Trade/migrate from another game | DV14: Trade/migrate from another game | DW14: Trade/migrate from another game | DX14: Trade/migrate from another game | DY14: Pallet Town | DZ14: Pallet Town | EA14: Trade/migrate from another game | EB14: Trade/migrate from another game | EC14: Trade/migrate from another game | ED14: Pallet Town | EE14: Pallet Town | EF14: Trade/migrate from another game | EG14: Trade/migrate from another game | EH14: Trade/migrate from another game | EI14: Trade/migrate from another game | EJ14: Lumiose City | EK14: Lumiose City | EL14: Trade/migrate from another game | EM14: Trade/migrate from another game | EN14: Trade/migrate from another game | EO14: Trade/migrate from another game | EP14: Seaward Cave | EQ14: Seaward Cave | ER14: Route 24 , 25 , Seafoam Islands , Vermilion City | ES14: Route 24 , 25 , Seafoam Islands , Vermilion City | ET14: Trade/migrate from another game | EU14: Trade/migrate from another game | EX14: Fountainspring Cave , Riverbank Cave , Still-Water Cavern | EY14: Fountainspring Cave , Riverbank Cave , Still-Water Cavern | EZ14: Not available in this game | FA14: Location data not yet available | FB14: Location data not yet available | FE14: Location data not yet available
A15: 0008-00 | B15: 8 | C15: Wartortle | D15: =image("https://img.pokemondb.net/sprites/home/normal/"& lower(C15) &".png") | E15: =image("https://img.pokemondb.net/sprites/home/shiny/"& lower(C15) &".png") | F15: =image("https://www.serebii.net/pokedex-bw/type/"&lower(H15)&".gif") | G15: =image("https://www.serebii.net/pokedex-bw/type/"&lower(I15)&".gif") | H15: Water | J15: Turtle Pokémon | K15: 1.0 m (3′03″) | L15: 22.5 kg (49.6 lbs) | M15: Torrent | O15: Rain Dish | P15: 1 Defense, 1 Sp. Def | Q15: 45 (5.9% with PokéBall, full HP) | R15: 50 (normal) | S15: 142 | T15: Medium Slow | U15: Monster | V15: Water 1 | W15: 87.5% male, 12.5% female | X15: 20 (4,884–5,140 steps) | Y15: 59 | Z15: 63 | AA15: 80 | AB15: 65 | AC15: 80 | AD15: 58 | AE15: =sum(Y15:AD15) -> 405 | AF15: Squirtle → Wartortle (Level 16) → Blastoise (Level 36) | AG15: 0008 | AH15: 0008 | AI15: 0008 | AJ15: 0233 | AK15: 0233 | AL15: 0233 | AP15: 0008 | AQ15: 0008 | AU15: 0238 | AV15: 0238 | BA15: 0087 | BB15: 0087 | BI15: 0008 | BJ15: 0008 | BM15: 0072 | BU15: 0171 | BV15: 0155 | BW15: Often hides in water to stalk unwary prey. For swimming fast, it moves its ears to maintain balance. | BX15: Often hides in water to stalk unwary prey. For swimming fast, it moves its ears to maintain balance. | BY15: When tapped, this POKéMON will pull in its head, but its tail will still stick out a little bit. | BZ15: It is recognized as a symbol of longevity. If its shell has algae on it, that WARTORTLE is very old. | CA15: It cleverly controls its furry ears and tail to maintain its balance while swimming. | CB15: Its long, furry tail is a symbol of longevity, making it quite popular among older people. | CC15: Its tail is large and covered with a rich, thick fur. The tail becomes increasingly deeper in color as WARTORTLE ages. The scratches on its shell are evidence of this POKéMON’s toughness as a battler. | CD15: Its tail is large and covered with a rich, thick fur. The tail becomes increasingly deeper in color as WARTORTLE ages. The scratches on its shell are evidence of this POKéMON’s toughness as a battler. | CE15: Its large tail is covered with rich, thick fur that deepens in color with age. The scratches on its shell are evidence of this POKéMON’s toughness in battle. | CF15: This POKéMON is very popular as a pet. Its fur-covered tail is a symbol of its longevity. | CG15: It often hides in water to stalk unwary prey. For fast swimming, it moves its ears to maintain balance. | CH15: It is said to live 10,000 years. Its furry tail is popular as a symbol of longevity. | CI15: It is said to live 10,000 years. Its furry tail is popular as a symbol of longevity. | CJ15: It is said to live 10,000 years. Its furry tail is popular as a symbol of longevity. | CK15: It is a well-established symbol of longevity. If its shell has algae on it, that WARTORTLE is very old. | CL15: It cleverly controls its furry ears and tail to maintain its balance while swimming. | CM15: It is said to live 10,000 years. Its furry tail is popular as a symbol of longevity. | CN15: It is said to live 10,000 years. Its furry tail is popular as a symbol of longevity. | CO15: It is said to live 10,000 years. Its furry tail is popular as a symbol of longevity. | CP15: It is said to live 10,000 years. Its furry tail is popular as a symbol of longevity. | CQ15: When tapped, this Pokémon will pull in its head, but its tail will still stick out a little bit. | CR15: It is said to live 10,000 years. Its furry tail is popular as a symbol of longevity. | CS15: Its tail is large and covered with a rich, thick fur. The tail becomes increasingly deeper in color as Wartortle ages. The scratches on its shell are evidence of this Pokémon’s toughness as a battler. | CT15: Its tail is large and covered with a rich, thick fur. The tail becomes increasingly deeper in color as Wartortle ages. The scratches on its shell are evidence of this Pokémon’s toughness as a battler. | CY15: When tapped on its head, this Pokémon will pull it in, but its tail will stick out a little bit. | CZ15: When tapped on its head, this Pokémon will pull it in, but its tail will stick out a little bit. | DA15: It is recognized as a symbol of longevity. If its shell has algae on it, that Wartortle is very old. | DB15: It cleverly controls its furry ears and tail to maintain its balance while swimming. | DE15: It is said to live 10,000 years. Its furry tail is popular as a symbol of longevity. | DF15: It is said to live 10,000 years. Its furry tail is popular as a symbol of longevity. | DP15: Evolve Squirtle | DQ15: Evolve Squirtle | DR15: Evolve Squirtle | DS15: Trade/migrate from another game | DT15: Trade/migrate from another game | DU15: Trade/migrate from another game | DV15: Trade/migrate from another game | DW15: Trade/migrate from another game | DX15: Trade/migrate from another game | DY15: Evolve Squirtle | DZ15: Evolve Squirtle | EA15: Trade/migrate from another game | EB15: Trade/migrate from another game | EC15: Trade/migrate from another game | ED15: Evolve Squirtle | EE15: Evolve Squirtle | EF15: Trade/migrate from another game | EG15: Trade/migrate from another game | EH15: Trade/migrate from another game | EI15: Trade/migrate from another game | EJ15: Evolve Squirtle | EK15: Evolve Squirtle | EL15: Trade/migrate from another game | EM15: Trade/migrate from another game | EN15: Trade/migrate from another game | EO15: Trade/migrate from another game | EP15: Evolve Squirtle | EQ15: Evolve Squirtle | ER15: Evolve Squirtle | ES15: Evolve Squirtle | ET15: Trade/migrate from another game | EU15: Trade/migrate from another game | EX15: Evolve Squirtle | EY15: Evolve Squirtle | EZ15: Not available in this game | FA15: Location data not yet available | FB15: Location data not yet available | FE15: Location data not yet available
A16: 0009-00 | B16: 9 | C16: Blastoise | D16: =image("https://img.pokemondb.net/sprites/home/normal/"& lower(C16) &".png") | E16: =image("https://img.pokemondb.net/sprites/home/shiny/"& lower(C16) &".png") | F16: =image("https://www.serebii.net/pokedex-bw/type/"&lower(H16)&".gif") | G16: =image("https://www.serebii.net/pokedex-bw/type/"&lower(I16)&".gif") | H16: Water | J16: Shellfish Pokémon | K16: 1.6 m (5′03″) | L16: 85.5 kg (188.5 lbs) | M16: Torrent | O16: Rain Dish | P16: 3 Sp. Def | Q16: 45 (5.9% with PokéBall, full HP) | R16: 50 (normal) | S16: 239 | T16: Medium Slow | U16: Monster | V16: Water 1 | W16: 87.5% male, 12.5% female | X16: 20 (4,884–5,140 steps) | Y16: 79 | Z16: 83 | AA16: 100 | AB16: 85 | AC16: 105 | AD16: 78 | AE16: =sum(Y16:AD16) -> 530 | AF16: Squirtle → Wartortle (Level 16) → Blastoise (Level 36) | AG16: 0009 | AH16: 0009 | AI16: 0009 | AJ16: 0234 | AK16: 0234 | AL16: 0234 | AP16: 0009 | AQ16: 0009 | AU16: 0239 | AV16: 0239 | BA16: 0088 | BB16: 0088 | BI16: 0009 | BJ16: 0009 | BM16: 0073 | BU16: 0172 | BV16: 0156 | BW16: A brutal POKéMON with pressurized water jets on its shell. They are used for high speed tackles. | BX16: A brutal POKéMON with pressurized water jets on its shell. They are used for high speed tackles. | BY16: Once it takes aim at its enemy, it blasts out water with even more force than a fire hose. | BZ16: It deliberately makes itself heavy so it can withstand the recoil of the water jets it fires. | CA16: The rocket cannons on its shell fire jets of water capable of punching holes through thick steel. | CB16: It firmly plants its feet on the ground before shooting water from the jets on its back. | CC16: BLASTOISE has water spouts that protrude from its shell. The water spouts are very accurate. They can shoot bullets of water with enough accuracy to strike empty cans from a distance of over 160 feet. | CD16: BLASTOISE has water spouts that protrude from its shell. The water spouts are very accurate. They can shoot bullets of water with enough accuracy to strike empty cans from a distance of over 160 feet. | CE16: The waterspouts that protrude from its shell are highly accurate. Their bullets of water can precisely nail tin cans from a distance of over 160 feet. | CF16: It crushes its foe under its heavy body to cause fainting. In a pinch, it will withdraw inside its shell. | CG16: The pressurized water jets on this brutal POKéMON’s shell are used for high-speed tackles. | CH16: The jets of water it spouts from the rocket cannons on its shell can punch through thick steel. | CI16: The jets of water it spouts from the rocket cannons on its shell can punch through thick steel. | CJ16: The jets of water it spouts from the rocket cannons on its shell can punch through thick steel. | CK16: It deliberately makes itself heavy so it can withstand the recoil of the water jets it fires. | CL16: The rocket cannons on its shell fire jets of water capable of punching holes through thick steel. | CM16: The jets of water it spouts from the rocket cannons on its shell can punch through thick steel. | CN16: The jets of water it spouts from the rocket cannons on its shell can punch through thick steel. | CO16: The jets of water it spouts from the rocket cannons on its shell can punch through thick steel. | CP16: The jets of water it spouts from the rocket cannons on its shell can punch through thick steel. | CQ16: It crushes its foe under its heavy body to cause fainting. In a pinch, it will withdraw inside its shell. | CR16: The pressurized water jets on this brutal Pokémon’s shell are used for high-speed tackles. | CS16: Blastoise has water spouts that protrude from its shell. The water spouts are very accurate. They can shoot bullets of water with enough accuracy to strike empty cans from a distance of over 160 feet. | CT16: Blastoise has water spouts that protrude from its shell. The water spouts are very accurate. They can shoot bullets of water with enough accuracy to strike empty cans from a distance of over 160 feet. | CY16: Once it takes aim at its enemy, it blasts out water with even more force than a fire hose. | CZ16: Once it takes aim at its enemy, it blasts out water with even more force than a fire hose. | DA16: It crushes its foe under its heavy body to cause fainting. In a pinch, it will withdraw inside its shell. | DB16: The rocket cannons on its shell fire jets of water capable of punching holes through thick steel. | DE16: The jets of water it spouts from the rocket cannons on its shell can punch through thick steel. | DF16: The jets of water it spouts from the rocket cannons on its shell can punch through thick steel. | DP16: Evolve Squirtle / Wartortle | DQ16: Evolve Squirtle / Wartortle | DR16: Evolve Squirtle / Wartortle | DS16: Trade/migrate from another game | DT16: Trade/migrate from another game | DU16: Trade/migrate from another game | DV16: Trade/migrate from another game | DW16: Trade/migrate from another game | DX16: Trade/migrate from another game | DY16: Evolve Squirtle / Wartortle | DZ16: Evolve Squirtle / Wartortle | EA16: Trade/migrate from another game | EB16: Trade/migrate from another game | EC16: Trade/migrate from another game | ED16: Evolve Squirtle / Wartortle | EE16: Evolve Squirtle / Wartortle | EF16: Trade/migrate from another game | EG16: Trade/migrate from another game | EH16: Trade/migrate from another game | EI16: Trade/migrate from another game | EJ16: Evolve Squirtle / Wartortle | EK16: Evolve Squirtle / Wartortle | EL16: Trade/migrate from another game | EM16: Trade/migrate from another game | EN16: Trade/migrate from another game | EO16: Trade/migrate from another game | EP16: Evolve Squirtle / Wartortle | EQ16: Evolve Squirtle / Wartortle | ER16: Evolve Squirtle / Wartortle | ES16: Evolve Squirtle / Wartortle | ET16: Trade/migrate from another game | EU16: Trade/migrate from another game | EX16: Evolve Squirtle / Wartortle | EY16: Evolve Squirtle / Wartortle | EZ16: Not available in this game | FA16: Location data not yet available | FB16: Location data not yet available | FE16: Location data not yet available
A17: 0009-01 | B17: 9 | C17: Mega Blastoise | D17: =Sprite_Data!F5 | E17: =Sprite_Data!G5 | F17: =image("https://www.serebii.net/pokedex-bw/type/"&lower(H17)&".gif") | G17: =image("https://www.serebii.net/pokedex-bw/type/"&lower(I17)&".gif") | H17: Water | J17: Shellfish Pokémon | K17: 1.6 m (5′03″) | L17: 101.1 kg (222.9 lbs) | M17: Mega Launcher | P17: 3 Sp. Def | Q17: 45 (5.9% with PokéBall, full HP) | R17: 50 (normal) | S17: 284 | T17: Medium Slow | U17: Monster | V17: Water 1 | W17: 87.5% male, 12.5% female | X17: 20 (4,884–5,140 steps) | Y17: 79 | Z17: 103 | AA17: 120 | AB17: 135 | AC17: 115 | AD17: 78 | AE17: =sum(Y17:AD17) -> 630 | AF17: Blastoiseite
A18: 0009-02 | B18: 9 | C18: Blastoise Gigantamax | D18: =Sprite_Data!J4 | E18: =Sprite_Data!K4 | F18: =image("https://www.serebii.net/pokedex-bw/type/"&lower(H18)&".gif") | G18: =image("https://www.serebii.net/pokedex-bw/type/"&lower(I18)&".gif") | H18: Water | J18: Shellfish Pokémon | AE18: =sum(Y18:AD18) -> 0
A19: 0010-00 | B19: 10 | C19: Caterpie | D19: =image("https://img.pokemondb.net/sprites/home/normal/"& lower(C19) &".png") | E19: =image("https://img.pokemondb.net/sprites/home/shiny/"& lower(C19) &".png") | F19: =image("https://www.serebii.net/pokedex-bw/type/"&lower(H19)&".gif") | G19: =image("https://www.serebii.net/pokedex-bw/type/"&lower(I19)&".gif") | H19: Bug | J19: Worm Pokémon | K19: 0.3 m (1′00″) | L19: 2.9 kg (6.4 lbs) | M19: Shield Dust | O19: Run Away | P19: 1 HP | Q19: 255 (33.3% with PokéBall, full HP) | R19: 50 (normal) | S19: 39 | T19: Medium Fast | U19: Bug | W19: 50% male, 50% female | X19: 15 (3,599–3,855 steps) | Y19: 45 | Z19: 30 | AA19: 35 | AB19: 20 | AC19: 20 | AD19: 45 | AE19: =sum(Y19:AD19) -> 195 | AF19: Caterpie → Metapod (Level 7) → Butterfree (Level 10) | AG19: 0010 | AH19: 0010 | AI19: 0010 | AJ19: 0024 | AK19: 0024 | AL19: 0024 | AP19: 0010 | AQ19: 0010 | AU19: 0024 | AV19: 0024 | BA19: 0023 | BB19: 0023 | BE19: 0017 | BF19: 0017 | BG19: 0017 | BH19: 0017 | BI19: 0010 | BJ19: 0010 | BK19: 0013 | BL19: 0013 | BW19: Its short feet are tipped with suction pads that enable it to tirelessly climb slopes and walls. | BX19: Its short feet are tipped with suction pads that enable it to tirelessly climb slopes and walls. | BY19: If you touch the feeler on top of its head, it will release a horrible stink to protect itself. | BZ19: For protection, it releases a horrible stench from the antenna on its head to drive away enemies. | CA19: Its feet have suction cups designed to stick to any surface. It tenaciously climbs trees to forage. | CB19: It crawls into foliage where it camouflages itself among leaves that are the same color as its body. | CC19: CATERPIE has a voracious appetite. It can devour leaves bigger than its body right before your eyes. From its antenna, this POKéMON releases a terrifically strong odor. | CD19: CATERPIE has a voracious appetite. It can devour leaves bigger than its body right before your eyes. From its antenna, this POKéMON releases a terrifically strong odor. | CE19: Its voracious appetite compels it to devour leaves bigger than itself without hesitation. It releases a terribly strong odor from its antennae. | CF19: It is covered with a green skin. When it grows, it sheds the skin, covers itself with silk, and becomes a cocoon. | CG19: Its short feet are tipped with suction pads that enable it to tirelessly climb slopes and walls. | CH19: It releases a stench from its red antenna to repel enemies. It grows by molting repeatedly. | CI19: It releases a stench from its red antenna to repel enemies. It grows by molting repeatedly. | CJ19: It releases a stench from its red antenna to repel enemies. It grows by molting repeatedly. | CK19: For protection, it releases a horrible stench from the antennae on its head to drive away enemies. | CL19: Its feet have suction cups designed to stick to any surface. It tenaciously climbs trees to forage. | CM19: It releases a stench from its red antenna to repel enemies. It grows by molting repeatedly. | CN19: It releases a stench from its red antenna to repel enemies. It grows by molting repeatedly. | CO19: It releases a stench from its red antenna to repel enemies. It grows by molting repeatedly. | CP19: It releases a stench from its red antenna to repel enemies. It grows by molting repeatedly. | CQ19: For protection, it releases a horrible stench from the antennae on its head to drive away enemies. | CR19: Its feet have suction cups designed to stick to any surface. It tenaciously climbs trees to forage. | CS19: Caterpie has a voracious appetite. It can devour leaves bigger than its body right before your eyes. From its antenna, this Pokémon releases a terrifically strong odor. | CT19: Caterpie has a voracious appetite. It can devour leaves bigger than its body right before your eyes. From its antenna, this Pokémon releases a terrifically strong odor. | CU19: When attacked by bird Pokémon, it resists by releasing a terrifically strong odor from its antennae, but it often becomes their prey. | CV19: It’s easy to catch, and it grows quickly, making it one of the top recommendations for novice Pokémon Trainers. | CW19: Perhaps because it would like to grow up quickly, it has a voracious appetite, eating a hundred leaves a day. | CX19: Its body is soft and weak. In nature, its perpetual fate is to be seen by others as food. | CY19: If you touch the feeler on top of its head, it will release a horrible stink to protect itself. | CZ19: If you touch the feeler on top of its head, it will release a horrible stink to protect itself. | DA19: For protection, it releases a horrible stench from the antenna on its head to drive away enemies. | DB19: Its short feet are tipped with suction pads that enable it to tirelessly climb slopes and walls. | DE19: It releases a stench from its red antennae to repel enemies. It grows by molting repeatedly. | DF19: It releases a stench from its red antennae to repel enemies. It grows by molting repeatedly. | DP19: Route 25 , Viridian Forest | DQ19: Route 2 , 24 , 25 , Viridian Forest | DR19: Viridian Forest | DS19: Route 2 , 26 , 27 , 30 , 31 , 34 , 35 , 36 , 37 , 38 , 39 , Azalea Town , Ilex Forest , Lake of Rage , National Park | DT19: National Park | DU19: Route 2 , 24 , 25 , 30 , 31 , Ilex Forest , National Park | DV19: Trade/migrate from another game | DW19: Trade/migrate from another game | DX19: Trade/migrate from another game | DY19: Route 2 , 24 , 25 , Pattern Bush , Viridian Forest | DZ19: Route 2 , 24 , 25 , Pattern Bush , Viridian Forest | EA19: Route 204 | EB19: Route 204 | EC19: Route 204 , Eterna Forest | ED19: Route 2 , 30 , 31 , Ilex Forest , National Park , Viridian Forest | EE19: National Park | EF19: Trade/migrate from another game | EG19: Breed Metapod / Butterfree | EH19: Trade/migrate from another game | EI19: Trade/migrate from another game | EJ19: Santalune Forest | EK19: Route 2 , Santalune Forest | EL19: Trade/migrate from another game | EM19: Trade/migrate from another game | EN19: Route 1 , 5 , Melemele Meadow , Lush Jungle | EO19: Route 1 , 5 , Melemele Meadow , Lush Jungle | EP19: Route 1 , 5 , Melemele Meadow , Lush Jungle | EQ19: Route 1 , 5 , Melemele Meadow , Lush Jungle | ER19: Route 2 , Viridian Forest | ES19: Route 2 , Viridian Forest | ET19: Route 1 | EU19: Route 1 | EX19: Spacious Cave , Grassland Cave , Swampy Cave , Riverbank Cave , Still-Water Cavern , Sunlit Cavern , Bogsunk Cavern | EY19: Trade/migrate from another game | EZ19: Not available in this game | FA19: Location data not yet available | FB19: Location data not yet available | FE19: Location data not yet available
A20: 0011-00 | B20: 11 | C20: Metapod | D20: =image("https://img.pokemondb.net/sprites/home/normal/"& lower(C20) &".png") | E20: =image("https://img.pokemondb.net/sprites/home/shiny/"& lower(C20) &".png") | F20: =image("https://www.serebii.net/pokedex-bw/type/"&lower(H20)&".gif") | G20: =image("https://www.serebii.net/pokedex-bw/type/"&lower(I20)&".gif") | H20: Bug | J20: Cocoon Pokémon | K20: 0.7 m (2′04″) | L20: 9.9 kg (21.8 lbs) | M20: Shed Skin | N20: . | P20: 2 Defense | Q20: 120 (15.7% with PokéBall, full HP) | R20: 50 (normal) | S20: 72 | T20: Medium Fast | U20: Bug | W20: 50% male, 50% female | X20: 15 (3,599–3,855 steps) | Y20: 50 | Z20: 20 | AA20: 55 | AB20: 25 | AC20: 25 | AD20: 30 | AE20: =sum(Y20:AD20) -> 205 | AF20: Caterpie → Metapod (Level 7) → Butterfree (Level 10) | AG20: 0011 | AH20: 0011 | AI20: 0011 | AJ20: 0025 | AK20: 0025 | AL20: 0025 | AP20: 0011 | AQ20: 0011 | AU20: 0025 | AV20: 0025 | BA20: 0024 | BB20: 0024 | BE20: 0018 | BF20: 0018 | BG20: 0018 | BH20: 0018 | BI20: 0011 | BJ20: 0011 | BK20: 0014 | BL20: 0014 | BW20: This POKéMON is vulnerable to attack while its shell is soft, exposing its weak and tender body. | BX20: This POKéMON is vulnerable to attack while its shell is soft, exposing its weak and tender body. | BY20: Hardens its shell to protect itself. However, a large impact may cause it to pop out of its shell. | BZ20: Inside the shell, it is soft and weak as it prepares to evolve. It stays motionless in the shell. | CA20: It prepares for evolution by hardening its shell as much as possible to protect its soft body. | CB20: This is its pre-evolved form. At this stage, it can only harden, so it remains motionless to avoid attack. | CC20: The shell covering this POKéMON’s body is as hard as an iron slab. METAPOD does not move very much. It stays still because it is preparing its soft innards for evolution inside the hard shell. | CD20: The shell covering this POKéMON’s body is as hard as an iron slab. METAPOD does not move very much. It stays still because it is preparing its soft innards for evolution inside the hard shell. | CE20: Its shell is as hard as an iron slab. A METAPOD does not move very much because it is preparing its soft innards for evolution inside the shell. | CF20: Even though it is encased in a sturdy shell, the body inside is tender. It can’t withstand a harsh attack. | CG20: This POKéMON is vulnerable to attack while its shell is soft, exposing its weak and tender body. | CH20: A steel-hard shell protects its tender body. It quietly endures hardships while awaiting evolution. | CI20: A steel-hard shell protects its tender body. It quietly endures hardships while awaiting evolution. | CJ20: A steel-hard shell protects its tender body. It quietly endures hardships while awaiting evolution. | CK20: Inside the shell, it is soft and weak as it prepares to evolve. It stays motionless in the shell. | CL20: It prepares for evolution by hardening its shell as much as possible to protect its soft body. | CM20: A steel-hard shell protects its tender body. It quietly endures hardships while awaiting evolution. | CN20: A steel-hard shell protects its tender body. It quietly endures hardships while awaiting evolution. | CO20: A steel-hard shell protects its tender body. It quietly endures hardships while awaiting evolution. | CP20: A steel-hard shell protects its tender body. It quietly endures hardships while awaiting evolution. | CQ20: A steel-hard shell protects its tender body. It quietly endures hardships while awaiting evolution. | CR20: This Pokémon is vulnerable to attack while its shell is soft, exposing its weak and tender body. | CS20: The shell covering this Pokémon’s body is as hard as an iron slab. Metapod does not move very much. It stays still because it is preparing its soft innards for evolution inside the hard shell. | CT20: The shell covering this Pokémon’s body is as hard as an iron slab. Metapod does not move very much. It stays still because it is preparing its soft innards for evolution inside the hard shell. | CU20: Its shell is filled with its soft innards. It doesn’t move much because of the risk it might carelessly spill its innards out. | CV20: Its shell is hard, but it’s still just a bug shell. It’s been known to break, so intense battles with it should be avoided. | CW20: Its shell is filled with a thick liquid. All of the cells throughout its body are being rebuilt in preparation for evolution. | CX20: Its hard shell doesn’t crack a bit even if Pikipek pecks at it, but it will tip over, spilling out its insides. | CY20: Hardens its shell to protect itself. However, a large impact may cause it to pop out of its shell. | CZ20: Hardens its shell to protect itself. However, a large impact may cause it to pop out of its shell. | DA20: It is waiting for the moment to evolve. At this stage, it can only harden, so it remains motionless to avoid attack. | DB20: Even though it is encased in a sturdy shell, the body inside is tender. It can’t withstand a harsh attack. | DE20: A steel-hard shell protects its tender body. The Pokémon quietly endures hardships while awaiting evolution. | DF20: A steel-hard shell protects its tender body. The Pokémon quietly endures hardships while awaiting evolution. | DP20: Route 25 , Viridian Forest | DQ20: Route 24 , 25 , Viridian Forest | DR20: Viridian Forest | DS20: Route 2 , 26 , 27 , 30 , 31 , 34 , 35 , 36 , 37 , 38 , 39 , Azalea Town , Ilex Forest , Lake of Rage , National Park | DT20: National Park | DU20: Route 24 , 25 , Ilex Forest , National Park | DV20: Trade/migrate from another game | DW20: Trade/migrate from another game | DX20: Trade/migrate from another game | DY20: Route 24 , 25 , Pattern Bush , Viridian Forest | DZ20: Route 24 , 25 , Pattern Bush , Viridian Forest | EA20: Eterna Forest | EB20: Eterna Forest | EC20: Eterna Forest | ED20: Route 2 , 30 , 31 , 47 , Ilex Forest , National Park , Viridian Forest | EE20: National Park | EF20: Trade/migrate from another game | EG20: Route 12 | EH20: Trade/migrate from another game | EI20: Trade/migrate from another game | EJ20: Evolve Caterpie | EK20: Santalune Forest | EL20: Trade/migrate from another game | EM20: Trade/migrate from another game | EN20: Route 1 , 5 , Melemele Meadow , Lush Jungle | EO20: Route 1 , 5 , Melemele Meadow , Lush Jungle | EP20: Route 5 , Melemele Meadow , Lush Jungle | EQ20: Route 5 , Melemele Meadow , Lush Jungle | ER20: Viridian Forest | ES20: Viridian Forest | ET20: Rolling Fields | EU20: Rolling Fields | EX20: Evolve Caterpie | EY20: Trade/migrate from another game | EZ20: Not available in this game | FA20: Location data not yet available | FB20: Location data not yet available | FE20: Location data not yet available
A21: 0012-00 | B21: 12 | C21: Butterfree | D21: =image("https://img.pokemondb.net/sprites/home/normal/"& lower(C21) &".png") | E21: =image("https://img.pokemondb.net/sprites/home/shiny/"& lower(C21) &".png") | F21: =image("https://www.serebii.net/pokedex-bw/type/"&lower(H21)&".gif") | G21: =image("https://www.serebii.net/pokedex-bw/type/"&lower(I21)&".gif") | H21: Bug | I21: Flying | J21: Butterfly Pokémon | K21: 1.1 m (3′07″) | L21: 32.0 kg (70.5 lbs) | M21: Compound Eyes | O21: Tinted Lens | P21: 2 Sp. Atk, 1 Sp. Def | Q21: 45 (5.9% with PokéBall, full HP) | R21: 50 (normal) | S21: 178 | T21: Medium Fast | U21: Bug | W21: 50% male, 50% female | X21: 15 (3,599–3,855 steps) | Y21: 60 | Z21: 45 | AA21: 50 | AB21: 90 | AC21: 80 | AD21: 70 | AE21: =sum(Y21:AD21) -> 395 | AF21: Caterpie → Metapod (Level 7) → Butterfree (Level 10) | AG21: 0012 | AH21: 0012 | AI21: 0012 | AJ21: 0026 | AK21: 0026 | AL21: 0026 | AP21: 0012 | AQ21: 0012 | AU21: 0026 | AV21: 0026 | BA21: 0025 | BB21: 0025 | BE21: 0019 | BF21: 0019 | BG21: 0019 | BH21: 0019 | BI21: 0012 | BJ21: 0012 | BK21: 0015 | BL21: 0015 | BW21: In battle, it flaps its wings at high speed to release highly toxic dust into the air. | BX21: In battle, it flaps its wings at high speed to release highly toxic dust into the air. | BY21: Its wings, covered with poisonous powders, repel water. This allows it to fly in the rain. | BZ21: It collects honey every day. It rubs honey onto the hairs on its legs to carry it back to its nest. | CA21: Water-repellent powder on its wings enables it to collect honey, even in the heaviest of rains. | CB21: It flits from flower to flower, collecting honey. It can even identify distant flowers in bloom. | CC21: BUTTERFREE has a superior ability to search for delicious honey from flowers. It can even search out, extract, and carry honey from flowers that are blooming over six miles from its nest. | CD21: BUTTERFREE has a superior ability to search for delicious honey from flowers. It can even search out, extract, and carry honey from flowers that are blooming over six miles from its nest. | CE21: It has a superior ability to search for delicious honey from flowers. It can seek, extract, and carry honey from flowers blooming over six miles away. | CF21: The wings are protected by rain-repellent dust. As a result, this POKéMON can fly about even in rain. | CG21: In battle, it flaps its wings at great speed to release highly toxic dust into the air. | CH21: It loves the honey of flowers and can locate flower patches that have even tiny amounts of pollen. | CI21: It loves the honey of flowers and can locate flower patches that have even tiny amounts of pollen. | CJ21: It loves the honey of flowers and can locate flower patches that have even tiny amounts of pollen. | CK21: It collects honey every day. It rubs honey onto the hairs on its legs to carry it back to its nest. | CL21: Water-repellent powder on its wings enables it to collect honey, even in the heaviest of rains. | CM21: It loves the honey of flowers and can locate flower patches that have even tiny amounts of pollen. | CN21: It loves the honey of flowers and can locate flower patches that have even tiny amounts of pollen. | CO21: It loves the honey of flowers and can locate flower patches that have even tiny amounts of pollen. | CP21: It loves the honey of flowers and can locate flower patches that have even tiny amounts of pollen. | CQ21: It loves the honey of flowers and can locate flower patches that have even tiny amounts of pollen. | CR21: The wings are protected by rain-repellent dust. As a result, this Pokémon can fly about even in rain. | CS21: Butterfree has a superior ability to search for delicious honey from flowers. It can even search out, extract, and carry honey from flowers that are blooming over six miles from its nest. | CT21: Butterfree has a superior ability to search for delicious honey from flowers. It can even search out, extract, and carry honey from flowers that are blooming over six miles from its nest. | CU21: Close examination of its large eyes reveals that each eye is composed of a myriad of tiny eyes. | CV21: When attacked by other Pokémon, it defends itself by scattering its poisonous scales and fluttering its wings. | CW21: Its wings are covered in toxic scales. If it finds bird Pokémon going after Caterpie, Butterfree sprinkles its scales on them to drive them off. | CX21: Nectar from pretty flowers is its favorite food. In fields of flowers, it has heated battles with Cutiefly for territory. | CY21: Its wings, covered with poisonous powder, repel water. This allows it to fly in the rain. | CZ21: Its wings, covered with poisonous powder, repel water. This allows it to fly in the rain. | DA21: In battle, it flaps its wings at great speed to release highly toxic dust into the air. | DB21: It collects honey every day. It rubs honey onto the hairs on its legs to carry it back to its nest. | DE21: It loves the nectar of flowers and can locate flower patches that have even tiny amounts of pollen. | DF21: It loves the nectar of flowers and can locate flower patches that have even tiny amounts of pollen. | DP21: Evolve Caterpie / Metapod | DQ21: Evolve Caterpie / Metapod | DR21: Evolve Caterpie / Metapod | DS21: Route 2 , 26 , 27 , 34 , 35 , 36 , 37 , 38 , 39 , Azalea Town , Ilex Forest , Lake of Rage , National Park | DT21: National Park | DU21: Route 2 , 24 , 25 , Ilex Forest , National Park | DV21: Trade/migrate from another game | DW21: Trade/migrate from another game | DX21: Trade/migrate from another game | DY21: Evolve Caterpie / Metapod | DZ21: Evolve Caterpie / Metapod | EA21: Evolve Caterpie / Metapod | EB21: Evolve Caterpie / Metapod | EC21: Evolve Caterpie / Metapod | ED21: Route 2 , 47 , Ilex Forest , National Park , Viridian Forest | EE21: National Park | EF21: Trade/migrate from another game | EG21: Route 12 | EH21: Trade/migrate from another game | EI21: Trade/migrate from another game | EJ21: Evolve Caterpie / Metapod | EK21: Evolve Caterpie / Metapod | EL21: Trade/migrate from another game | EM21: Trade/migrate from another game | EN21: Route 5 , Melemele Meadow , Lush Jungle | EO21: Route 5 , Melemele Meadow , Lush Jungle | EP21: Route 5 , Melemele Meadow , Lush Jungle | EQ21: Route 5 , Melemele Meadow , Lush Jungle | ER21: Viridian Forest | ES21: Evolve Caterpie / Metapod | ET21: Rolling Fields , East Lake Axewell , Slumbering Weald , Giant's Mirror | EU21: Rolling Fields , East Lake Axewell , Slumbering Weald , Giant's Mirror | EX21: Evolve Caterpie / Metapod | EY21: Trade/migrate from another game | EZ21: Not available in this game | FA21: Location data not yet available | FB21: Location data not yet available | FE21: Location data not yet available
A22: 0012-01 | B22: 12 | C22: Butterfree Gigantamax | D22: =Sprite_Data!J5 | E22: =Sprite_Data!K5 | F22: =image("https://www.serebii.net/pokedex-bw/type/"&lower(H22)&".gif") | G22: =image("https://www.serebii.net/pokedex-bw/type/"&lower(I22)&".gif") | H22: Bug | I22: Flying | J22: Butterfly Pokémon
A23: 0013-00 | B23: 13 | C23: Weedle | D23: =image("https://img.pokemondb.net/sprites/home/normal/"& lower(C23) &".png") | E23: =image("https://img.pokemondb.net/sprites/home/shiny/"& lower(C23) &".png") | F23: =image("https://www.serebii.net/pokedex-bw/type/"&lower(H23)&".gif") | G23: =image("https://www.serebii.net/pokedex-bw/type/"&lower(I23)&".gif") | H23: Bug | I23: Poison | J23: Hairy Bug Pokémon | K23: 0.3 m (1′00″) | L23: 3.2 kg (7.1 lbs) | M23: Shield Dust | O23: Run Away | P23: 1 Speed | Q23: 255 (33.3% with PokéBall, full HP) | R23: 50 (normal) | S23: 39 | T23: Medium Fast | U23: Bug | W23: 50% male, 50% female | X23: 15 (3,599–3,855 steps) | Y23: 40 | Z23: 35 | AA23: 30 | AB23: 20 | AC23: 20 | AD23: 50 | AE23: =sum(Y23:AD23) -> 195 | AF23: Weedle → Kakuna (Level 7) → Beedrill (Level 10) | AG23: 0013 | AH23: 0013 | AI23: 0013 | AJ23: 0027 | AK23: 0027 | AL23: 0027 | AP23: 0013 | AQ23: 0013 | AU23: 0027 | AV23: 0027 | BA23: 0026 | BB23: 0026 | BI23: 0013 | BJ23: 0013 | BV23: 0018 | BW23: Often found in forests, eating leaves. It has a sharp venomous stinger on its head. | BX23: Often found in forests, eating leaves. It has a sharp venomous stinger on its head. | BY23: Beware of the sharp stinger on its head. It hides in grass and bushes where it eats leaves. | BZ23: Its poison stinger is very powerful. Its bright-colored body is intended to warn off its enemies. | CA23: It attacks using a two-inch poison barb on its head. It can usually be found under the leaves it eats. | CB23: The barb on top of its head secretes a strong poison. It uses this toxic barb to protect itself. | CC23: WEEDLE has an extremely acute sense of smell. It is capable of distinguishing its favorite kinds of leaves from those it dislikes just by sniffing with its big red proboscis (nose). | CD23: WEEDLE has an extremely acute sense of smell. It is capable of distinguishing its favorite kinds of leaves from those it dislikes just by sniffing with its big red proboscis (nose). | CE23: A WEEDLE has an extremely acute sense of smell. It distinguishes its favorite kinds of leaves from those it dislikes by sniffing with its big red proboscis (nose). | CF23: Often found in forests and grasslands. It has a sharp, toxic barb of around two inches on top of its head. | CG23: Often found in forests, eating leaves. It has a sharp stinger on its head that injects poison. | CH23: It eats its weight in leaves every day. It fends off attackers with the needle on its head. | CI23: It eats its weight in leaves every day. It fends off attackers with the needle on its head. | CJ23: It eats its weight in leaves every day. It fends off attackers with the needle on its head. | CK23: Its poison stinger is very powerful. Its bright-colored body is intended to warn off its enemies. | CL23: It attacks using a two-inch poison barb on its head. It can usually be found under the leaves it eats. | CM23: It eats its weight in leaves every day. It fends off attackers with the needle on its head. | CN23: It eats its weight in leaves every day. It fends off attackers with the needle on its head. | CO23: It eats its weight in leaves every day. It fends off attackers with the needle on its head. | CP23: It eats its weight in leaves every day. It fends off attackers with the needle on its head. | CQ23: Often found in forests and grasslands. It has a sharp, toxic barb of around two inches on top of its head. | CR23: Its poison stinger is very powerful. Its bright-colored body is intended to warn off its enemies. | CS23: Weedle has an extremely acute sense of smell. It is capable of distinguishing its favorite kinds of leaves from those it dislikes just by sniffing with its big red proboscis (nose). | CT23: Weedle has an extremely acute sense of smell. It is capable of distinguishing its favorite kinds of leaves from those it dislikes just by sniffing with its big red proboscis (nose). | CY23: Beware of the sharp stinger on its head. It hides in grass and bushes where it eats leaves. | CZ23: Beware of the sharp stinger on its head. It hides in grass and bushes where it eats leaves. | DE23: It eats its weight in leaves every day. It fends off attackers with the needle on its head. | DF23: It eats its weight in leaves every day. It fends off attackers with the needle on its head. | DP23: Route 2 , 24 , 25 , Viridian Forest | DQ23: Route 25 , Viridian Forest | DR23: Trade/migrate from another game | DS23: National Park | DT23: Route 2 , 26 , 27 , 30 , 31 , 34 , 35 , 36 , 37 , 38 , 39 , Azalea Town , Ilex Forest , Lake of Rage , National Park | DU23: Route 30 , 31 , Ilex Forest , National Park | DV23: Trade/migrate from another game | DW23: Trade/migrate from another game | DX23: Trade/migrate from another game | DY23: Route 2 , 24 , 25 , Pattern Bush , Viridian Forest | DZ23: Route 2 , 24 , 25 , Pattern Bush , Viridian Forest | EA23: Route 204 | EB23: Route 204 | EC23: Route 204 , Eterna Forest | ED23: National Park | EE23: Route 2 , 30 , 31 , Ilex Forest , National Park , Viridian Forest | EF23: Breed Kakuna / Beedrill | EG23: Trade/migrate from another game | EH23: Trade/migrate from another game | EI23: Trade/migrate from another game | EJ23: Route 2 , Santalune Forest | EK23: Santalune Forest | EL23: Breed Kakuna / Beedrill | EM23: Breed Kakuna / Beedrill | EN23: Trade/migrate from another game | EO23: Trade/migrate from another game | EP23: Breed Kakuna / Beedrill | EQ23: Breed Kakuna / Beedrill | ER23: Route 2 , Viridian Forest | ES23: Route 2 , Viridian Forest | ET23: Not available in this game | EU23: Not available in this game | EX23: Trade/migrate from another game | EY23: Spacious Cave , Grassland Cave , Swampy Cave , Riverbank Cave , Still-Water Cavern , Sunlit Cavern , Bogsunk Cavern | EZ23: Not available in this game | FA23: Location data not yet available | FB23: Location data not yet available | FE23: Location data not yet available
A24: 0014-00 | B24: 14 | C24: Kakuna | D24: =image("https://img.pokemondb.net/sprites/home/normal/"& lower(C24) &".png") | E24: =image("https://img.pokemondb.net/sprites/home/shiny/"& lower(C24) &".png") | F24: =image("https://www.serebii.net/pokedex-bw/type/"&lower(H24)&".gif") | G24: =image("https://www.serebii.net/pokedex-bw/type/"&lower(I24)&".gif") | H24: Bug | I24: Poison | J24: Cocoon Pokémon | K24: 0.6 m (2′00″) | L24: 10.0 kg (22.0 lbs) | M24: Shed Skin | N24: . | P24: 2 Defense | Q24: 120 (15.7% with PokéBall, full HP) | R24: 50 (normal) | S24: 72 | T24: Medium Fast | U24: Bug | W24: 50% male, 50% female | X24: 15 (3,599–3,855 steps) | Y24: 45 | Z24: 25 | AA24: 50 | AB24: 25 | AC24: 25 | AD24: 35 | AE24: =sum(Y24:AD24) -> 205 | AF24: Weedle → Kakuna (Level 7) → Beedrill (Level 10) | AG24: 0014 | AH24: 0014 | AI24: 0014 | AJ24: 0028 | AK24: 0028 | AL24: 0028 | AP24: 0014 | AQ24: 0014 | AU24: 0028 | AV24: 0028 | BA24: 0027 | BB24: 0027 | BI24: 0014 | BJ24: 0014 | BV24: 0019 | BW24: Almost incapable of moving, this POKéMON can only harden its shell to protect itself from predators. | BX24: Almost incapable of moving, this POKéMON can only harden its shell to protect itself from predators. | BY24: Able to move only slightly. When endangered, it may stick out its stinger and poison its enemy. | BZ24: Although it is a cocoon, it can move a little. It can extend its poison barb if it is attacked. | CA24: From this form, it will grow into an adult. As its body becomes softer, the external shell hardens. | CB24: Nearly incapable of movement, it leans against stout trees while waiting for its evolution. | CC24: KAKUNA remains virtually immobile as it clings to a tree. However, on the inside, it is extremely busy as it prepares for its coming evolution. This is evident from how hot the shell becomes to the touch. | CD24: KAKUNA remains virtually immobile as it clings to a tree. However, on the inside, it is extremely busy as it prepares for its coming evolution. This is evident from how hot the shell becomes to the touch. | CE24: It remains virtually immobile while it clings to a tree. However, on the inside, it busily prepares for evolution. This is evident from how hot its shell becomes. | CF24: This POKéMON is in a temporary stage while making its body. It is almost completely unable to move on its own. | CG24: Almost incapable of moving, this POKéMON can only harden its shell to protect itself when it is in danger. | CH24: While awaiting evolution, it hides from predators under leaves and in nooks of branches. | CI24: While awaiting evolution, it hides from predators under leaves and in nooks of branches. | CJ24: While awaiting evolution, it hides from predators under leaves and in nooks of branches. | CK24: Although it is a cocoon, it can move a little. It can extend its poison barb if it is attacked. | CL24: From this form, it will grow into an adult. As its body becomes softer, the external shell hardens. | CM24: While awaiting evolution, it hides from predators under leaves and in nooks of branches. | CN24: While awaiting evolution, it hides from predators under leaves and in nooks of branches. | CO24: While awaiting evolution, it hides from predators under leaves and in nooks of branches. | CP24: While awaiting evolution, it hides from predators under leaves and in nooks of branches. | CQ24: Almost incapable of moving, this Pokémon can only harden its shell to protect itself when it is in danger. | CR24: While awaiting evolution, it hides from predators under leaves and in nooks of branches. | CS24: Kakuna remains virtually immobile as it clings to a tree. However, on the inside, it is extremely busy as it prepares for its coming evolution. This is evident from how hot the shell becomes to the touch. | CT24: Kakuna remains virtually immobile as it clings to a tree. However, on the inside, it is extremely busy as it prepares for its coming evolution. This is evident from how hot the shell becomes to the touch. | CY24: Able to move only slightly. When endangered, it may stick out its stinger and poison its enemy. | CZ24: Able to move only slightly. When endangered, it may stick out its stinger and poison its enemy. | DE24: While awaiting evolution, it hides from predators under leaves and in nooks of branches. | DF24: While awaiting evolution, it hides from predators under leaves and in nooks of branches. | DP24: Route 24 , 25 , Viridian Forest | DQ24: Route 25 , Viridian Forest | DR24: Trade/migrate from another game | DS24: National Park | DT24: Route 2 , 26 , 27 , 30 , 31 , 34 , 35 , 36 , 37 , 38 , 39 , Azalea Town , Ilex Forest , Lake of Rage , National Park | DU24: Ilex Forest , National Park | DV24: Trade/migrate from another game | DW24: Trade/migrate from another game | DX24: Trade/migrate from another game | DY24: Route 24 , 25 , Pattern Bush , Viridian Forest | DZ24: Route 24 , 25 , Pattern Bush , Viridian Forest | EA24: Eterna Forest | EB24: Eterna Forest | EC24: Eterna Forest | ED24: National Park | EE24: Route 2 , 30 , 31 , 47 , Ilex Forest , National Park , Viridian Forest | EF24: Route 12 | EG24: Trade/migrate from another game | EH24: Trade/migrate from another game | EI24: Trade/migrate from another game | EJ24: Santalune Forest | EK24: Evolve Weedle | EL24: Safari Zone | EM24: Safari Zone | EN24: Trade/migrate from another game | EO24: Trade/migrate from another game | EP24: Evolve Weedle | EQ24: Evolve Weedle | ER24: Viridian Forest | ES24: Viridian Forest | ET24: Not available in this game | EU24: Not available in this game | EX24: Trade/migrate from another game | EY24: Evolve Weedle | EZ24: Not available in this game | FA24: Location data not yet available | FB24: Location data not yet available | FE24: Location data not yet available
A25: 0015-00 | B25: 15 | C25: Beedrill | D25: =image("https://img.pokemondb.net/sprites/home/normal/"& lower(C25) &".png") | E25: =image("https://img.pokemondb.net/sprites/home/shiny/"& lower(C25) &".png") | F25: =image("https://www.serebii.net/pokedex-bw/type/"&lower(H25)&".gif") | G25: =image("https://www.serebii.net/pokedex-bw/type/"&lower(I25)&".gif") | H25: Bug | I25: Poison | J25: Poison Bee Pokémon | K25: 1.0 m (3′03″) | L25: 29.5 kg (65.0 lbs) | M25: Swarm | O25: Sniper | P25: 2 Attack, 1 Sp. Def | Q25: 45 (5.9% with PokéBall, full HP) | R25: 50 (normal) | S25: 178 | T25: Medium Fast | U25: Bug | W25: 50% male, 50% female | X25: 15 (3,599–3,855 steps) | Y25: 65 | Z25: 90 | AA25: 40 | AB25: 45 | AC25: 80 | AD25: 75 | AE25: =sum(Y25:AD25) -> 395 | AF25: Weedle → Kakuna (Level 7) → Beedrill (Level 10) | AG25: 0015 | AH25: 0015 | AI25: 0015 | AJ25: 0029 | AK25: 0029 | AL25: 0029 | AP25: 0015 | AQ25: 0015 | AU25: 0029 | AV25: 0029 | BA25: 0028 | BB25: 0028 | BI25: 0015 | BJ25: 0015 | BV25: 0020 | BW25: Flies at high speed and attacks using its large venomous stingers on its forelegs and tail. | BX25: Flies at high speed and attacks using its large venomous stingers on its forelegs and tail. | BY25: It has 3 poisonous stingers on its forelegs and its tail. They are used to jab its enemy repeatedly. | BZ25: It can take down any opponent with its powerful poison stingers. It sometimes attacks in swarms. | CA25: It has three poison barbs. The barb on its tail secretes the most powerful poison. | CB25: It uses sharp, poisonous stings to defeat prey, then takes the victim back to its nest for food. | CC25: BEEDRILL is extremely territorial. No one should ever approach its nest - this is for their own safety. If angered, they will attack in a furious swarm. | CD25: BEEDRILL is extremely territorial. No one should ever approach its nest - this is for their own safety. If angered, they will attack in a furious swarm. | CE25: A BEEDRILL is extremely territorial. For safety reasons, no one should ever approach its nest. If angered, they will attack in a swarm. | CF25: May appear in a swarm. Flies at violent speeds, all the while stabbing with the toxic stinger on its rear. | CG25: It flies at high speed and attacks using the large venomous stingers on its forelegs and tail. | CH25: Its best attack involves flying around at high speed, striking with poison needles, then flying off. | CI25: Its best attack involves flying around at high speed, striking with poison needles, then flying off. | CJ25: Its best attack involves flying around at high speed, striking with poison needles, then flying off. | CK25: It can take down any opponent with its powerful poison stingers. It sometimes attacks in swarms. | CL25: It has three poison barbs. The barb on its tail secretes the most powerful poison. | CM25: Its best attack involves flying around at high speed, striking with poison needles, then flying off. | CN25: Its best attack involves flying around at high speed, striking with poison needles, then flying off. | CO25: Its best attack involves flying around at high speed, striking with poison needles, then flying off. | CP25: Its best attack involves flying around at high speed, striking with poison needles, then flying off. | CQ25: It has three poisonous stingers on its forelegs and its tail. They are used to jab its enemy repeatedly. | CR25: May appear in a swarm. Flies at violent speeds, all the while stabbing with the toxic stinger on its rear. | CS25: Beedrill is extremely territorial. No one should ever approach its nest—this is for their own safety. If angered, they will attack in a furious swarm. | CT25: Beedrill is extremely territorial. No one should ever approach its nest—this is for their own safety. If angered, they will attack in a furious swarm. | CY25: It has three poisonous stingers on its forelegs and its tail. They are used to jab its enemy repeatedly. | CZ25: It has three poisonous stingers on its forelegs and its tail. They are used to jab its enemy repeatedly. | DE25: Its best attack involves flying around at high speed, striking with poison needles, then flying off. | DF25: Its best attack involves flying around at high speed, striking with poison needles, then flying off. | DP25: Evolve Weedle / Kakuna | DQ25: Evolve Weedle / Kakuna | DR25: Trade/migrate from another game | DS25: National Park | DT25: Route 2 , 26 , 27 , 34 , 35 , 36 , 37 , 38 , 39 , Azalea Town , Ilex Forest , Lake of Rage , National Park | DU25: Ilex Forest , National Park | DV25: Trade/migrate from another game | DW25: Trade/migrate from another game | DX25: Trade/migrate from another game | DY25: Evolve Weedle / Kakuna | DZ25: Evolve Weedle / Kakuna | EA25: Evolve Weedle / Kakuna | EB25: Evolve Weedle / Kakuna | EC25: Evolve Weedle / Kakuna | ED25: National Park | EE25: Route 2 , 47 , Ilex Forest , National Park , Viridian Forest | EF25: Route 12 | EG25: Trade/migrate from another game | EH25: Trade/migrate from another game | EI25: Trade/migrate from another game | EJ25: Evolve Weedle / Kakuna | EK25: Evolve Weedle / Kakuna | EL25: Evolve Weedle / Kakuna | EM25: Evolve Weedle / Kakuna | EN25: Trade/migrate from another game | EO25: Trade/migrate from another game | EP25: Route 4 | EQ25: Route 4 | ER25: Evolve Weedle / Kakuna | ES25: Viridian Forest | ET25: Not available in this game | EU25: Not available in this game | EX25: Trade/migrate from another game | EY25: Evolve Weedle / Kakuna | EZ25: Not available in this game | FA25: Location data not yet available | FB25: Location data not yet available | FE25: Location data not yet available
A26: 0015-01 | B26: 15 | C26: Mega Beedrill | D26: =Sprite_Data!F6 | E26: =Sprite_Data!G6 | F26: =image("https://www.serebii.net/pokedex-bw/type/"&lower(H26)&".gif") | G26: =image("https://www.serebii.net/pokedex-bw/type/"&lower(I26)&".gif") | H26: Bug | I26: Poison | J26: Poison Bee Pokémon | K26: 1.4 m (4′07″) | L26: 40.5 kg (89.3 lbs) | M26: Adaptability | P26: 2 Attack, 1 Sp. Def | Q26: 45 (5.9% with PokéBall, full HP) | R26: 50 (normal) | S26: 223 | U26: Bug | W26: 50% male, 50% female | X26: 16 (3,599–3,855 steps) | Y26: 65 | Z26: 150 | AA26: 40 | AB26: 15 | AC26: 80 | AD26: 145 | AE26: =sum(Y26:AD26) -> 495
A27: 0016-00 | B27: 16 | C27: Pidgey | D27: =image("https://img.pokemondb.net/sprites/home/normal/"& lower(C27) &".png") | E27: =image("https://img.pokemondb.net/sprites/home/shiny/"& lower(C27) &".png") | F27: =image("https://www.serebii.net/pokedex-bw/type/"&lower(H27)&".gif") | G27: =image("https://www.serebii.net/pokedex-bw/type/"&lower(I27)&".gif") | H27: Normal | I27: Flying | J27: Tiny Bird Pokémon | K27: 0.3 m (1′00″) | L27: 1.8 kg (4.0 lbs) | M27: Keen Eye | N27: Tangled Feet | O27: Big Pecks | P27: 1 Speed | Q27: 255 (33.3% with PokéBall, full HP) | R27: 50 (normal) | S27: 50 | T27: Medium Slow | U27: Flying | W27: 50% male, 50% female | X27: 15 (3,599–3,855 steps) | Y27: 40 | Z27: 45 | AA27: 40 | AB27: 35 | AC27: 35 | AD27: 56 | AE27: =sum(Y27:AD27) -> 251 | AF27: Pidgey → Pidgeotto (Level 18) → Pidgeot (Level 36) | AG27: 0016 | AH27: 0016 | AI27: 0016 | AJ27: 0010 | AK27: 0010 | AL27: 0010 | AP27: 0016 | AQ27: 0016 | AU27: 0010 | AV27: 0010 | BA27: 0017 | BB27: 0017 | BI27: 0016 | BJ27: 0016 | BV27: 0021 | BW27: A common sight in forests and woods. It flaps its wings at ground level to kick up blinding sand. | BX27: A common sight in forests and woods. It flaps its wings at ground level to kick up blinding sand. | BY27: Very docile. If attacked, it will often kick up sand to protect itself rather than fight back. | BZ27: It usually hides in tall grass. Because it dislikes fighting, it protects itself by kicking up sand. | CA27: Common in grassy areas and forests, it is very docile and will chase off enemies by flapping up sand. | CB27: It rapidly flaps its wings in the grass, stirring up a dust cloud that drives insect prey out into the open. | CC27: PIDGEY has an extremely sharp sense of direction. It is capable of unerringly returning home to its nest, however far it may be removed from its familiar surroundings. | CD27: PIDGEY has an extremely sharp sense of direction. It is capable of unerringly returning home to its nest, however far it may be removed from its familiar surroundings. | CE27: It has an extremely sharp sense of direction. It can unerringly return home to its nest, however far it may be removed from its familiar surroundings. | CF27: Does not like to fight. It hides in tall grass and so on, foraging for food such as small bugs. | CG27: A common sight in forests and woods. It flaps its wings at ground level to kick up blinding sand. | CH27: It is docile and prefers to avoid conflict. If disturbed, however, it can ferociously strike back. | CI27: It is docile and prefers to avoid conflict. If disturbed, however, it can ferociously strike back. | CJ27: It is docile and prefers to avoid conflict. If disturbed, however, it can ferociously strike back. | CK27: It usually hides in tall grass. Because it dislikes fighting, it protects itself by kicking up sand. | CL27: Common in grassy areas and forests, it is very docile and will chase off enemies by flapping up sand. | CM27: It is docile and prefers to avoid conflict. If disturbed, however, it can ferociously strike back. | CN27: It is docile and prefers to avoid conflict. If disturbed, however, it can ferociously strike back. | CO27: It is docile and prefers to avoid conflict. If disturbed, however, it can ferociously strike back. | CP27: It is docile and prefers to avoid conflict. If disturbed, however, it can ferociously strike back. | CQ27: A common sight in forests and woods. It flaps its wings at ground level to kick up blinding sand. | CR27: It is docile and prefers to avoid conflict. If disturbed, however, it can ferociously strike back. | CS27: Pidgey has an extremely sharp sense of direction. It is capable of unerringly returning home to its nest, however far it may be removed from its familiar surroundings. | CT27: Pidgey has an extremely sharp sense of direction. It is capable of unerringly returning home to its nest, however far it may be removed from its familiar surroundings. | CY27: Very docile. If attacked, it will often kick up sand to protect itself rather than fight back. | CZ27: Very docile. If attacked, it will often kick up sand to protect itself rather than fight back. | DE27: It is docile and prefers to avoid conflict. If disturbed, however, it can ferociously strike back. | DF27: It is docile and prefers to avoid conflict. If disturbed, however, it can ferociously strike back. | DP27: Route 1 , 2 , 3 , 5 , 6 , 7 , 8 , 12 , 13 , 14 , 15 , 21 , 24 , 25 | DQ27: Route 1 , 2 , 3 , 5 , 6 , 7 , 8 , 12 , 13 , 14 , 15 , 21 , 24 , 25 | DR27: Route 1 , 2 , 5 , 6 , 7 , 8 , 11 , 12 , 13 , 21 , 24 , 25 , Viridian Forest | DS27: Route 1 , 2 , 5 , 6 , 25 , 29 , 30 , 31 , 35 , 36 , 37 , National Park | DT27: Route 1 , 2 , 5 , 6 , 25 , 29 , 30 , 31 , 35 , 36 , 37 , National Park | DU27: Route 1 , 2 , 5 , 25 , 29 , 30 , 31 , 32 , 34 , 35 , 36 , 37 , Ilex Forest , National Park | DV27: Trade/migrate from another game | DW27: Trade/migrate from another game | DX27: Trade/migrate from another game | DY27: Route 1 , 2 , 3 , 5 , 6 , 7 , 8 , 12 , 13 , 14 , 15 , 24 , 25 , Berry Forest , Bond Bridge , Five Isle Meadow | DZ27: Route 1 , 2 , 3 , 5 , 6 , 7 , 8 , 12 , 13 , 14 , 15 , 24 , 25 , Berry Forest , Bond Bridge , Five Isle Meadow | EA27: Route 229 | EB27: Route 229 | EC27: Route 229 | ED27: Route 1 , 2 , 5 , 6 , 25 , 29 , 30 , 31 , 35 , 36 , 37 , National Park , Viridian Forest | EE27: Route 1 , 2 , 5 , 6 , 25 , 29 , 30 , 31 , 35 , 36 , 37 , National Park , Viridian Forest | EF27: Trade/migrate from another game | EG27: White Forest | EH27: Trade/migrate from another game | EI27: Trade/migrate from another game | EJ27: Route 2 , 3 | EK27: Route 2 , 3 | EL27: Breed Pidgeotto / Pidgeot | EM27: Breed Pidgeotto / Pidgeot | EN27: Trade/migrate from another game | EO27: Trade/migrate from another game | EP27: Breed Pidgeotto / Pidgeot | EQ27: Breed Pidgeotto / Pidgeot | ER27: Route 1 , 2 , 5 , 6 , 7 , 8 , 11 , 12 , 13 , 14 , 15 , 16 , 17 , 18 , 19 , 20 , 21 , 24 , 25 , Cerulean City , Cinnabar Island , Fuchsia City , Lavender Town , Pallet Town , Pewter City , Vermilion City , Viridian City , Viridian Forest | ES27: Route 1 , 2 , 5 , 6 , 7 , 8 , 11 , 12 , 13 , 14 , 15 , 16 , 17 , 18 , 19 , 20 , 21 , 24 , 25 , Cerulean City , Cinnabar Island , Fuchsia City , Lavender Town , Pallet Town , Pewter City , Vermilion City , Viridian City , Viridian Forest | ET27: Not available in this game | EU27: Not available in this game | EX27: Route 229 | EY27: Route 229 | EZ27: Not available in this game | FA27: Location data not yet available | FB27: Location data not yet available | FE27: Location data not yet available
A28: 0017-00 | B28: 17 | C28: Pidgeotto | D28: =image("https://img.pokemondb.net/sprites/home/normal/"& lower(C28) &".png") | E28: =image("https://img.pokemondb.net/sprites/home/shiny/"& lower(C28) &".png") | F28: =image("https://www.serebii.net/pokedex-bw/type/"&lower(H28)&".gif") | G28: =image("https://www.serebii.net/pokedex-bw/type/"&lower(I28)&".gif") | H28: Normal | I28: Flying | J28: Bird Pokémon | K28: 1.1 m (3′07″) | L28: 30.0 kg (66.1 lbs) | M28: Keen Eye | N28: Tangled Feet | O28: Big Pecks | P28: 2 Speed | Q28: 120 (15.7% with PokéBall, full HP) | R28: 50 (normal) | S28: 122 | T28: Medium Slow | U28: Flying | W28: 50% male, 50% female | X28: 15 (3,599–3,855 steps) | Y28: 63 | Z28: 60 | AA28: 55 | AB28: 50 | AC28: 50 | AD28: 71 | AE28: =sum(Y28:AD28) -> 349 | AF28: Pidgey → Pidgeotto (Level 18) → Pidgeot (Level 36) | AG28: 0017 | AH28: 0017 | AI28: 0017 | AJ28: 0011 | AK28: 0011 | AL28: 0011 | AP28: 0017 | AQ28: 0017 | AU28: 0011 | AV28: 0011 | BA28: 0018 | BB28: 0018 | BI28: 0017 | BJ28: 0017 | BV28: 0022 | BW28: Very protective of its sprawling territorial area, this POKéMON will fiercely peck at any intruder. | BX28: Very protective of its sprawling territorial area, this POKéMON will fiercely peck at any intruder. | BY28: This POKéMON is full of vitality. It constantly flies around its large territory in search of prey. | BZ28: It has outstanding vision. However high it flies, it is able to distinguish the movements of its prey. | CA28: It immobilizes its prey using well-developed claws, then carries the prey more than 60 miles to its nest. | CB28: It slowly flies in a circular pattern, all the while keeping a sharp lookout for prey. | CC28: PIDGEOTTO claims a large area as its own territory. This POKéMON flies around, patrolling its living space. If its territory is violated, it shows no mercy in thoroughly punishing the foe with its sharp claws. | CD28: PIDGEOTTO claims a large area as its own territory. This POKéMON flies around, patrolling its living space. If its territory is violated, it shows no mercy in thoroughly punishing the foe with its sharp claws. | CE28: This POKéMON flies around, patrolling its large territory. If its living space is violated, it shows no mercy in thoroughly punishing the foe with its sharp claws. | CF28: The claws on its feet are well developed. It can carry prey such as an EXEGGCUTE to its nest over 60 miles away. | CG28: Very protective of its sprawling territorial area, this POKéMON will fiercely peck at any intruder. | CH28: It flies over its wide territory in search of prey, downing it with its highly developed claws. | CI28: It flies over its wide territory in search of prey, downing it with its highly developed claws. | CJ28: It flies over its wide territory in search of prey, downing it with its highly developed claws. | CK28: It has outstanding vision. However high it flies, it is able to distinguish the movements of its prey. | CL28: It renders its prey immobile using well-developed claws, then carries the prey more than 60 miles to its nest. | CM28: It flies over its wide territory in search of prey, downing it with its highly developed claws. | CN28: It flies over its wide territory in search of prey, downing it with its highly developed claws. | CO28: It flies over its wide territory in search of prey, downing it with its highly developed claws. | CP28: It flies over its wide territory in search of prey, downing it with its highly developed claws. | CQ28: The claws on its feet are well developed. It can carry prey such as an Exeggcute to its nest over 60 miles away. | CR28: Very protective of its sprawling territorial area, this Pokémon will fiercely peck at any intruder. | CS28: Pidgeotto claims a large area as its own territory. This Pokémon flies around, patrolling its living space. If its territory is violated, it shows no mercy in thoroughly punishing the foe with its sharp claws. | CT28: Pidgeotto claims a large area as its own territory. This Pokémon flies around, patrolling its living space. If its territory is violated, it shows no mercy in thoroughly punishing the foe with its sharp claws. | CY28: This Pokémon is full of vitality. It constantly flies around its large territory in search of prey. | CZ28: This Pokémon is full of vitality. It constantly flies around its large territory in search of prey. | DE28: It flies over its wide territory in search of prey, downing it with its highly developed claws. | DF28: It flies over its wide territory in search of prey, downing it with its highly developed claws. | DP28: Route 14 , 15 , 21 | DQ28: Route 14 , 15 , 21 | DR28: Route 5 , 6 , 7 , 8 , 11 , 12 , 13 , 14 , 15 , 21 , 24 , 25 , Viridian Forest | DS28: Route 2 , 8 , 13 , 14 , 15 , 25 , 37 , 43 | DT28: Route 2 , 8 , 13 , 14 , 15 , 25 , 37 , 43 | DU28: Route 2 , 5 , 8 , 11 , 13 , 14 , 15 , 25 , 37 , 38 , 39 , 43 | DV28: Trade/migrate from another game | DW28: Trade/migrate from another game | DX28: Trade/migrate from another game | DY28: Route 13 , 14 , 15 , Berry Forest , Bond Bridge , Five Isle Meadow | DZ28: Route 13 , 14 , 15 , Berry Forest , Bond Bridge , Five Isle Meadow | EA28: Evolve Pidgey | EB28: Evolve Pidgey | EC28: Evolve Pidgey | ED28: Route 2 , 8 , 13 , 14 , 15 , 25 , 37 , 43 , Viridian Forest | EE28: Route 2 , 8 , 13 , 14 , 15 , 25 , 37 , 43 , Viridian Forest | EF28: Trade/migrate from another game | EG28: Evolve Pidgey | EH28: Trade/migrate from another game | EI28: Trade/migrate from another game | EJ28: Evolve Pidgey | EK28: Evolve Pidgey | EL28: Safari Zone | EM28: Safari Zone | EN28: Trade/migrate from another game | EO28: Trade/migrate from another game | EP28: Evolve Pidgey | EQ28: Evolve Pidgey | ER28: Route 1 , 2 , 5 , 6 , 7 , 8 , 11 , 12 , 13 , 14 , 15 , 16 , 17 , 18 , 19 , 20 , 21 , 24 , 25 , Cerulean City , Cinnabar Island , Fuchsia City , Lavender Town , Pallet Town , Pewter City , Vermilion City , Viridian City | ES28: Route 1 , 2 , 5 , 6 , 7 , 8 , 11 , 12 , 13 , 14 , 15 , 16 , 17 , 18 , 19 , 20 , 21 , 24 , 25 , Cerulean City , Cinnabar Island , Fuchsia City , Lavender Town , Pallet Town , Pewter City , Vermilion City , Viridian City | ET28: Not available in this game | EU28: Not available in this game | EX28: Evolve Pidgey | EY28: Evolve Pidgey | EZ28: Not available in this game | FA28: Location data not yet available | FB28: Location data not yet available | FE28: Location data not yet available
A29: 0018-00 | B29: 18 | C29: Pidgeot | D29: =image("https://img.pokemondb.net/sprites/home/normal/"& lower(C29) &".png") | E29: =image("https://img.pokemondb.net/sprites/home/shiny/"& lower(C29) &".png") | F29: =image("https://www.serebii.net/pokedex-bw/type/"&lower(H29)&".gif") | G29: =image("https://www.serebii.net/pokedex-bw/type/"&lower(I29)&".gif") | H29: Normal | I29: Flying | J29: Bird Pokémon | K29: 1.5 m (4′11″) | L29: 39.5 kg (87.1 lbs) | M29: Keen Eye | N29: Tangled Feet | O29: Big Pecks | P29: 3 Speed | Q29: 45 (5.9% with PokéBall, full HP) | R29: 50 (normal) | S29: 216 | T29: Medium Slow | U29: Flying | W29: 50% male, 50% female | X29: 15 (3,599–3,855 steps) | Y29: 83 | Z29: 80 | AA29: 75 | AB29: 70 | AC29: 70 | AD29: 101 | AE29: =sum(Y29:AD29) -> 479 | AF29: Pidgey → Pidgeotto (Level 18) → Pidgeot (Level 36) | AG29: 0018 | AH29: 0018 | AI29: 0018 | AJ29: 0012 | AK29: 0012 | AL29: 0012 | AP29: 0018 | AQ29: 0018 | AU29: 0012 | AV29: 0012 | BA29: 0019 | BB29: 0019 | BI29: 0018 | BJ29: 0018 | BV29: 0023 | BW29: When hunting, it skims the surface of water at high speed to pick off unwary prey such as MAGIKARP. | BX29: When hunting, it skims the surface of water at high speed to pick off unwary prey such as MAGIKARP. | BY29: This POKéMON flies at Mach 2 speed, seeking prey. Its large talons are feared as wicked weapons. | BZ29: Its well-developed chest muscles make it strong enough to whip up a gusty windstorm with just a few flaps. | CA29: It spreads its beautiful wings wide to frighten its enemies. It can fly at Mach 2 speed. | CB29: Its outstanding vision allows it to spot splashing MAGIKARP, even while flying at 3300 feet. | CC29: This POKéMON has a dazzling plumage of beautifully glossy feathers. Many TRAINERS are captivated by the striking beauty of the feathers on its head, compelling them to choose PIDGEOT as their POKéMON. | CD29: This POKéMON has a dazzling plumage of beautifully glossy feathers. Many TRAINERS are captivated by the striking beauty of the feathers on its head, compelling them to choose PIDGEOT as their POKéMON. | CE29: This POKéMON has gorgeous, glossy feathers. Many TRAINERS are so captivated by the beautiful feathers on its head that they choose PIDGEOT as their POKéMON. | CF29: It spreads its gorgeous wings widely to intimidate enemies. It races through the skies at Mach-2 speed. | CG29: When hunting, it skims the surface of water at high speed to pick off unwary prey such as MAGIKARP. | CH29: By flapping its wings with all its might, PIDGEOT can make a gust of wind capable of bending tall trees. | CI29: By flapping its wings with all its might, PIDGEOT can make a gust of wind capable of bending tall trees. | CJ29: By flapping its wings with all its might, PIDGEOT can make a gust of wind capable of bending tall trees. | CK29: Its well-developed chest muscles make it strong enough to whip up a gusty windstorm with just a few flaps. | CL29: It spreads its beautiful wings wide to frighten its enemies. It can fly at Mach 2 speed. | CM29: By flapping its wings with all its might, Pidgeot can make a gust of wind capable of bending tall trees. | CN29: By flapping its wings with all its might, Pidgeot can make a gust of wind capable of bending tall trees. | CO29: By flapping its wings with all its might, Pidgeot can make a gust of wind capable of bending tall trees. | CP29: By flapping its wings with all its might, Pidgeot can make a gust of wind capable of bending tall trees. | CQ29: When hunting, it skims the surface of water at high speed to pick off unwary prey such as Magikarp. | CR29: It spreads its gorgeous wings widely to intimidate enemies. It races through the skies at Mach-2 speed. | CS29: This Pokémon has a dazzling plumage of beautifully glossy feathers. Many Trainers are captivated by the striking beauty of the feathers on its head, compelling them to choose Pidgeot as their Pokémon. | CT29: This Pokémon has a dazzling plumage of beautifully glossy feathers. Many Trainers are captivated by the striking beauty of the feathers on its head, compelling them to choose Pidgeot as their Pokémon. | CY29: This Pokémon flies at Mach 2 speed, seeking prey. Its large talons are feared as wicked weapons. | CZ29: This Pokémon flies at Mach 2 speed, seeking prey. Its large talons are feared as wicked weapons. | DE29: By flapping its wings with all its might, Pidgeot can make a gust of wind capable of bending tall trees. | DF29: By flapping its wings with all its might, Pidgeot can make a gust of wind capable of bending tall trees. | DP29: Evolve Pidgey / Pidgeotto | DQ29: Evolve Pidgey / Pidgeotto | DR29: Evolve Pidgey / Pidgeotto | DS29: Evolve Pidgey / Pidgeotto | DT29: Evolve Pidgey / Pidgeotto | DU29: Evolve Pidgey / Pidgeotto | DV29: Trade/migrate from another game | DW29: Trade/migrate from another game | DX29: Trade/migrate from another game | DY29: Evolve Pidgey / Pidgeotto | DZ29: Evolve Pidgey / Pidgeotto | EA29: Evolve Pidgey / Pidgeotto | EB29: Evolve Pidgey / Pidgeotto | EC29: Evolve Pidgey / Pidgeotto | ED29: Evolve Pidgey / Pidgeotto | EE29: Evolve Pidgey / Pidgeotto | EF29: Trade/migrate from another game | EG29: Evolve Pidgey / Pidgeotto | EH29: Trade/migrate from another game | EI29: Trade/migrate from another game | EJ29: Evolve Pidgey / Pidgeotto | EK29: Evolve Pidgey / Pidgeotto | EL29: Evolve Pidgey / Pidgeotto | EM29: Evolve Pidgey / Pidgeotto | EN29: Trade/migrate from another game | EO29: Trade/migrate from another game | EP29: Route 10 | EQ29: Route 10 | ER29: Route 1 , 2 , 5 , 6 , 7 , 8 , 11 , 12 , 13 , 14 , 15 , 16 , 17 , 18 , 19 , 20 , 21 , 24 , 25 , Cerulean City , Cinnabar Island , Fuchsia City , Lavender Town , Pallet Town , Pewter City , Vermilion City , Viridian City | ES29: Route 1 , 2 , 5 , 6 , 7 , 8 , 11 , 12 , 13 , 14 , 15 , 16 , 17 , 18 , 19 , 20 , 21 , 24 , 25 , Cerulean City , Cinnabar Island , Fuchsia City , Lavender Town , Pallet Town , Pewter City , Vermilion City , Viridian City | ET29: Not available in this game | EU29: Not available in this game | EX29: Evolve Pidgey / Pidgeotto | EY29: Evolve Pidgey / Pidgeotto | EZ29: Not available in this game | FA29: Location data not yet available | FB29: Location data not yet available | FE29: Location data not yet available
A30: 0019-00 | B30: 19 | C30: Rattata | D30: =image("https://img.pokemondb.net/sprites/home/normal/"& lower(C30) &".png") | E30: =image("https://img.pokemondb.net/sprites/home/shiny/"& lower(C30) &".png") | F30: =image("https://www.serebii.net/pokedex-bw/type/"&lower(H30)&".gif") | G30: =image("https://www.serebii.net/pokedex-bw/type/"&lower(I30)&".gif") | H30: Normal | J30: Mouse Pokémon | K30: 0.3 m (1′00″) | L30: 3.5 kg (7.7 lbs) | M30: Run Away | N30: Guts | O30: Hustle | P30: 1 Speed | Q30: 255 (33.3% with PokéBall, full HP) | R30: 50 (normal) | S30: 51 | T30: Medium Fast | U30: F | V30: i | W30: 50% male, 50% female | X30: 15 (3,599–3,855 steps) | Y30: 30 | Z30: 56 | AA30: 35 | AB30: 25 | AC30: 35 | AD30: 72 | AE30: =sum(Y30:AD30) -> 253 | AF30: Rattata → Raticate (Level 20) | AG30: 0019 | AH30: 0019 | AI30: 0019 | AJ30: 0017 | AK30: 0017 | AL30: 0017 | AP30: 0019 | AQ30: 0019 | AU30: 0017 | AV30: 0017 | AY30: 0059 | AZ30: 0059 | BE30: 0015 | BF30: 0015 | BG30: 0015 | BH30: 0015 | BI30: 0019 | BJ30: 0019 | BW30: Bites anything when it attacks. Small and very quick, it is a common sight in many places. | BX30: Bites anything when it attacks. Small and very quick, it is a common sight in many places. | BY30: Will chew on anything with its fangs. If you see one, it is certain that 40 more live in the area. | BZ30: It eats anything. Wherever food is available, it will settle down and produce offspring continuously. | CA30: Living wherever there is food available, it ceaselessly scavenges for edibles the entire day. | CB30: This POKéMON’s impressive vitality allows it to live anywhere. It also multiplies very quickly. | CC30: RATTATA is cautious in the extreme. Even while it is asleep, it constantly listens by moving its ears around. It is not picky about where it lives - it will make its nest anywhere. | CD30: RATTATA is cautious in the extreme. Even while it is asleep, it constantly listens by moving its ears around. It is not picky about where it lives - it will make its nest anywhere. | CE30: A RATTATA is cautious in the extreme. Even while it is asleep, it constantly moves its ears and listens for danger. It will make its nest anywhere. | CF30: Its fangs are long and very sharp. They grow continuously, so it gnaws on hard things to whittle them down. | CG30: Bites anything when it attacks. Small and very quick, it is a common sight in many places. | CH30: Cautious in the extreme, its hardy vitality lets it live in any kind of environment. | CI30: Cautious in the extreme, its hardy vitality lets it live in any kind of environment. | CJ30: Cautious in the extreme, its hardy vitality lets it live in any kind of environment. | CK30: It eats anything. Wherever food is available, it will settle down and produce offspring continuously. | CL30: Living wherever there is food available, it ceaselessly scavenges for edibles the entire day. | CM30: Cautious in the extreme, its hardy vitality lets it live in any kind of environment. | CN30: Cautious in the extreme, its hardy vitality lets it live in any kind of environment. | CO30: It searches for food all day. It gnaws on hard objects to wear down its fangs, which grow constantly during its lifetime. | CP30: It searches for food all day. It gnaws on hard objects to wear down its fangs, which grow constantly during its lifetime. | CQ30: Living wherever there is food available, it ceaselessly scavenges for edibles the entire day. | CR30: Its fangs are long and very sharp. They grow continuously, so it gnaws on hard things to whittle them down. | CS30: Rattata is cautious in the extreme. Even while it is asleep, it constantly listens by moving its ears around. It is not picky about where it lives—it will make its nest anywhere. | CT30: Rattata is cautious in the extreme. Even while it is asleep, it constantly listens by moving its ears around. It is not picky about where it lives—it will make its nest anywhere. | CU30: Its incisors continue growing until its death. If its Trainer doesn’t offer it a file to gnaw on, it will gnaw on door frames, table legs, and so on. | CV30: With their strong capacity for survival, they can live in dirty places without concern. Left unchecked, their numbers multiply rapidly. | CW30: Its incisors grow continuously throughout its life. If its incisors get too long, this Pokémon becomes unable to eat, and it starves to death. | CX30: This Pokémon is common but hazardous. Its sharp incisors can easily cut right through hard wood. | CY30: Will chew on anything with its fangs. If you see one, you can be certain that 40 more live in the area. | CZ30: Will chew on anything with its fangs. If you see one, you can be certain that 40 more live in the area. | DE30: It’s cautious in the extreme, and its hardy vitality lets it live in any kind of environment. | DF30: It’s cautious in the extreme, and its hardy vitality lets it live in any kind of environment. | DP30: Route 1 , 2 , 4 , 9 , 16 , 21 , 22 | DQ30: Route 1 , 2 , 4 , 9 , 16 , 21 , 22 | DR30: Route 1 , 2 , 3 , 4 , 5 , 6 , 7 , 8 , 9 , 10 , 11 , 16 , 18 , 21 , 22 , Pokémon Mansion | DS30: Route 1 , 3 , 4 , 7 , 9 , 11 , 22 , 29 , 30 , 31 , 32 , 33 , 34 , 38 , 39 , 46 , Burned Tower , Mt. Mortar , Sprout Tower , Tin Tower , Tohjo Falls , Union Cave | DT30: Route 1 , 3 , 4 , 7 , 9 , 11 , 22 , 29 , 30 , 31 , 32 , 33 , 34 , 46 , Burned Tower , Mt. Mortar , Sprout Tower , Tin Tower , Tohjo Falls , Union Cave | DU30: Route 1 , 3 , 4 , 6 , 7 , 9 , 11 , 21 , 22 , 29 , 32 , 33 , 34 , 38 , 39 , 42 , 46 , Burned Tower , Mt. Mortar , Sprout Tower , Tin Tower , Tohjo Falls , Union Cave | DV30: Trade/migrate from another game | DW30: Trade/migrate from another game | DX30: Trade/migrate from another game | DY30: Route 1 , 2 , 4 , 9 , 16 , 17 , 18 , 22 , Pokémon Mansion | DZ30: Route 1 , 2 , 4 , 9 , 16 , 17 , 18 , 22 , Pokémon Mansion | EA30: Route 225 , 226 | EB30: Route 225 , 226 | EC30: Route 225 , 226 | ED30: Route 1 , 3 , 4 , 7 , 9 , 11 , 22 , 29 , 31 , 32 , 33 , 34 , 38 , 39 , 46 , Bell Tower , Burned Tower , Mt. Mortar , Sprout Tower , Tohjo Falls , Union Cave | EE30: Route 1 , 3 , 4 , 7 , 9 , 11 , 22 , 29 , 30 , 31 , 32 , 33 , 34 , 46 , Bell Tower , Burned Tower , Mt. Mortar , Sprout Tower , Tohjo Falls , Union Cave | EF30: Breed Raticate | EG30: Breed Raticate | EH30: Castelia City , Castelia Sewers , Relic Passage | EI30: Castelia City , Castelia Sewers , Relic Passage | EJ30: Trade/migrate from another game | EK30: Trade/migrate from another game | EL30: Route 117 | EM30: Route 117 | EN30: Route 1 , 2 , 3 , 4 , 6 , 8 , Kala'e Bay , Hau'oli City , Verdant Cavern | EO30: Route 1 , 2 , 3 , 4 , 6 , 8 , Kala'e Bay , Hau'oli City , Verdant Cavern | EP30: Route 1 , 2 , 4 , 6 , 8 , Kala'e Bay | EQ30: Route 1 , 2 , 4 , 6 , 8 , Kala'e Bay , Verdant Cavern | ER30: Route 1 , 2 , 3 , 4 , 5 , 6 , 7 , 8 , 9 , 10 , 11 , 16 , 17 , 18 , 21 , 22 , Cerulean City , Pokémon Mansion | ES30: Route 1 , 2 , 3 , 4 , 5 , 6 , 7 , 8 , 9 , 10 , 11 , 16 , 17 , 18 , 21 , 22 , Cerulean City , Pokémon Mansion | ET30: Not available in this game | EU30: Not available in this game | EX30: Route 225 , 226 , Spacious Cave , Grassland Cave , Riverbank Cave , Still-Water Cavern , Sunlit Cavern | EY30: Route 225 , 226 , Spacious Cave , Grassland Cave , Riverbank Cave , Still-Water Cavern , Sunlit Cavern | EZ30: Not available in this game | FA30: Location data not yet available | FB30: Location data not yet available | FE30: Location data not yet available
A31: 0020-00 | B31: 20 | C31: Raticate | D31: =image("https://img.pokemondb.net/sprites/home/normal/"& lower(C31) &".png") | E31: =image("https://img.pokemondb.net/sprites/home/shiny/"& lower(C31) &".png") | F31: =image("https://www.serebii.net/pokedex-bw/type/"&lower(H31)&".gif") | G31: =image("https://www.serebii.net/pokedex-bw/type/"&lower(I31)&".gif") | H31: Normal | J31: Mouse Pokémon | K31: 0.7 m (2′04″) | L31: 18.5 kg (40.8 lbs) | M31: Run Away | N31: Guts | O31: Hustle | P31: 2 Speed | Q31: 127 (16.6% with PokéBall, full HP) | R31: 50 (normal) | S31: 145 | T31: Medium Fast | U31: F | V31: i | W31: 50% male, 50% female | X31: 15 (3,599–3,855 steps) | Y31: 55 | Z31: 81 | AA31: 60 | AB31: 50 | AC31: 70 | AD31: 97 | AE31: =sum(Y31:AD31) -> 413 | AF31: Rattata → Raticate (Level 20) | AG31: 0020 | AH31: 0020 | AI31: 0020 | AJ31: 0018 | AK31: 0018 | AL31: 0018 | AP31: 0020 | AQ31: 0020 | AU31: 0018 | AV31: 0018 | AY31: 0060 | AZ31: 0060 | BE31: 0016 | BF31: 0016 | BG31: 0016 | BH31: 0016 | BI31: 0020 | BJ31: 0020 | BW31: It uses its whiskers to maintain its balance. It apparently slows down if they are cut off. | BX31: It uses its whiskers to maintain its balance. It apparently slows down if they are cut off. | BY31: Its hind feet are webbed. They act as flippers, so it can swim in rivers and hunt for prey. | BZ31: Gnaws on anything with its tough fangs. It can even topple concrete buildings by gnawing on them. | CA31: Its whiskers help it to maintain balance. Its fangs never stop growing, so it gnaws to pare them down. | CB31: The webs on its hind legs enable it to cross rivers. It searches wide areas for food. | CC31: RATICATE’s sturdy fangs grow steadily. To keep them ground down, it gnaws on rocks and logs. It may even chew on the walls of houses. | CD31: RATICATE’s sturdy fangs grow steadily. To keep them ground down, it gnaws on rocks and logs. It may even chew on the walls of houses. | CE31: A RATICATE’s sturdy fangs grow steadily. To keep them ground down, it gnaws on rocks and logs. It may even chew on the walls of houses. | CF31: Its rear feet have three toes each. They are webbed, enabling it to swim across rivers. | CG31: It uses its whiskers to maintain its balance. It apparently slows down if they are cut off. | CH31: It whittles its constantly growing fangs by gnawing on hard things. It can chew apart cinder walls. | CI31: It whittles its constantly growing fangs by gnawing on hard things. It can chew apart cinder walls. | CJ31: It whittles its constantly growing fangs by gnawing on hard things. It can chew apart cinder walls. | CK31: Gnaws on anything with its tough fangs. It can even topple concrete buildings by gnawing on them. | CL31: Its whiskers help it to maintain balance. Its fangs never stop growing, so it gnaws to pare them down. | CM31: It whittles its constantly growing fangs by gnawing on hard things. It can chew apart cinder walls. | CN31: It whittles its constantly growing fangs by gnawing on hard things. It can chew apart cinder walls. | CO31: With its long fangs, this surprisingly violent Pokémon can gnaw away even thick concrete with ease. | CP31: With its long fangs, this surprisingly violent Pokémon can gnaw away even thick concrete with ease. | CQ31: It whittles its constantly growing fangs by gnawing on hard things. It can chew apart cinder walls. | CR31: The webs on its hind legs enable it to cross rivers. It searches wide areas for food. | CS31: Raticate’s sturdy fangs grow steadily. To keep them ground down, it gnaws on rocks and logs. It may even chew on the walls of houses. | CT31: Raticate’s sturdy fangs grow steadily. To keep them ground down, it gnaws on rocks and logs. It may even chew on the walls of houses. | CU31: Its hind feet are webbed, so it’s a strong swimmer. It can cross rivers and sometimes even oceans. | CV31: Its disposition is far more violent than its looks would suggest. Don’t let your hand get too close to its face, as it could bite your hand clean off. | CW31: People say that it fled from its enemies by using its small webbed hind feet to swim from island to island in Alola. | CX31: Its whiskers are essential for maintaining its balance. No matter how friendly you are, it will get angry and bite you if you touch its whiskers. | CY31: Its hind feet are webbed. They act as flippers, so it can swim in rivers and hunt for prey. | CZ31: Its hind feet are webbed. They act as flippers, so it can swim in rivers and hunt for prey. | DE31: It whittles down its constantly growing fangs by gnawing on hard things. It can chew apart cinder block walls. | DF31: It whittles down its constantly growing fangs by gnawing on hard things. It can chew apart cinder block walls. | DP31: Route 16 , 17 , 18 , 21 | DQ31: Route 16 , 17 , 18 , 21 | DR31: Route 9 , 10 , 11 , 16 , 18 , 21 , Pokémon Mansion | DS31: Route 7 , 9 , 10 , 26 , 27 , 38 , 39 , Burned Tower , Mt. Mortar , Tohjo Falls , Union Cave | DT31: Route 7 , 9 , 10 , 26 , 27 , 38 , 39 , Burned Tower , Mt. Mortar , Tohjo Falls , Union Cave | DU31: Route 1 , 3 , 4 , 6 , 7 , 9 , 10 , 11 , 21 , 26 , 27 , 38 , 39 , 42 , 43 , Burned Tower , Mt. Mortar , Tohjo Falls , Union Cave | DV31: Trade/migrate from another game | DW31: Trade/migrate from another game | DX31: Trade/migrate from another game | DY31: Route 16 , 17 , 18 , Pokémon Mansion | DZ31: Route 16 , 17 , 18 , Pokémon Mansion | EA31: Route 225 , 226 | EB31: Route 225 , 226 | EC31: Route 225 , 226 | ED31: Route 7 , 9 , 10 , 26 , 27 , 38 , 39 , 47 , Burned Tower , Mt. Mortar , Tohjo Falls , Union Cave | EE31: Route 7 , 9 , 10 , 26 , 27 , 38 , 39 , 47 , Burned Tower , Mt. Mortar , Tohjo Falls , Union Cave | EF31: Dreamyard | EG31: Dreamyard | EH31: Dreamyard , Relic Passage , Strange House | EI31: Dreamyard , Relic Passage , Strange House | EJ31: Trade/migrate from another game | EK31: Trade/migrate from another game | EL31: Route 118 | EM31: Route 118 | EN31: Route 10 , 11 , 14 , 15 , 16 , 17 , Akala Outskirts , Tapu Village , Malie City , Poni Wilds , Ancient Poni Path , Poni Grove , Poni Plains , Poni Gauntlet | EO31: Route 10 , 11 , 14 , 15 , 16 , 17 , Akala Outskirts , Tapu Village , Malie City , Poni Wilds , Ancient Poni Path , Poni Grove , Poni Plains , Poni Gauntlet | EP31: Route 8 , 10 , 14 , 15 , 16 , 17 , Akala Outskirts , Tapu Village , Mount Lanakila , Poni Plains | EQ31: Route 8 , 10 , 14 , 15 , 16 , 17 , Akala Outskirts , Tapu Village , Mount Lanakila , Poni Plains , Heahea Beach | ER31: Route 7 , 8 , 9 , 10 , 11 , 16 , 17 , 18 , 21 , Pokémon Mansion | ES31: Route 7 , 8 , 9 , 10 , 11 , 16 , 17 , 18 , 21 , Pokémon Mansion | ET31: Not available in this game | EU31: Not available in this game | EX31: Route 225 , 226 , Spacious Cave , Grassland Cave , Riverbank Cave , Still-Water Cavern , Sunlit Cavern | EY31: Route 225 , 226 , Spacious Cave , Grassland Cave , Riverbank Cave , Still-Water Cavern , Sunlit Cavern | EZ31: Not available in this game | FA31: Location data not yet available | FB31: Location data not yet available | FE31: Location data not yet available
A32: 0021-00 | B32: 21 | C32: Spearow | D32: =image("https://img.pokemondb.net/sprites/home/normal/"& lower(C32) &".png") | E32: =image("https://img.pokemondb.net/sprites/home/shiny/"& lower(C32) &".png") | F32: =image("https://www.serebii.net/pokedex-bw/type/"&lower(H32)&".gif") | G32: =image("https://www.serebii.net/pokedex-bw/type/"&lower(I32)&".gif") | H32: Normal | I32: Flying | J32: Tiny Bird Pokémon | K32: 0.3 m (1′00″) | L32: 2.0 kg (4.4 lbs) | M32: Keen Eye | O32: Sniper | P32: 1 Speed | Q32: 255 (33.3% with PokéBall, full HP) | R32: 50 (normal) | S32: 52 | T32: Medium Fast | U32: F | V32: l | W32: 50% male, 50% female | X32: 15 (3,599–3,855 steps) | Y32: 40 | Z32: 60 | AA32: 30 | AB32: 31 | AC32: 31 | AD32: 70 | AE32: =sum(Y32:AD32) -> 262 | AF32: Spearow → Fearow (Level 20) | AG32: 0021 | AH32: 0021 | AI32: 0021 | AJ32: 0013 | AK32: 0013 | AL32: 0013 | AP32: 0021 | AQ32: 0021 | AU32: 0013 | AV32: 0013 | BA32: 0109 | BB32: 0109 | BE32: 0073 | BF32: 0073 | BG32: 0087 | BH32: 0087 | BI32: 0021 | BJ32: 0021 | BW32: Eats bugs in grassy areas. It has to flap its short wings at high speed to stay airborne. | BX32: Eats bugs in grassy areas. It has to flap its short wings at high speed to stay airborne. | BY32: Inept at flying high. However, it can fly around very fast to protect its territory. | BZ32: It flaps its short wings to flush out insects from tall grass. It then plucks them with its stubby beak. | CA32: Very protective of its territory, it flaps its short wings busily to dart around at high speed. | CB32: To protect its territory, it flies around ceaselessly, making high-pitched cries. | CC32: SPEAROW has a very loud cry that can be heard over half a mile away. If its high, keening cry is heard echoing all around, it is a sign that they are warning each other of danger. | CD32: SPEAROW has a very loud cry that can be heard over half a mile away. If its high, keening cry is heard echoing all around, it is a sign that they are warning each other of danger. | CE32: Its loud cry can be heard over half a mile away. If its high, keening cry is heard echoing all around, it is a sign that they are warning each other of danger. | CF32: It busily flits around here and there. Even if it is frail, it can be a tough foe that uses MIRROR MOVE. | CG32: Eats bugs in grassy areas. It has to flap its short wings at high speed to stay airborne. | CH32: It flaps its small wings busily to fly. Using its beak, it searches in grass for prey. | CI32: It flaps its small wings busily to fly. Using its beak, it searches in grass for prey. | CJ32: It flaps its small wings busily to fly. Using its beak, it searches in grass for prey. | CK32: It flaps its short wings to flush out insects from tall grass. It then plucks them with its stubby beak. | CL32: Very protective of its territory, it flaps its short wings busily to dart around at high speed. | CM32: It flaps its small wings busily to fly. Using its beak, it searches in grass for prey. | CN32: It flaps its small wings busily to fly. Using its beak, it searches in grass for prey. | CO32: It flaps its small wings busily to fly. Using its beak, it searches in grass for prey. | CP32: It flaps its small wings busily to fly. Using its beak, it searches in grass for prey. | CQ32: Very protective of its territory, it flaps its short wings busily to dart around at high speed. | CR32: Eats bugs in grassy areas. It has to flap its short wings at high speed to stay airborne. | CS32: Spearow has a very loud cry that can be heard over half a mile away. If its high, keening cry is heard echoing all around, it is a sign that they are warning each other of danger. | CT32: Spearow has a very loud cry that can be heard over half a mile away. If its high, keening cry is heard echoing all around, it is a sign that they are warning each other of danger. | CU32: Its short wings make it inept at flying. It moves about hurriedly and pecks at Bug-type Pokémon in the tall grass. | CV32: Farmers whose fields are troubled by bug Pokémon appreciate Spearow for its vigorous appetite and look after it. | CW32: Its reckless nature leads it to stand up to others—even large Pokémon—if it has to protect its territory. | CX32: Due to its short wings, it can’t fly long distances. It wanders about restlessly and pecks at bug Pokémon. | CY32: Inept at flying high. However, it can fly around very fast to protect its territory. | CZ32: Inept at flying high. However, it can fly around very fast to protect its territory. | DE32: It flaps its small wings busily to fly. Using its beak, it searches in grass for prey. | DF32: It flaps its small wings busily to fly. Using its beak, it searches in grass for prey. | DP32: Route 3 , 4 , 9 , 10 , 11 , 16 , 17 , 18 , 22 , 23 | DQ32: Route 3 , 4 , 9 , 10 , 11 , 16 , 17 , 18 , 22 , 23 | DR32: Route 3 , 4 , 9 , 16 , 18 , 22 | DS32: Route 3 , 4 , 7 , 9 , 10 , 22 , 29 , 30 , 31 , 32 , 33 , 35 , 42 , 43 , 44 , 45 , 46 | DT32: Route 3 , 4 , 7 , 9 , 10 , 22 , 29 , 30 , 31 , 32 , 33 , 35 , 42 , 43 , 44 , 45 , 46 | DU32: Route 3 , 4 , 7 , 9 , 10 , 22 , 33 , 35 , 42 , 44 , 46 , Azalea Town | DV32: Trade/migrate from another game | DW32: Trade/migrate from another game | DX32: Trade/migrate from another game | DY32: Route 3 , 4 , 9 , 10 , 11 , 16 , 17 , 18 , 22 , 23 , Canyon Entrance , Cape Brink , Kindle Road , Mt. Ember , Ruin Valley , Treasure Beach , Water Path | DZ32: Route 3 , 4 , 9 , 10 , 11 , 16 , 17 , 18 , 22 , 23 , Canyon Entrance , Cape Brink , Kindle Road , Mt. Ember , Ruin Valley , Treasure Beach , Water Path | EA32: Route 225 , 226 | EB32: Route 225 , 226 | EC32: Route 225 | ED32: Route 3 , 4 , 7 , 9 , 10 , 11 , 16 , 22 , 33 , 42 , 44 , 45 , 46 , 47 , Azalea Town , Vermilion City | EE32: Route 3 , 4 , 7 , 9 , 10 , 11 , 16 , 22 , 33 , 42 , 44 , 45 , 46 , 47 , Azalea Town , Vermilion City | EF32: Breed Fearow | EG32: Breed Fearow | EH32: Trade/migrate from another game | EI32: Trade/migrate from another game | EJ32: Breed Fearow | EK32: Breed Fearow | EL32: Trade/migrate from another game | EM32: Trade/migrate from another game | EN32: Route 2 , 3 , Poké Pelago | EO32: Route 2 , 3 , Poké Pelago | EP32: Route 2 , 3 | EQ32: Route 2 , 3 | ER32: Route 3 , 4 , 9 , 10 , 22 , 23 | ES32: Route 3 , 4 , 9 , 10 , 22 , 23 | ET32: Not available in this game | EU32: Not available in this game | EX32: Route 225 , 226 | EY32: Route 225 , 226 | EZ32: Not available in this game | FA32: Location data not yet available | FB32: Location data not yet available | FE32: Location data not yet available
A33: 0022-00 | B33: 22 | C33: Fearow | D33: =image("https://img.pokemondb.net/sprites/home/normal/"& lower(C33) &".png") | E33: =image("https://img.pokemondb.net/sprites/home/shiny/"& lower(C33) &".png") | F33: =image("https://www.serebii.net/pokedex-bw/type/"&lower(H33)&".gif") | G33: =image("https://www.serebii.net/pokedex-bw/type/"&lower(I33)&".gif") | H33: Normal | I33: Flying | J33: Beak Pokémon | K33: 1.2 m (3′11″) | L33: 38.0 kg (83.8 lbs) | M33: Keen Eye | O33: Sniper | P33: 2 Speed | Q33: 90 (11.8% with PokéBall, full HP) | R33: 50 (normal) | S33: 155 | T33: Medium Fast | U33: F | V33: l | W33: 50% male, 50% female | X33: 15 (3,599–3,855 steps) | Y33: 65 | Z33: 90 | AA33: 65 | AB33: 61 | AC33: 61 | AD33: 100 | AE33: =sum(Y33:AD33) -> 442 | AF33: Spearow → Fearow (Level 20) | AG33: 0022 | AH33: 0022 | AI33: 0022 | AJ33: 0014 | AK33: 0014 | AL33: 0014 | AP33: 0022 | AQ33: 0022 | AU33: 0014 | AV33: 0014 | BA33: 0110 | BB33: 0110 | BE33: 0074 | BF33: 0074 | BG33: 0088 | BH33: 0088 | BI33: 0022 | BJ33: 0022 | BW33: With its huge and magnificent wings, it can keep aloft without ever having to land for rest. | BX33: With its huge and magnificent wings, it can keep aloft without ever having to land for rest. | BY33: A POKéMON that dates back many years. If it senses danger, it flies high and away, instantly. | BZ33: It shoots itself suddenly high into the sky, then plummets down in one fell swoop to strike its prey. | CA33: It cleverly uses its thin, long beak to pluck and eat small insects that hide under the ground. | CB33: It uses its long beak to attack. It has a surprisingly long reach, so it must be treated with caution. | CC33: FEAROW is recognized by its long neck and elongated beak. They are conveniently shaped for catching prey in soil or water. It deftly moves its long and skinny beak to pluck prey. | CD33: FEAROW is recognized by its long neck and elongated beak. They are conveniently shaped for catching prey in soil or water. It deftly moves its long and skinny beak to pluck prey. | CE33: Its long neck and elongated beak are ideal for catching prey in soil or water. It deftly moves this extended and skinny beak to pluck prey. | CF33: Its huge and magnificent wings can keep it aloft in the sky. It can remain flying a whole day without landing. | CG33: With its huge and magnificent wings, it can keep aloft without ever having to land for rest. | CH33: It has the stamina to fly all day on its broad wings. It fights by using its sharp beak. | CI33: It has the stamina to keep flying all day on its broad wings. It fights by using its sharp beak. | CJ33: It has the stamina to fly all day on its broad wings. It fights by using its sharp beak. | CK33: It shoots itself suddenly high into the sky, then plummets down in one fell swoop to strike its prey. | CL33: It cleverly uses its thin, long beak to pluck and eat small insects that hide under the ground. | CM33: It has the stamina to fly all day on its broad wings. It fights by using its sharp beak. | CN33: It has the stamina to fly all day on its broad wings. It fights by using its sharp beak. | CO33: It has the stamina to fly all day on its broad wings. It fights by using its sharp beak. | CP33: It has the stamina to fly all day on its broad wings. It fights by using its sharp beak. | CQ33: With its huge and magnificent wings, it can keep aloft without ever having to land for rest. | CR33: It has the stamina to fly all day on its broad wings. It fights by using its sharp beak. | CS33: Fearow is recognized by its long neck and elongated beak. They are conveniently shaped for catching prey in soil or water. It deftly moves its long and skinny beak to pluck prey. | CT33: Fearow is recognized by its long neck and elongated beak. They are conveniently shaped for catching prey in soil or water. It deftly moves its long and skinny beak to pluck prey. | CU33: It’s tough and has excellent stamina. It has no problem flying continuously for a whole day carrying a heavy load. | CV33: Drawings of a Pokémon resembling Fearow can be seen in murals from deep in ancient history. | CW33: Carrying food through Fearow’s territory is dangerous. It will snatch the food away from you in a flash! | CX33: In Alola, fish Pokémon are its prey. It can be seen circling above the ocean searching for food. | CY33: A Pokémon that dates back many years. If it senses danger, it flies high and away, instantly. | CZ33: A Pokémon that dates back many years. If it senses danger, it flies high and away, instantly. | DE33: It has the stamina to fly all day on its broad wings. It fights by using its sharp beak. | DF33: It has the stamina to fly all day on its broad wings. It fights by using its sharp beak. | DP33: Route 17 , 18 , 23 | DQ33: Route 17 , 18 , 23 | DR33: Route 9 , 16 , 17 , 18 , 23 | DS33: Route 9 , 10 , 16 , 17 , 18 , 22 | DT33: Route 9 , 10 , 16 , 17 , 18 , 22 | DU33: Route 9 , 10 , 16 , 17 , 18 , 22 , 42 | DV33: Trade/migrate from another game | DW33: Trade/migrate from another game | DX33: Trade/migrate from another game | DY33: Route 17 , 18 , 23 , Canyon Entrance , Cape Brink , Kindle Road , Mt. Ember , Ruin Valley , Sevault Canyon , Treasure Beach , Water Path | DZ33: Route 17 , 18 , 23 , Canyon Entrance , Cape Brink , Kindle Road , Mt. Ember , Ruin Valley , Sevault Canyon , Treasure Beach , Water Path | EA33: Route 225 , 226 , 227 , Stark Mountain | EB33: Route 225 , 226 , 227 , Stark Mountain | EC33: Route 225 , 226 , 227 , Stark Mountain | ED33: Route 9 , 10 , 16 , 17 , 18 , 22 , 47 , 48 | EE33: Route 9 , 10 , 16 , 17 , 18 , 22 , 47 , 48 | EF33: Route 15 | EG33: Route 15 | EH33: Trade/migrate from another game | EI33: Trade/migrate from another game | EJ33: Victory Road | EK33: Victory Road | EL33: Trade/migrate from another game | EM33: Trade/migrate from another game | EN33: Route 10 , 17 , Mount Hokulani , Poni Plains | EO33: Route 10 , 17 , Mount Hokulani , Poni Plains | EP33: Route 10 , 17 , Mount Hokulani , Poni Plains | EQ33: Route 10 , 17 , Mount Hokulani , Poni Plains | ER33: Route 3 , 4 , 9 , 10 , 22 , 23 | ES33: Route 3 , 4 , 9 , 10 , 22 , 23 | ET33: Not available in this game | EU33: Not available in this game | EX33: Route 225 , 226 , 227 , Stark Mountain | EY33: Route 225 , 226 , 227 , Stark Mountain | EZ33: Not available in this game | FA33: Location data not yet available | FB33: Location data not yet available | FE33: Location data not yet available
A34: 0023-00 | B34: 23 | C34: Ekans | D34: =image("https://img.pokemondb.net/sprites/home/normal/"& lower(C34) &".png") | E34: =image("https://img.pokemondb.net/sprites/home/shiny/"& lower(C34) &".png") | F34: =image("https://www.serebii.net/pokedex-bw/type/"&lower(H34)&".gif") | G34: =image("https://www.serebii.net/pokedex-bw/type/"&lower(I34)&".gif") | H34: Poison | J34: Snake Pokémon | K34: 2.0 m (6′07″) | L34: 6.9 kg (15.2 lbs) | M34: Intimidate | N34: Shed Skin | O34: Unnerve | P34: 1 Attack | Q34: 255 (33.3% with PokéBall, full HP) | R34: 50 (normal) | S34: 58 | T34: Medium Fast | U34: Dragon | V34: Field | W34: 50% male, 50% female | X34: 20 (4,884–5,140 steps) | Y34: 35 | Z34: 60 | AA34: 44 | AB34: 40 | AC34: 54 | AD34: 55 | AE34: =sum(Y34:AD34) -> 288 | AF34: Ekans → Arbok (Level 22) | AG34: 0023 | AH34: 0023 | AI34: 0023 | AJ34: 0050 | AK34: 0050 | AL34: 0050 | AP34: 0023 | AQ34: 0023 | AU34: 0050 | AV34: 0050 | BA34: 0037 | BB34: 0037 | BG34: 0061 | BH34: 0061 | BI34: 0023 | BJ34: 0023 | BT34: 0018 | BV34: 0060 | BW34: Moves silently and stealthily. Eats the eggs of birds, such as PIDGEY and SPEAROW, whole. | BX34: Moves silently and stealthily. Eats the eggs of birds, such as PIDGEY and SPEAROW, whole. | BY34: The older it gets, the longer it grows. At night, it wraps its long body around tree branches to rest. | BZ34: It can freely detach its jaw to swallow large prey whole. It can become too heavy to move, however. | CA34: It always hides in grass. When first born, it has no poison, so its bite is painful, but harmless. | CB34: It flutters the tip of its tongue to seek out the scent of prey, then swallows the prey whole. | CC34: EKANS curls itself up in a spiral while it rests. Assuming this position allows it to quickly respond to a threat from any direction with a glare from its upraised head. | CD34: EKANS curls itself up in a spiral while it rests. Assuming this position allows it to quickly respond to a threat from any direction with a glare from its upraised head. | CE34: An EKANS curls itself up in a spiral while it rests. This position allows it to quickly respond to an enemy from any direction with a threat from its upraised head. | CF34: A very common sight in grassland, etc. It flicks its tongue in and out to sense danger in its surroundings. | CG34: Moving silently and stealthily, it eats the eggs of birds, such as PIDGEY and SPEAROW, whole. | CH34: It sneaks through grass without making a sound and strikes unsuspecting prey from behind. | CI34: It sneaks through grass without making a sound and strikes unsuspecting prey from behind. | CJ34: It sneaks through grass without making a sound and strikes unsuspecting prey from behind. | CK34: It can freely detach its jaw to swallow large prey whole. It can become too heavy to move, however. | CL34: It always hides in grass. When first born, it has no poison, so its bite is painful, but harmless. | CM34: It sneaks through grass without making a sound and strikes unsuspecting prey from behind. | CN34: It sneaks through grass without making a sound and strikes unsuspecting prey from behind. | CO34: It sneaks through grass without making a sound and strikes unsuspecting prey from behind. | CP34: It sneaks through grass without making a sound and strikes unsuspecting prey from behind. | CQ34: The older it gets, the longer it grows. At night, it wraps its long body around tree branches to rest. | CR34: Moving silently and stealthily, it eats the eggs of birds, such as Pidgey and Spearow, whole. | CS34: Ekans curls itself up in a spiral while it rests. Assuming this position allows it to quickly respond to a threat from any direction with a glare from its upraised head. | CT34: Ekans curls itself up in a spiral while it rests. Assuming this position allows it to quickly respond to a threat from any direction with a glare from its upraised head. | CW34: By dislocating its jaw, it can swallow prey larger than itself. After a meal, it curls up and rests. | CX34: The eggs of bird Pokémon are its favorite food. It swallows eggs whole, so sometimes an egg gets stuck, and Ekans faints. | CY34: The older it gets, the longer it grows. At night, it wraps its long body around tree branches to rest. | CZ34: The older it gets, the longer it grows. At night, it wraps its long body around tree branches to rest. | DE34: It sneaks through grass without making a sound and strikes unsuspecting prey from behind. | DF34: It sneaks through grass without making a sound and strikes unsuspecting prey from behind. | DP34: Route 4 , 8 , 9 , 10 , 11 , 23 | DQ34: Trade/migrate from another game | DR34: Trade/migrate from another game | DS34: Goldenrod City | DT34: Route 3 , 4 , 32 , 33 | DU34: Route 3 , 4 , 26 , 27 , 32 , 33 , 42 , Azalea Town | DV34: Trade/migrate from another game | DW34: Trade/migrate from another game | DX34: Trade/migrate from another game | DY34: Route 4 , 8 , 9 , 10 , 11 , 23 | DZ34: Trade/migrate from another game | EA34: Route 212 | EB34: Route 212 | EC34: Route 212 | ED34: Goldenrod City | EE34: Route 3 , 4 , 32 , 33 | EF34: Trade/migrate from another game | EG34: Trade/migrate from another game | EH34: Trade/migrate from another game | EI34: Trade/migrate from another game | EJ34: Route 14 | EK34: Route 14 | EL34: Trade/migrate from another game | EM34: Trade/migrate from another game | EN34: Trade/migrate from another game | EO34: Trade/migrate from another game | EP34: Route 2 | EQ34: Route 2 | ER34: Trade/migrate from another game | ES34: Route 3 , 4 | ET34: Not available in this game | EU34: Not available in this game | EX34: Grassland Cave , Swampy Cave , Riverbank Cave , Still-Water Cavern , Sunlit Cavern , Bogsunk Cavern | EY34: Trade/migrate from another game | EZ34: Not available in this game | FA34: Location data not yet available | FB34: Location data not yet available | FE34: Location data not yet available
A35: 0024-00 | B35: 24 | C35: Arbok | D35: =image("https://img.pokemondb.net/sprites/home/normal/"& lower(C35) &".png") | E35: =image("https://img.pokemondb.net/sprites/home/shiny/"& lower(C35) &".png") | F35: =image("https://www.serebii.net/pokedex-bw/type/"&lower(H35)&".gif") | G35: =image("https://www.serebii.net/pokedex-bw/type/"&lower(I35)&".gif") | H35: Poison | J35: Cobra Pokémon | K35: 3.5 m (11′06″) | L35: 65.0 kg (143.3 lbs) | M35: Intimidate | N35: Shed Skin | O35: Unnerve | P35: 2 Attack | Q35: 90 (11.8% with PokéBall, full HP) | R35: 50 (normal) | S35: 157 | T35: Medium Fast | U35: Dragon | V35: Field | W35: 50% male, 50% female | X35: 20 (4,884–5,140 steps) | Y35: 60 | Z35: 95 | AA35: 69 | AB35: 65 | AC35: 79 | AD35: 80 | AE35: =sum(Y35:AD35) -> 448 | AF35: Ekans → Arbok (Level 22) | AG35: 0024 | AH35: 0024 | AI35: 0024 | AJ35: 0051 | AK35: 0051 | AL35: 0051 | AP35: 0024 | AQ35: 0024 | AU35: 0051 | AV35: 0051 | BA35: 0038 | BB35: 0038 | BG35: 0062 | BH35: 0062 | BI35: 0024 | BJ35: 0024 | BT35: 0019 | BV35: 0061 | BW35: It is rumored that the ferocious warning markings on its belly differ from area to area. | BX35: It is rumored that the ferocious warning markings on its belly differ from area to area. | BY35: The frightening patterns on its belly have been studied. Six variations have been confirmed. | BZ35: Transfixing prey with the face-like pattern on its belly, it binds and poisons the frightened victim. | CA35: With a very vengeful nature, it won’t give up the chase, no matter how far, once it targets its prey. | CB35: To intimidate foes, it spreads its chest wide and makes eerie sounds by expelling air from its mouth. | CC35: This POKéMON is terrifically strong in order to constrict things with its body. It can even flatten steel oil drums. Once ARBOK wraps its body around its foe, escaping its crunching embrace is impossible. | CD35: This POKéMON is terrifically strong in order to constrict things with its body. It can even flatten steel oil drums. Once ARBOK wraps its body around its foe, escaping its crunching embrace is impossible. | CE35: This POKéMON has a terrifically strong constricting power. It can even flatten steel oil drums. Once it wraps its body around its foe, escaping is impossible. | CF35: The pattern on its belly appears to be a frightening face. Weak foes will flee just at the sight of the pattern. | CG35: It is rumored that the ferocious warning markings on its belly differ from area to area. | CH35: The pattern on its belly is for intimidation. It constricts foes while they are frozen in fear. | CI35: The pattern on its belly is for intimidation. It constricts foes while they are frozen in fear. | CJ35: The pattern on its belly is for intimidation. It constricts foes while they are frozen in fear. | CK35: Transfixing prey with the face-like pattern on its belly, it binds and poisons the frightened victim. | CL35: With a very vengeful nature, it won’t give up the chase, no matter how far, once it targets its prey. | CM35: The pattern on its belly is for intimidation. It constricts foes while they are frozen in fear. | CN35: The pattern on its belly is for intimidation. It constricts foes while they are frozen in fear. | CO35: The pattern on its belly is for intimidation. It constricts foes while they are frozen in fear. | CP35: The pattern on its belly is for intimidation. It constricts foes while they are frozen in fear. | CQ35: The pattern on its belly appears to be a frightening face. Weak foes will flee just at the sight of the pattern. | CR35: To intimidate foes, it spreads its chest wide and makes eerie sounds by expelling air from its mouth. | CS35: This Pokémon is terrifically strong in order to constrict things with its body. It can even flatten steel oil drums. Once Arbok wraps its body around its foe, escaping its crunching embrace is impossible. | CT35: This Pokémon is terrifically strong in order to constrict things with its body. It can even flatten steel oil drums. Once Arbok wraps its body around its foe, escaping its crunching embrace is impossible. | CW35: The latest research has determined that there are over 20 possible arrangements of the patterns on its stomach. | CX35: After stunning its opponents with the pattern on its stomach, it quickly wraps them up in its body and waits for them to stop moving. | CY35: The frightening patterns on its belly have been studied. Six variations have been confirmed. | CZ35: The frightening patterns on its belly have been studied. Six variations have been confirmed. | DE35: The pattern on its belly is for intimidation. It constricts foes while they are frozen in fear. | DF35: The pattern on its belly is for intimidation. It constricts foes while they are frozen in fear. | DP35: Route 23 , Cerulean Cave | DQ35: Trade/migrate from another game | DR35: Trade/migrate from another game | DS35: Evolve Ekans | DT35: Route 3 , 4 , 26 , 27 | DU35: Route 3 , 4 , 26 , 27 , 28 , 42 , Mt. Silver | DV35: Trade/migrate from another game | DW35: Trade/migrate from another game | DX35: Trade/migrate from another game | DY35: Route 23 , Victory Road | DZ35: Trade/migrate from another game | EA35: Great Marsh | EB35: Great Marsh | EC35: Great Marsh | ED35: Evolve Ekans | EE35: Route 3 , 4 , 26 , 27 | EF35: Trade/migrate from another game | EG35: Trade/migrate from another game | EH35: Trade/migrate from another game | EI35: Trade/migrate from another game | EJ35: Route 19 | EK35: Route 19 | EL35: Trade/migrate from another game | EM35: Trade/migrate from another game | EN35: Trade/migrate from another game | EO35: Trade/migrate from another game | EP35: Route 8 | EQ35: Route 8 | ER35: Trade/migrate from another game | ES35: Evolve Ekans | ET35: Not available in this game | EU35: Not available in this game | EX35: Evolve Ekans | EY35: Trade/migrate from another game | EZ35: Not available in this game | FA35: Location data not yet available | FB35: Location data not yet available | FE35: Location data not yet available
A36: 0025-00 | B36: 25 | C36: Pikachu | D36: =image("https://img.pokemondb.net/sprites/home/normal/"& lower(C36) &".png") | E36: =image("https://img.pokemondb.net/sprites/home/shiny/"& lower(C36) &".png") | F36: =image("https://www.serebii.net/pokedex-bw/type/"&lower(H36)&".gif") | G36: =image("https://www.serebii.net/pokedex-bw/type/"&lower(I36)&".gif") | H36: Electric | J36: Mouse Pokémon | K36: 0.4 m (1′04″) | L36: 6.0 kg (13.2 lbs) | M36: Static | O36: Lightning Rod | P36: 2 Speed | Q36: 190 (24.8% with PokéBall, full HP) | R36: 50 (normal) | S36: 112 | T36: Medium Fast | U36: Fairy | V36: Field | W36: 50% male, 50% female | X36: 10 (2,314–2,570 steps) | Y36: 35 | Z36: 55 | AA36: 40 | AB36: 50 | AC36: 50 | AD36: 90 | AE36: =sum(Y36:AD36) -> 320 | AF36: Pichu → Pikachu (high Friendship ) → Raichu (use Thunder Stone , outside Alola) | AG36: 0025 | AH36: 0025 | AI36: 0025 | AJ36: 0022 | AK36: 0022 | AL36: 0022 | AM36: 0156 | AN36: 0156 | AO36: 0156 | AP36: 0025 | AQ36: 0025 | AR36: 0104 | AS36: 0104 | AT36: 0104 | AU36: 0022 | AV36: 0022 | BA36: 0036 | BB36: 0036 | BC36: 0163 | BD36: 0163 | BE36: 0025 | BF36: 0025 | BG36: 0032 | BH36: 0032 | BI36: 0025 | BJ36: 0025 | BK36: 0194 | BL36: 0194 | BM36: 0085 | BO36: 0104 | BP36: 0104 | BQ36: 0056 | BR36: 0074 | BS36: 0074 | BT36: 0021 | BV36: 0053 | BW36: When several of these POKéMON gather, their electricity could build and cause lightning storms. | BX36: When several of these POKéMON gather, their electricity could build and cause lightning storms. | BY36: It keeps its tail raised to monitor its surroundings. If you yank its tail, it will try to bite you. | BZ36: This intelligent POKéMON roasts hard BERRIES with electricity to make them tender enough to eat. | CA36: It raises its tail to check its surroundings. The tail is sometimes struck by lightning in this pose. | CB36: When it is angered, it immediately discharges the energy stored in the pouches in its cheeks. | CC36: Whenever PIKACHU comes across something new, it blasts it with a jolt of electricity. If you come across a blackened berry, it’s evidence that this POKéMON mistook the intensity of its charge. | CD36: This POKéMON has electricity-storing pouches on its cheeks. These appear to become electrically charged during the night while PIKACHU sleeps. It occasionally discharges electricity when it is dozy after waking up. | CE36: It stores electricity in the electric sacs on its cheeks. When it releases pent-up energy in a burst, the electric power is equal to a lightning bolt. | CF36: It has small electric sacs on both its cheeks. If threatened, it looses electric charges from the sacs. | CG36: When several of these POKéMON gather, their electricity can build and cause lightning storms. | CH36: It lives in forests with others. It stores electricity in the pouches on its cheeks. | CI36: If it looses crackling power from the electric pouches on its cheeks, it is being wary. | CJ36: It occasionally uses an electric shock to recharge a fellow PIKACHU that is in a weakened state. | CK36: This intelligent Pokémon roasts hard berries with electricity to make them tender enough to eat. | CL36: It raises its tail to check its surroundings. The tail is sometimes struck by lightning in this pose. | CM36: It occasionally uses an electric shock to recharge a fellow Pikachu that is in a weakened state. | CN36: It occasionally uses an electric shock to recharge a fellow Pikachu that is in a weakened state. | CO36: It occasionally uses an electric shock to recharge a fellow Pikachu that is in a weakened state. | CP36: It occasionally uses an electric shock to recharge a fellow Pikachu that is in a weakened state. | CQ36: It raises its tail to check its surroundings. The tail is sometimes struck by lightning in this pose. | CR36: It has small electric sacs on both its cheeks. If threatened, it looses electric charges from the sacs. | CS36: Whenever Pikachu comes across something new, it blasts it with a jolt of electricity. If you come across a blackened berry, it’s evidence that this Pokémon mistook the intensity of its charge. | CT36: This Pokémon has electricity-storing pouches on its cheeks. These appear to become electrically charged during the night while Pikachu sleeps. It occasionally discharges electricity when it is dozy after waking up. | CU36: A plan was recently announced to gather many Pikachu and make an electric power plant. | CV36: It’s in its nature to store electricity. It feels stressed now and then if it’s unable to fully discharge the electricity. | CW36: Its nature is to store up electricity. Forests where nests of Pikachu live are dangerous, since the trees are so often struck by lightning. | CX36: While sleeping, it generates electricity in the sacs in its cheeks. If it’s not getting enough sleep, it will be able to use only weak electricity. | CY36: This forest-dwelling Pokémon stores electricity in its cheeks, so you’ll feel a tingly shock if you touch it. | CZ36: This forest-dwelling Pokémon stores electricity in its cheeks, so you’ll feel a tingly shock if you touch it. | DA36: Pikachu that can generate powerful electricity have cheek sacs that are extra soft and super stretchy. | DB36: When Pikachu meet, they’ll touch their tails together and exchange electricity through them as a form of greeting. | DE36: It lives in forests with others. It stores electricity in the electric sacs on its cheeks. | DF36: If it looses crackling power from the electric sacs on its cheeks, it is being wary. | DG36: Possesses cheek sacs in which it stores electricity. This clever forest-dweller roasts tough berries with an electric shock before consuming them. | DH36: When it is angered, it immediately discharges the energy stored in the pouches in its cheeks. | DI36: When several of these Pokémon gather, their electricity can build and cause lightning storms. | DP36: Power Plant , Viridian Forest | DQ36: Power Plant , Viridian Forest | DR36: Pallet Town | DS36: Route 2 | DT36: Route 2 | DU36: Route 2 , Celadon City | DV36: Safari Zone | DW36: Safari Zone | DX36: Safari Zone | DY36: Power Plant , Viridian Forest | DZ36: Power Plant , Viridian Forest | EA36: Trophy Garden | EB36: Trophy Garden | EC36: Trophy Garden | ED36: Saffron City , Viridian Forest | EE36: Saffron City , Viridian Forest | EF36: Trade/migrate from another game | EG36: Trade/migrate from another game | EH36: Trade/migrate from another game | EI36: Trade/migrate from another game | EJ36: Route 3 , Santalune Forest | EK36: Route 3 , Santalune Forest | EL36: Safari Zone | EM36: Safari Zone | EN36: Route 1 , Hau'oli City | EO36: Route 1 , Hau'oli City | EP36: Route 1 , Heahea City | EQ36: Route 1 , Heahea City | ER36: Pallet Town , Viridian Forest | ES36: Viridian Forest | ET36: Route 4 , Stony Wilderness , Forest of Focus | EU36: Route 4 , Stony Wilderness , Forest of Focus | EX36: Trophy Garden | EY36: Trophy Garden | EZ36: Nature’s Pantry , Golden Lowlands | FA36: East Province (Area One) , South Province (Area Two) , South Province (Area Four) , West Province (Area Three) | FB36: East Province (Area One) , South Province (Area Two) , South Province (Area Four) , West Province (Area Three) | FE36: Location data not yet available
A37: 0026-00 | B37: 26 | C37: Raichu | D37: =image("https://img.pokemondb.net/sprites/home/normal/"& lower(C37) &".png") | E37: =image("https://img.pokemondb.net/sprites/home/shiny/"& lower(C37) &".png") | F37: =image("https://www.serebii.net/pokedex-bw/type/"&lower(H37)&".gif") | G37: =image("https://www.serebii.net/pokedex-bw/type/"&lower(I37)&".gif") | H37: Electric | J37: Mouse Pokémon | K37: 0.8 m (2′07″) | L37: 30.0 kg (66.1 lbs) | M37: Static | O37: Lightning Rod | P37: 3 Speed | Q37: 75 (9.8% with PokéBall, full HP) | R37: 50 (normal) | S37: 243 | T37: Medium Fast | U37: Fairy | V37: Field | W37: 50% male, 50% female | X37: 10 (2,314–2,570 steps) | Y37: 60 | Z37: 90 | AA37: 55 | AB37: 90 | AC37: 80 | AD37: 110 | AE37: =sum(Y37:AD37) -> 485 | AF37: Pichu → Pikachu (high Friendship ) → Raichu (use Thunder Stone , outside Alola) | AG37: 0026 | AH37: 0026 | AI37: 0026 | AJ37: 0023 | AK37: 0023 | AL37: 0023 | AM37: 0157 | AN37: 0157 | AO37: 0157 | AP37: 0026 | AQ37: 0026 | AR37: 0105 | AS37: 0105 | AT37: 0105 | AU37: 0023 | AV37: 0023 | BA37: 0037 | BB37: 0037 | BC37: 0164 | BD37: 0164 | BE37: 0026 | BF37: 0026 | BG37: 0033 | BH37: 0033 | BI37: 0026 | BJ37: 0026 | BK37: 0195 | BL37: 0195 | BM37: 0086 | BO37: 0105 | BP37: 0105 | BQ37: 0057 | BR37: 0075 | BS37: 0075 | BT37: 0022 | BV37: 0054 | BW37: Its long tail serves as a ground to protect itself from its own high voltage power. | BX37: Its long tail serves as a ground to protect itself from its own high voltage power. | BY37: When electricity builds up inside its body, it becomes feisty. It also glows in the dark. | BZ37: When its electricity builds, its muscles are stimulated, and it becomes more aggressive than usual. | CA37: If the electric pouches in its cheeks become fully charged, both ears will stand straight up. | CB37: If its electric pouches run empty, it raises its tail to gather electricity from the atmosphere. | CC37: If the electrical sacks become excessively charged, RAICHU plants its tail in the ground and discharges. Scorched patches of ground will be found near this POKéMON’s nest. | CD37: This POKéMON exudes a weak electrical charge from all over its body that makes it take on a slight glow in darkness. RAICHU searches for electricity by planting its tail in the ground. | CE37: If it stores too much electricity, its behavior turns aggressive. To avoid this, it occasionally discharges excess energy and calms itself down. | CF37: Its electric charges can reach even 100,000 volts. Careless contact can cause even an Indian elephant to faint. | CG37: Its long tail serves as a ground to protect itself from its own high-voltage power. | CH37: It turns aggressive if it has too much electricity in its body. It discharges power through its tail. | CI37: It can loose 100,000-volt bursts of electricity, instantly downing foes several times its size. | CJ37: Its tail discharges electricity into the ground, protecting it from getting shocked. | CK37: When its electricity builds, its muscles are stimulated, and it becomes more aggressive than usual. | CL37: If the electric pouches in its cheeks become fully charged, both ears will stand straight up. | CM37: Its tail discharges electricity into the ground, protecting it from getting shocked. | CN37: Its tail discharges electricity into the ground, protecting it from getting shocked. | CO37: Its tail discharges electricity into the ground, protecting it from getting shocked. | CP37: Its tail discharges electricity into the ground, protecting it from getting shocked. | CQ37: When its electricity builds, its muscles are stimulated, and it becomes more aggressive than usual. | CR37: It can loose 100,000-volt bursts of electricity, instantly downing foes several times its size. | CS37: If the electrical sacs become excessively charged, Raichu plants its tail in the ground and discharges. Scorched patches of ground will be found near this Pokémon’s nest. | CT37: This Pokémon exudes a weak electrical charge from all over its body that makes it take on a slight glow in darkness. Raichu plants its tail in the ground to discharge electricity. | CU37: It unleashes electric shocks that can reach 100,000 volts. When agitated, it can knock out even an Indian elephant. | CV37: It becomes aggressive when it has electricity stored up. At such times, even its Trainer has to take care to avoid being attacked. | CW37: As electricity builds up inside its body, it becomes more aggressive. One theory is that the electricity buildup is actually causing stress. | CX37: Because so many Trainers like the way Pikachu looks, you don’t see this Pokémon very often. | CY37: When electricity builds up inside its body, it becomes feisty. It also glows in the dark. | CZ37: When electricity builds up inside its body, it becomes feisty. It also glows in the dark. | DA37: Its long tail serves as a ground to protect itself from its own high-voltage power. | DB37: If its electric pouches run empty, it raises its tail to gather electricity from the atmosphere. | DE37: It turns aggressive if it has too much electricity in its body. It discharges power through its tail. | DF37: It can loose 100,000-volt bursts of electricity, instantly downing foes several times its size. | DG37: It can discharge bursts of electricity exceeding 100,000 volts— a single strike with that amount of power would incapacitate one of the Copperajah of my homeland. | DH37: Its tail discharges electricity into the ground, protecting it from getting shocked. | DI37: If the electric pouches in its cheeks become fully charged, both ears will stand straight up. | DP37: Cerulean Cave | DQ37: Cerulean Cave , Power Plant | DR37: Evolve Pikachu | DS37: Evolve Pikachu / Pichu | DT37: Evolve Pikachu / Pichu | DU37: Evolve Pikachu / Pichu | DV37: Evolve Pikachu / Pichu | DW37: Evolve Pikachu / Pichu | DX37: Evolve Pikachu / Pichu | DY37: Evolve Pikachu / Pichu | DZ37: Evolve Pikachu / Pichu | EA37: Evolve Pikachu / Pichu | EB37: Evolve Pikachu / Pichu | EC37: Evolve Pikachu / Pichu | ED37: Evolve Pikachu / Pichu | EE37: Evolve Pikachu / Pichu | EF37: Trade/migrate from another game | EG37: Trade/migrate from another game | EH37: Trade/migrate from another game | EI37: Trade/migrate from another game | EJ37: Evolve Pikachu / Pichu | EK37: Evolve Pikachu / Pichu | EL37: Evolve Pikachu / Pichu | EM37: Evolve Pikachu / Pichu | EN37: Evolve Pikachu / Pikachu (Partner Pikachu) / Pichu | EO37: Evolve Pikachu / Pikachu (Partner Pikachu) / Pichu | EP37: Evolve Pikachu / Pikachu (Partner Pikachu) / Pichu | EQ37: Evolve Pikachu / Pikachu (Partner Pikachu) / Pichu | ER37: Saffron City | ES37: Saffron City | ET37: Evolve Pikachu / Pikachu (Partner Pikachu) / Pichu | EU37: Evolve Pikachu / Pikachu (Partner Pikachu) / Pichu | EX37: Evolve Pikachu / Pikachu (Partner Pikachu) / Pichu | EY37: Evolve Pikachu / Pikachu (Partner Pikachu) / Pichu | EZ37: Golden Lowlands | FA37: Tagtree Thicket , Casseroya Lake , North Province (Area One) , North Province (Area Two) , East Province (Area One) , East Province (Area Two) , South Province (Area One) , South Province (Area Two) , South Province (Area Four) , West Province (Area Three) , The Great Crater of Paldea | FB37: Tagtree Thicket , Casseroya Lake , North Province (Area One) , North Province (Area Two) , East Province (Area One) , East Province (Area Two) , South Province (Area One) , South Province (Area Two) , South Province (Area Four) , West Province (Area Three) , The Great Crater of Paldea | FE37: Location data not yet available
A38: 0027-00 | B38: 27 | C38: Sandshrew | D38: =image("https://img.pokemondb.net/sprites/home/normal/"& lower(C38) &".png") | E38: =image("https://img.pokemondb.net/sprites/home/shiny/"& lower(C38) &".png") | F38: =image("https://www.serebii.net/pokedex-bw/type/"&lower(H38)&".gif") | G38: =image("https://www.serebii.net/pokedex-bw/type/"&lower(I38)&".gif") | H38: Ground | J38: Mouse Pokémon | K38: 0.6 m (2′00″) | L38: 12.0 kg (26.5 lbs) | M38: Sand Veil | O38: Sand Rush | P38: 1 Defense | Q38: 255 (33.3% with PokéBall, full HP) | R38: 50 (normal) | S38: 60 | T38: Medium Fast | U38: F | V38: i | W38: 50% male, 50% female | X38: 20 (4,884–5,140 steps) | Y38: 50 | Z38: 75 | AA38: 85 | AB38: 20 | AC38: 30 | AD38: 40 | AE38: =sum(Y38:AD38) -> 300 | AF38: Sandshrew → Sandslash (Level 22) | AG38: 0027 | AH38: 0027 | AI38: 0027 | AJ38: 0048 | AK38: 0048 | AL38: 0048 | AM38: 0112 | AN38: 0112 | AO38: 0112 | AP38: 0027 | AQ38: 0027 | AU38: 0048 | AV38: 0048 | AY38: 0113 | AZ38: 0113 | BA38: 0097 | BB38: 0097 | BC38: 0117 | BD38: 0117 | BE38: 0251 | BF38: 0251 | BG38: 0328 | BH38: 0328 | BI38: 0027 | BJ38: 0027 | BM38: 0168 | BT38: 0116 | BU38: 0155 | BW38: Burrows deep underground in arid locations far from water. It only emerges to hunt for food. | BX38: Burrows deep underground in arid locations far from water. It only emerges to hunt for food. | BY38: Its body is dry. When it gets cold at night, its hide is said to become coated with a fine dew. | BZ38: If it fell from a great height, this POKéMON could save itself by rolling into a ball and bouncing. | CA38: Disliking water, it lives in deep burrows in arid areas. It can roll itself instantly into a ball. | CB38: It prefers dry, sandy places because it uses the sand to protect itself when threatened. | CC38: SANDSHREW’s body is configured to absorb water without waste, enabling it to survive in an arid desert. This POKéMON curls up to protect itself from its enemies. | CD38: SANDSHREW has a very dry hide that is extremely tough. The POKéMON can roll into a ball that repels any attack. At night, it burrows into the desert sand to sleep. | CE38: When it curls up in a ball, it can make any attack bounce off harmlessly. Its hide has turned tough and solid as a result of living in the desert. | CF38: It burrows and lives underground. If threatened, it curls itself up into a ball for protection. | CG38: Burrows deep underground in arid locations far from water. It only emerges to hunt for prey. | CH38: To protect itself from attackers, it curls up into a ball. It lives in arid regions with minimal rainfall. | CI38: To protect itself from attackers, it curls up into a ball. It lives in arid regions with minimal rainfall. | CJ38: To protect itself from attackers, it curls up into a ball. It lives in arid regions with minimal rainfall. | CK38: If it fell from a great height, this Pokémon could save itself by rolling into a ball and bouncing. | CL38: Disliking water, it lives in deep burrows in arid areas. It can roll itself instantly into a ball. | CM38: To protect itself from attackers, it curls up into a ball. It lives in arid regions with minimal rainfall. | CN38: To protect itself from attackers, it curls up into a ball. It lives in arid regions with minimal rainfall. | CO38: It digs deep burrows to live in. When in danger, it rolls up its body to withstand attacks. | CP38: It digs deep burrows to live in. When in danger, it rolls up its body to withstand attacks. | CQ38: It burrows and lives underground. If threatened, it curls itself up into a ball for protection. | CR38: Disliking water, it lives in deep burrows in arid areas. It can roll itself instantly into a ball. | CS38: Sandshrew’s body is configured to absorb water without waste, enabling it to survive in an arid desert. This Pokémon curls up to protect itself from its enemies. | CT38: Sandshrew has a very dry hide that is extremely tough. The Pokémon can roll into a ball that repels any attack. At night, it burrows into the desert sand to sleep. | CU38: It can roll its body into a ball. It moves through the desert by rolling at high speeds. | CV38: It usually makes its home in deserts and arid zones, where rain does not fall. It digs holes to catch Bug-type Pokémon. | CW38: It lives in areas of limited rainfall. When danger approaches, it curls up into a ball to protect its soft stomach. | CX38: When its skin gets wrinkled from moisture, it heads for a volcano. It lies flat on a spot with a lot of geothermal heat and dries itself out. | CY38: Its body is dry. When it gets cold at night, its hide is said to become coated with a fine dew. | CZ38: Its body is dry. When it gets cold at night, its hide is said to become coated with a fine dew. | DA38: It loves to bathe in the grit of dry, sandy areas. By sand bathing, the Pokémon rids itself of dirt and moisture clinging to its body. | DB38: It burrows into the ground to create its nest. If hard stones impede its tunneling, it uses its sharp claws to shatter them and then carries on digging. | DE38: To protect itself from attackers, it curls up into a ball. It lives in arid regions with minimal rainfall. | DF38: To protect itself from attackers, it curls up into a ball. It lives in arid regions with minimal rainfall. | DP38: Trade/migrate from another game | DQ38: Route 4 , 8 , 9 , 10 , 11 , 23 | DR38: Route 3 , 4 , Mt. Moon | DS38: Mt. Moon , Union Cave | DT38: Goldenrod City , Union Cave | DU38: Route 3 , 4 , Mt. Moon , Union Cave | DV38: Route 111 , 113 | DW38: Route 111 , 113 | DX38: Route 111 , Mirage Tower | DY38: Trade/migrate from another game | DZ38: Route 4 , 8 , 9 , 10 , 11 , 23 | EA38: Wayward Cave | EB38: Wayward Cave | EC38: Wayward Cave | ED38: Mt. Moon , Union Cave | EE38: Goldenrod City | EF38: Breed Sandslash | EG38: Breed Sandslash | EH38: Relic Castle , Desert Resort | EI38: Relic Castle , Desert Resort | EJ38: Breed Sandslash | EK38: Breed Sandslash | EL38: Route 111 , 113 | EM38: Route 111 , 113 | EN38: Trade/migrate from another game | EO38: Route 14 , Tapu Village , Mount Lanakila | EP38: Trade/migrate from another game | EQ38: Route 14 , Tapu Village , Mount Lanakila | ER38: Route 3 , 4 , Celadon City | ES38: Trade/migrate from another game | ET38: Warm-Up Tunnel | EU38: Warm-Up Tunnel | EX38: Trade/migrate from another game | EY38: Spacious Cave , Rocky Cave , Sandsear Cave , Big Bluff Cavern | EZ38: Not available in this game | FA38: Location data not yet available | FB38: Location data not yet available | FE38: Location data not yet available
A39: 0028-00 | B39: 28 | C39: Sandslash | D39: =image("https://img.pokemondb.net/sprites/home/normal/"& lower(C39) &".png") | E39: =image("https://img.pokemondb.net/sprites/home/shiny/"& lower(C39) &".png") | F39: =image("https://www.serebii.net/pokedex-bw/type/"&lower(H39)&".gif") | G39: =image("https://www.serebii.net/pokedex-bw/type/"&lower(I39)&".gif") | H39: Ground | J39: Mouse Pokémon | K39: 1.0 m (3′03″) | L39: 29.5 kg (65.0 lbs) | M39: Sand Veil | O39: Sand Rush | P39: 2 Defense | Q39: 90 (11.8% with PokéBall, full HP) | R39: 50 (normal) | S39: 158 | T39: Medium Fast | U39: F | V39: i | W39: 50% male, 50% female | X39: 20 (4,884–5,140 steps) | Y39: 75 | Z39: 100 | AA39: 110 | AB39: 45 | AC39: 55 | AD39: 65 | AE39: =sum(Y39:AD39) -> 450 | AF39: Sandshrew → Sandslash (Level 22) | AG39: 0028 | AH39: 0028 | AI39: 0028 | AJ39: 0049 | AK39: 0049 | AL39: 0049 | AM39: 0113 | AN39: 0113 | AO39: 0113 | AP39: 0028 | AQ39: 0028 | AU39: 0049 | AV39: 0049 | AY39: 0114 | AZ39: 0114 | BA39: 0098 | BB39: 0098 | BC39: 0118 | BD39: 0118 | BE39: 0252 | BF39: 0252 | BG39: 0329 | BH39: 0329 | BI39: 0028 | BJ39: 0028 | BM39: 0169 | BT39: 0117 | BU39: 0156 | BW39: Curls up into a spiny ball when threatened. It can roll while curled up to attack or escape. | BX39: Curls up into a spiny ball when threatened. It can roll while curled up to attack or escape. | BY39: It is skilled at slashing enemies with its claws. If broken, they start to grow back in a day. | BZ39: In an attempt to hide itself, it will run around at top speed to kick up a blinding dust storm. | CA39: If it digs at an incredible pace, it may snap off its spikes and claws. They grow back in a day. | CB39: Adept at climbing trees, it rolls into a spiny ball, then attacks its enemies from above. | CC39: SANDSLASH’s body is covered by tough spikes, which are hardened sections of its hide. Once a year, the old spikes fall out, to be replaced with new spikes that grow out from beneath the old ones. | CD39: SANDSLASH can roll up its body as if it were a ball covered with large spikes. In battle, this POKéMON will try to make the foe flinch by jabbing it with its spines. It then leaps at the stunned foe to tear wildly with its sharp claws. | CE39: It curls up in a ball to protect itself from enemy attacks. It also curls up to prevent heatstroke during the daytime when temperatures rise sharply. | CF39: It is adept at attacking with the spines on its back and its sharp claws while quickly scurrying about. | CG39: Curls up into a spiny ball when threatened. It can roll while curled up to attack or escape. | CH39: It curls up, then rolls into foes with its back. Its sharp spines inflict severe damage. | CI39: It curls up, then rolls into foes with its back. Its sharp spines inflict severe damage. | CJ39: It curls up, then rolls into foes with its back. Its sharp spines inflict severe damage. | CK39: In an attempt to hide itself, it will run around at top speed to kick up a blinding dust storm. | CL39: If it digs at an incredible pace, it may snap off its spikes and claws. They grow back in a day. | CM39: It curls up, then rolls into foes with its back. Its sharp spines inflict severe damage. | CN39: It curls up, then rolls into foes with its back. Its sharp spines inflict severe damage. | CO39: The spikes on its body are made up of its hardened hide. It rolls up and attacks foes with its spikes. | CP39: The spikes on its body are made up of its hardened hide. It rolls up and attacks foes with its spikes. | CQ39: If it digs at an incredible pace, it may snap off its spikes and claws. They grow back in a day. | CR39: Curls up into a spiny ball when threatened. It can roll while curled up to attack or escape. | CS39: Sandslash’s body is covered by tough spikes, which are hardened sections of its hide. Once a year, the old spikes fall out, to be replaced with new spikes that grow out from beneath the old ones. | CT39: Sandslash can roll up its body as if it were a ball covered with large spikes. In battle, this Pokémon will try to make the foe flinch by jabbing it with its spines. It then leaps at the stunned foe to tear wildly with its sharp claws. | CU39: Although they are sharp, its claws and spikes often break off. They grow back the next day, so it is not bothered by the temporary loss. | CV39: It uses its claws to climb trees and then curls its body into a spiny ball, ready to drop onto any prey that appears. | CW39: Its claws and horns often break off. The broken claws and horns can be used to carve plows for tilling farm fields. | CX39: Thanks to its thick claws, it’s good at climbing trees. There are plenty of Sandslash that park themselves in trees and go right to sleep. | CY39: It is skilled at slashing enemies with its claws. If broken, they start to grow back in a day. | CZ39: It is skilled at slashing enemies with its claws. If broken, they start to grow back in a day. | DA39: The drier the area Sandslash lives in, the harder and smoother the Pokémon’s spikes will feel when touched. | DB39: It climbs trees by hooking on with its sharp claws. Sandslash shares the berries it gathers, dropping them down to Sandshrew waiting below the tree. | DE39: It curls up, then rolls into foes with its back. Its sharp spines inflict severe damage. | DF39: It curls up, then rolls into foes with its back. Its sharp spines inflict severe damage. | DP39: Trade/migrate from another game | DQ39: Route 23 , Cerulean Cave | DR39: Cerulean Cave | DS39: Route 26 , 27 , Mt. Moon | DT39: Evolve Sandshrew | DU39: Route 26 , Victory Road | DV39: Evolve Sandshrew | DW39: Evolve Sandshrew | DX39: Evolve Sandshrew | DY39: Trade/migrate from another game | DZ39: Route 23 , Victory Road | EA39: Route 228 | EB39: Route 228 | EC39: Route 228 | ED39: Route 26 , 27 , Mt. Moon | EE39: Evolve Sandshrew | EF39: Relic Castle | EG39: Relic Castle | EH39: Route 15 , Relic Castle | EI39: Route 15 , Relic Castle | EJ39: Route 18 , Terminus Cave | EK39: Route 18 , Terminus Cave | EL39: Evolve Sandshrew | EM39: Evolve Sandshrew | EN39: Trade/migrate from another game | EO39: Evolve Sandshrew / Alolan Sandshrew | EP39: Trade/migrate from another game | EQ39: Evolve Sandshrew / Alolan Sandshrew | ER39: Evolve Sandshrew / Alolan Sandshrew | ES39: Trade/migrate from another game | ET39: Evolve Sandshrew / Alolan Sandshrew | EU39: Evolve Sandshrew / Alolan Sandshrew | EX39: Trade/migrate from another game | EY39: Spacious Cave , Rocky Cave , Sandsear Cave , Big Bluff Cavern | EZ39: Not available in this game | FA39: Location data not yet available | FB39: Location data not yet available | FE39: Location data not yet available
A40: 0029-00 | B40: 29 | C40: Nidoran♀ (female) | D40: =image("https://img.pokemondb.net/sprites/home/normal/"& lower(C40) &".png") | E40: =image("https://img.pokemondb.net/sprites/home/shiny/"& lower(C40) &".png") | F40: =image("https://www.serebii.net/pokedex-bw/type/"&lower(H40)&".gif") | G40: =image("https://www.serebii.net/pokedex-bw/type/"&lower(I40)&".gif") | H40: Poison | J40: Poison Pin Pokémon | K40: 0.4 m (1′04″) | L40: 7.0 kg (15.4 lbs) | M40: Poison Point | N40: Rivalry | O40: Hustle | P40: 1 HP | Q40: 235 (30.7% with PokéBall, full HP) | R40: 50 (normal) | S40: 55 | T40: Medium Slow | U40: Field | V40: Monster | W40: 0% male, 100% female | X40: 20 (4,884–5,140 steps) | Y40: 55 | Z40: 47 | AA40: 52 | AB40: 40 | AC40: 40 | AD40: 41 | AE40: =sum(Y40:AD40) -> 275 | AF40: Nidoran♀ → Nidorina (Level 16) → Nidoqueen (use Moon Stone ) | AG40: 0029 | AH40: 0029 | AI40: 0029 | AJ40: 0095 | AK40: 0095 | AL40: 0095 | AP40: 0029 | AQ40: 0029 | AU40: 0095 | AV40: 0095 | BA40: 0104 | BB40: 0104 | BI40: 0029 | BJ40: 0029 | BN40: 0065 | BW40: Although small, its venomous barbs render this POKéMON dangerous. The female has smaller horns. | BX40: Although small, its venomous barbs render this POKéMON dangerous. The female has smaller horns. | BY40: A mild-mannered POKéMON that does not like to fight. Beware, its small horns secrete venom. | BZ40: The poison hidden in its small horn is extremely potent. Even a tiny scratch can have fatal results. | CA40: Although not very combative, it will torment its foes with poison spikes if it is threatened in any way. | CB40: Small and very docile, it protects itself with its small, poisonous horn when attacked. | CC40: NIDORAN has barbs that secrete a powerful poison. They are thought to have developed as protection for this small-bodied POKéMON. When enraged, it releases a horrible toxin from its horn. | CD40: NIDORAN has barbs that secrete a powerful poison. They are thought to have developed as protection for this small-bodied POKéMON. When enraged, it releases a horrible toxin from its horn. | CE40: Its highly toxic barbs are thought to have developed as protection for this small-bodied POKéMON. When enraged, it releases a horrible toxin from its horn. | CF40: Though small, it must be treated with caution because of its powerfully toxic barbs. The female has smaller horns. | CG40: Although small, its venomous barbs render this POKéMON dangerous. The female has smaller horns. | CH40: While it does not prefer to fight, even one drop of the poison it secretes from barbs can be fatal. | CI40: While it does not prefer to fight, even one drop of the poison it secretes from barbs can be fatal. | CJ40: While it does not prefer to fight, even one drop of the poison it secretes from barbs can be fatal. | CK40: The poison hidden in its small horn is extremely potent. Even a tiny scratch can have fatal results. | CL40: Although not very combative, it will torment its foes with poison spikes if it is threatened in any way. | CM40: While it does not prefer to fight, even one drop of the poison it secretes from barbs can be fatal. | CN40: While it does not prefer to fight, even one drop of the poison it secretes from barbs can be fatal. | CO40: While it does not prefer to fight, even one drop of the poison it secretes from barbs can be fatal. | CP40: While it does not prefer to fight, even one drop of the poison it secretes from barbs can be fatal. | CQ40: Although small, its venomous barbs render this Pokémon dangerous. The female has smaller horns. | CR40: Small and very docile, it protects itself with its small, poisonous horn when attacked. | CS40: Nidoran♀ has barbs that secrete a powerful poison. They are thought to have developed as protection for this small-bodied Pokémon. When enraged, it releases a horrible toxin from its horn. | CT40: Nidoran♀ has barbs that secrete a powerful poison. They are thought to have developed as protection for this small-bodied Pokémon. When enraged, it releases a horrible toxin from its horn. | CY40: A mild-mannered Pokémon that does not like to fight. Beware—its small horn secretes venom. | CZ40: A mild-mannered Pokémon that does not like to fight. Beware—its small horn secretes venom. | DA40: Females are more sensitive to smells than males. While foraging, they’ll use their whiskers to check wind direction and stay downwind of predators. | DB40: It uses its hard incisor teeth to crush and eat berries. The tip of a female Nidoran’s horn is a bit more rounded than the tip of a male’s horn. | DE40: While this Pokémon does not prefer to fight, even one drop of the venom it secretes from its barbs can be fatal. | DF40: While this Pokémon does not prefer to fight, even one drop of the venom it secretes from its barbs can be fatal. | DP40: Route 5 , 22 , Underground Path 5-6 , Safari Zone | DQ40: Route 5 , 22 , Underground Path 5-6 , Safari Zone | DR40: Route 2 , 9 , 10 , 22 , Safari Zone | DS40: Route 35 , 36 | DT40: Route 35 , 36 | DU40: Route 35 , National Park | DV40: Trade/migrate from another game | DW40: Trade/migrate from another game | DX40: Trade/migrate from another game | DY40: Route 3 , 5 , Underground Path 5-6 , Safari Zone | DZ40: Route 3 , Safari Zone | EA40: Route 201 | EB40: Route 201 | EC40: Route 201 | ED40: Route 35 , 36 | EE40: Route 35 , 36 | EF40: Trade/migrate from another game | EG40: White Forest | EH40: Trade/migrate from another game | EI40: Trade/migrate from another game | EJ40: Route 11 | EK40: Route 11 | EL40: Trade/migrate from another game | EM40: Trade/migrate from another game | EN40: Trade/migrate from another game | EO40: Trade/migrate from another game | EP40: Trade/migrate from another game | EQ40: Trade/migrate from another game | ER40: Route 9 , 10 , 22 , 23 | ES40: Route 9 , 10 , 22 , 23 | ET40: Giant's Bed , Old Cemetery | EU40: Giant's Bed , Old Cemetery | EX40: Route 201 , Grassland Cave , Swampy Cave , Dazzling Cave , Riverbank Cave , Still-Water Cavern , Sunlit Cavern , Stargleam Cavern , Bogsunk Cavern | EY40: Route 201 , Grassland Cave , Swampy Cave , Dazzling Cave , Riverbank Cave , Still-Water Cavern , Sunlit Cavern , Stargleam Cavern , Bogsunk Cavern | EZ40: Not available in this game | FA40: Location data not yet available | FB40: Location data not yet available | FE40: Location data not yet available
